/*      */ package com.ghintech.puntocom.process;
/*      */ 
/*      */ import java.io.PrintStream;
/*      */ import java.math.BigDecimal;
/*      */ import java.math.RoundingMode;
/*      */ import java.sql.Timestamp;
/*      */ import java.util.List;
/*      */ import java.util.logging.Level;
/*      */ import org.compiere.model.MAllocationHdr;
/*      */ import org.compiere.model.MAllocationLine;
/*      */ import org.compiere.model.MBankAccount;
/*      */ import org.compiere.model.MInvoice;
/*      */ import org.compiere.model.MOrder;
/*      */ import org.compiere.model.MPayment;
/*      */ import org.compiere.model.Query;
/*      */ import org.compiere.process.ProcessInfoParameter;
/*      */ import org.compiere.process.SvrProcess;
/*      */ import org.compiere.util.CLogger;
/*      */ import org.compiere.util.Env;
/*      */ 
/*      */ 
/*      */ 
/*      */ 
/*      */ 
/*      */ 
/*      */ 
/*      */ 
/*      */ 
/*      */ 
/*      */ 
/*      */ 
/*      */ 
/*      */ 
/*      */ 
/*      */ 
/*      */ 
/*      */ 
/*      */ 
/*      */ 
/*      */ 
/*      */ 
/*      */ 
/*      */ 
/*      */ 
/*      */ 
/*      */ 
/*      */ 
/*      */ 
/*      */ 
/*      */ 
/*      */ 
/*      */ 
/*      */ 
/*      */ 
/*      */ 
/*      */ public class ImportOrder
/*      */   extends SvrProcess
/*      */ {
/*   59 */   private int m_AD_Client_ID = 0;
/*      */   
/*   61 */   private int m_AD_Org_ID = 0;
/*      */   
/*   63 */   private boolean m_deleteOldImported = false;
/*      */   
/*   65 */   private String m_docAction = "PR";
/*      */   
/*      */ 
/*      */ 
/*   69 */   private Timestamp m_DateValue = null;
/*      */   
/*      */ 
/*      */ 
/*      */ 
/*      */   protected void prepare()
/*      */   {
/*   76 */     ProcessInfoParameter[] para = getParameter();
/*   77 */     for (int i = 0; i < para.length; i++)
/*      */     {
/*   79 */       String name = para[i].getParameterName();
/*   80 */       if (name.equals("AD_Client_ID")) {
/*   81 */         this.m_AD_Client_ID = ((BigDecimal)para[i].getParameter()).intValue();
/*   82 */       } else if (name.equals("AD_Org_ID")) {
/*   83 */         this.m_AD_Org_ID = ((BigDecimal)para[i].getParameter()).intValue();
/*   84 */       } else if (name.equals("DeleteOldImported")) {
/*   85 */         this.m_deleteOldImported = "Y".equals(para[i].getParameter());
/*   86 */       } else if (name.equals("DocAction")) {
/*   87 */         this.m_docAction = ((String)para[i].getParameter());
/*      */       } else
/*   89 */         this.log.log(Level.SEVERE, "Unknown Parameter: " + name);
/*      */     }
/*   91 */     if (this.m_DateValue == null) {
/*   92 */       this.m_DateValue = new Timestamp(System.currentTimeMillis());
/*      */     }
/*      */   }
/*      */   
/*      */   /* Error */
/*      */   protected String doIt()
/*      */     throws java.lang.Exception
/*      */   {
/*      */     // Byte code:
/*      */     //   0: aconst_null
/*      */     //   1: astore_1
/*      */     //   2: iconst_0
/*      */     //   3: istore_2
/*      */     //   4: new 81	java/lang/StringBuilder
/*      */     //   7: dup
/*      */     //   8: ldc 121
/*      */     //   10: invokespecial 85	java/lang/StringBuilder:<init>	(Ljava/lang/String;)V
/*      */     //   13: aload_0
/*      */     //   14: getfield 19	com/ghintech/puntocom/process/ImportOrder:m_AD_Client_ID	I
/*      */     //   17: invokevirtual 123	java/lang/StringBuilder:append	(I)Ljava/lang/StringBuilder;
/*      */     //   20: astore_3
/*      */     //   21: aload_0
/*      */     //   22: getfield 23	com/ghintech/puntocom/process/ImportOrder:m_deleteOldImported	Z
/*      */     //   25: ifeq +70 -> 95
/*      */     //   28: new 81	java/lang/StringBuilder
/*      */     //   31: dup
/*      */     //   32: ldc 126
/*      */     //   34: invokespecial 85	java/lang/StringBuilder:<init>	(Ljava/lang/String;)V
/*      */     //   37: ldc -128
/*      */     //   39: invokevirtual 88	java/lang/StringBuilder:append	(Ljava/lang/String;)Ljava/lang/StringBuilder;
/*      */     //   42: aload_3
/*      */     //   43: invokevirtual 130	java/lang/StringBuilder:append	(Ljava/lang/CharSequence;)Ljava/lang/StringBuilder;
/*      */     //   46: astore_1
/*      */     //   47: aload_1
/*      */     //   48: invokevirtual 92	java/lang/StringBuilder:toString	()Ljava/lang/String;
/*      */     //   51: aload_0
/*      */     //   52: invokevirtual 133	com/ghintech/puntocom/process/ImportOrder:get_TrxName	()Ljava/lang/String;
/*      */     //   55: invokestatic 136	org/compiere/util/DB:executeUpdate	(Ljava/lang/String;Ljava/lang/String;)I
/*      */     //   58: istore_2
/*      */     //   59: aload_0
/*      */     //   60: getfield 71	com/ghintech/puntocom/process/ImportOrder:log	Lorg/compiere/util/CLogger;
/*      */     //   63: getstatic 142	java/util/logging/Level:FINE	Ljava/util/logging/Level;
/*      */     //   66: invokevirtual 145	org/compiere/util/CLogger:isLoggable	(Ljava/util/logging/Level;)Z
/*      */     //   69: ifeq +26 -> 95
/*      */     //   72: aload_0
/*      */     //   73: getfield 71	com/ghintech/puntocom/process/ImportOrder:log	Lorg/compiere/util/CLogger;
/*      */     //   76: new 81	java/lang/StringBuilder
/*      */     //   79: dup
/*      */     //   80: ldc -107
/*      */     //   82: invokespecial 85	java/lang/StringBuilder:<init>	(Ljava/lang/String;)V
/*      */     //   85: iload_2
/*      */     //   86: invokevirtual 123	java/lang/StringBuilder:append	(I)Ljava/lang/StringBuilder;
/*      */     //   89: invokevirtual 92	java/lang/StringBuilder:toString	()Ljava/lang/String;
/*      */     //   92: invokevirtual 151	org/compiere/util/CLogger:fine	(Ljava/lang/String;)V
/*      */     //   95: new 81	java/lang/StringBuilder
/*      */     //   98: dup
/*      */     //   99: ldc -102
/*      */     //   101: invokespecial 85	java/lang/StringBuilder:<init>	(Ljava/lang/String;)V
/*      */     //   104: ldc -100
/*      */     //   106: invokevirtual 88	java/lang/StringBuilder:append	(Ljava/lang/String;)Ljava/lang/StringBuilder;
/*      */     //   109: aload_0
/*      */     //   110: getfield 19	com/ghintech/puntocom/process/ImportOrder:m_AD_Client_ID	I
/*      */     //   113: invokevirtual 123	java/lang/StringBuilder:append	(I)Ljava/lang/StringBuilder;
/*      */     //   116: ldc -98
/*      */     //   118: invokevirtual 88	java/lang/StringBuilder:append	(Ljava/lang/String;)Ljava/lang/StringBuilder;
/*      */     //   121: ldc -96
/*      */     //   123: invokevirtual 88	java/lang/StringBuilder:append	(Ljava/lang/String;)Ljava/lang/StringBuilder;
/*      */     //   126: aload_0
/*      */     //   127: getfield 21	com/ghintech/puntocom/process/ImportOrder:m_AD_Org_ID	I
/*      */     //   130: invokevirtual 123	java/lang/StringBuilder:append	(I)Ljava/lang/StringBuilder;
/*      */     //   133: ldc -98
/*      */     //   135: invokevirtual 88	java/lang/StringBuilder:append	(Ljava/lang/String;)Ljava/lang/StringBuilder;
/*      */     //   138: ldc -94
/*      */     //   140: invokevirtual 88	java/lang/StringBuilder:append	(Ljava/lang/String;)Ljava/lang/StringBuilder;
/*      */     //   143: ldc -92
/*      */     //   145: invokevirtual 88	java/lang/StringBuilder:append	(Ljava/lang/String;)Ljava/lang/StringBuilder;
/*      */     //   148: ldc -90
/*      */     //   150: invokevirtual 88	java/lang/StringBuilder:append	(Ljava/lang/String;)Ljava/lang/StringBuilder;
/*      */     //   153: ldc -88
/*      */     //   155: invokevirtual 88	java/lang/StringBuilder:append	(Ljava/lang/String;)Ljava/lang/StringBuilder;
/*      */     //   158: ldc -86
/*      */     //   160: invokevirtual 88	java/lang/StringBuilder:append	(Ljava/lang/String;)Ljava/lang/StringBuilder;
/*      */     //   163: ldc -84
/*      */     //   165: invokevirtual 88	java/lang/StringBuilder:append	(Ljava/lang/String;)Ljava/lang/StringBuilder;
/*      */     //   168: ldc -82
/*      */     //   170: invokevirtual 88	java/lang/StringBuilder:append	(Ljava/lang/String;)Ljava/lang/StringBuilder;
/*      */     //   173: ldc -80
/*      */     //   175: invokevirtual 88	java/lang/StringBuilder:append	(Ljava/lang/String;)Ljava/lang/StringBuilder;
/*      */     //   178: astore_1
/*      */     //   179: aload_1
/*      */     //   180: invokevirtual 92	java/lang/StringBuilder:toString	()Ljava/lang/String;
/*      */     //   183: aload_0
/*      */     //   184: invokevirtual 133	com/ghintech/puntocom/process/ImportOrder:get_TrxName	()Ljava/lang/String;
/*      */     //   187: invokestatic 136	org/compiere/util/DB:executeUpdate	(Ljava/lang/String;Ljava/lang/String;)I
/*      */     //   190: istore_2
/*      */     //   191: aload_0
/*      */     //   192: getfield 71	com/ghintech/puntocom/process/ImportOrder:log	Lorg/compiere/util/CLogger;
/*      */     //   195: getstatic 178	java/util/logging/Level:INFO	Ljava/util/logging/Level;
/*      */     //   198: invokevirtual 145	org/compiere/util/CLogger:isLoggable	(Ljava/util/logging/Level;)Z
/*      */     //   201: ifeq +26 -> 227
/*      */     //   204: aload_0
/*      */     //   205: getfield 71	com/ghintech/puntocom/process/ImportOrder:log	Lorg/compiere/util/CLogger;
/*      */     //   208: new 81	java/lang/StringBuilder
/*      */     //   211: dup
/*      */     //   212: ldc -75
/*      */     //   214: invokespecial 85	java/lang/StringBuilder:<init>	(Ljava/lang/String;)V
/*      */     //   217: iload_2
/*      */     //   218: invokevirtual 123	java/lang/StringBuilder:append	(I)Ljava/lang/StringBuilder;
/*      */     //   221: invokevirtual 92	java/lang/StringBuilder:toString	()Ljava/lang/String;
/*      */     //   224: invokevirtual 183	org/compiere/util/CLogger:info	(Ljava/lang/String;)V
/*      */     //   227: new 81	java/lang/StringBuilder
/*      */     //   230: dup
/*      */     //   231: ldc -70
/*      */     //   233: invokespecial 85	java/lang/StringBuilder:<init>	(Ljava/lang/String;)V
/*      */     //   236: ldc -68
/*      */     //   238: invokevirtual 88	java/lang/StringBuilder:append	(Ljava/lang/String;)Ljava/lang/StringBuilder;
/*      */     //   241: ldc -66
/*      */     //   243: invokevirtual 88	java/lang/StringBuilder:append	(Ljava/lang/String;)Ljava/lang/StringBuilder;
/*      */     //   246: ldc -64
/*      */     //   248: invokevirtual 88	java/lang/StringBuilder:append	(Ljava/lang/String;)Ljava/lang/StringBuilder;
/*      */     //   251: aload_3
/*      */     //   252: invokevirtual 130	java/lang/StringBuilder:append	(Ljava/lang/CharSequence;)Ljava/lang/StringBuilder;
/*      */     //   255: astore_1
/*      */     //   256: aload_1
/*      */     //   257: invokevirtual 92	java/lang/StringBuilder:toString	()Ljava/lang/String;
/*      */     //   260: aload_0
/*      */     //   261: invokevirtual 133	com/ghintech/puntocom/process/ImportOrder:get_TrxName	()Ljava/lang/String;
/*      */     //   264: invokestatic 136	org/compiere/util/DB:executeUpdate	(Ljava/lang/String;Ljava/lang/String;)I
/*      */     //   267: istore_2
/*      */     //   268: iload_2
/*      */     //   269: ifeq +26 -> 295
/*      */     //   272: aload_0
/*      */     //   273: getfield 71	com/ghintech/puntocom/process/ImportOrder:log	Lorg/compiere/util/CLogger;
/*      */     //   276: new 81	java/lang/StringBuilder
/*      */     //   279: dup
/*      */     //   280: ldc -62
/*      */     //   282: invokespecial 85	java/lang/StringBuilder:<init>	(Ljava/lang/String;)V
/*      */     //   285: iload_2
/*      */     //   286: invokevirtual 123	java/lang/StringBuilder:append	(I)Ljava/lang/StringBuilder;
/*      */     //   289: invokevirtual 92	java/lang/StringBuilder:toString	()Ljava/lang/String;
/*      */     //   292: invokevirtual 151	org/compiere/util/CLogger:fine	(Ljava/lang/String;)V
/*      */     //   295: new 81	java/lang/StringBuilder
/*      */     //   298: dup
/*      */     //   299: ldc -70
/*      */     //   301: invokespecial 85	java/lang/StringBuilder:<init>	(Ljava/lang/String;)V
/*      */     //   304: ldc -60
/*      */     //   306: invokevirtual 88	java/lang/StringBuilder:append	(Ljava/lang/String;)Ljava/lang/StringBuilder;
/*      */     //   309: ldc -58
/*      */     //   311: invokevirtual 88	java/lang/StringBuilder:append	(Ljava/lang/String;)Ljava/lang/StringBuilder;
/*      */     //   314: ldc -56
/*      */     //   316: invokevirtual 88	java/lang/StringBuilder:append	(Ljava/lang/String;)Ljava/lang/StringBuilder;
/*      */     //   319: ldc -54
/*      */     //   321: invokevirtual 88	java/lang/StringBuilder:append	(Ljava/lang/String;)Ljava/lang/StringBuilder;
/*      */     //   324: aload_3
/*      */     //   325: invokevirtual 130	java/lang/StringBuilder:append	(Ljava/lang/CharSequence;)Ljava/lang/StringBuilder;
/*      */     //   328: astore_1
/*      */     //   329: aload_1
/*      */     //   330: invokevirtual 92	java/lang/StringBuilder:toString	()Ljava/lang/String;
/*      */     //   333: aload_0
/*      */     //   334: invokevirtual 133	com/ghintech/puntocom/process/ImportOrder:get_TrxName	()Ljava/lang/String;
/*      */     //   337: invokestatic 136	org/compiere/util/DB:executeUpdate	(Ljava/lang/String;Ljava/lang/String;)I
/*      */     //   340: istore_2
/*      */     //   341: iload_2
/*      */     //   342: ifeq +26 -> 368
/*      */     //   345: aload_0
/*      */     //   346: getfield 71	com/ghintech/puntocom/process/ImportOrder:log	Lorg/compiere/util/CLogger;
/*      */     //   349: new 81	java/lang/StringBuilder
/*      */     //   352: dup
/*      */     //   353: ldc -52
/*      */     //   355: invokespecial 85	java/lang/StringBuilder:<init>	(Ljava/lang/String;)V
/*      */     //   358: iload_2
/*      */     //   359: invokevirtual 123	java/lang/StringBuilder:append	(I)Ljava/lang/StringBuilder;
/*      */     //   362: invokevirtual 92	java/lang/StringBuilder:toString	()Ljava/lang/String;
/*      */     //   365: invokevirtual 206	org/compiere/util/CLogger:warning	(Ljava/lang/String;)V
/*      */     //   368: new 81	java/lang/StringBuilder
/*      */     //   371: dup
/*      */     //   372: ldc -70
/*      */     //   374: invokespecial 85	java/lang/StringBuilder:<init>	(Ljava/lang/String;)V
/*      */     //   377: ldc -47
/*      */     //   379: invokevirtual 88	java/lang/StringBuilder:append	(Ljava/lang/String;)Ljava/lang/StringBuilder;
/*      */     //   382: ldc -45
/*      */     //   384: invokevirtual 88	java/lang/StringBuilder:append	(Ljava/lang/String;)Ljava/lang/StringBuilder;
/*      */     //   387: ldc -43
/*      */     //   389: invokevirtual 88	java/lang/StringBuilder:append	(Ljava/lang/String;)Ljava/lang/StringBuilder;
/*      */     //   392: aload_3
/*      */     //   393: invokevirtual 130	java/lang/StringBuilder:append	(Ljava/lang/CharSequence;)Ljava/lang/StringBuilder;
/*      */     //   396: astore_1
/*      */     //   397: aload_1
/*      */     //   398: invokevirtual 92	java/lang/StringBuilder:toString	()Ljava/lang/String;
/*      */     //   401: aload_0
/*      */     //   402: invokevirtual 133	com/ghintech/puntocom/process/ImportOrder:get_TrxName	()Ljava/lang/String;
/*      */     //   405: invokestatic 136	org/compiere/util/DB:executeUpdate	(Ljava/lang/String;Ljava/lang/String;)I
/*      */     //   408: istore_2
/*      */     //   409: aload_0
/*      */     //   410: getfield 71	com/ghintech/puntocom/process/ImportOrder:log	Lorg/compiere/util/CLogger;
/*      */     //   413: getstatic 142	java/util/logging/Level:FINE	Ljava/util/logging/Level;
/*      */     //   416: invokevirtual 145	org/compiere/util/CLogger:isLoggable	(Ljava/util/logging/Level;)Z
/*      */     //   419: ifeq +26 -> 445
/*      */     //   422: aload_0
/*      */     //   423: getfield 71	com/ghintech/puntocom/process/ImportOrder:log	Lorg/compiere/util/CLogger;
/*      */     //   426: new 81	java/lang/StringBuilder
/*      */     //   429: dup
/*      */     //   430: ldc -41
/*      */     //   432: invokespecial 85	java/lang/StringBuilder:<init>	(Ljava/lang/String;)V
/*      */     //   435: iload_2
/*      */     //   436: invokevirtual 123	java/lang/StringBuilder:append	(I)Ljava/lang/StringBuilder;
/*      */     //   439: invokevirtual 92	java/lang/StringBuilder:toString	()Ljava/lang/String;
/*      */     //   442: invokevirtual 151	org/compiere/util/CLogger:fine	(Ljava/lang/String;)V
/*      */     //   445: new 81	java/lang/StringBuilder
/*      */     //   448: dup
/*      */     //   449: ldc -70
/*      */     //   451: invokespecial 85	java/lang/StringBuilder:<init>	(Ljava/lang/String;)V
/*      */     //   454: ldc -47
/*      */     //   456: invokevirtual 88	java/lang/StringBuilder:append	(Ljava/lang/String;)Ljava/lang/StringBuilder;
/*      */     //   459: ldc -39
/*      */     //   461: invokevirtual 88	java/lang/StringBuilder:append	(Ljava/lang/String;)Ljava/lang/StringBuilder;
/*      */     //   464: ldc -37
/*      */     //   466: invokevirtual 88	java/lang/StringBuilder:append	(Ljava/lang/String;)Ljava/lang/StringBuilder;
/*      */     //   469: aload_3
/*      */     //   470: invokevirtual 130	java/lang/StringBuilder:append	(Ljava/lang/CharSequence;)Ljava/lang/StringBuilder;
/*      */     //   473: astore_1
/*      */     //   474: aload_1
/*      */     //   475: invokevirtual 92	java/lang/StringBuilder:toString	()Ljava/lang/String;
/*      */     //   478: aload_0
/*      */     //   479: invokevirtual 133	com/ghintech/puntocom/process/ImportOrder:get_TrxName	()Ljava/lang/String;
/*      */     //   482: invokestatic 136	org/compiere/util/DB:executeUpdate	(Ljava/lang/String;Ljava/lang/String;)I
/*      */     //   485: istore_2
/*      */     //   486: aload_0
/*      */     //   487: getfield 71	com/ghintech/puntocom/process/ImportOrder:log	Lorg/compiere/util/CLogger;
/*      */     //   490: getstatic 142	java/util/logging/Level:FINE	Ljava/util/logging/Level;
/*      */     //   493: invokevirtual 145	org/compiere/util/CLogger:isLoggable	(Ljava/util/logging/Level;)Z
/*      */     //   496: ifeq +26 -> 522
/*      */     //   499: aload_0
/*      */     //   500: getfield 71	com/ghintech/puntocom/process/ImportOrder:log	Lorg/compiere/util/CLogger;
/*      */     //   503: new 81	java/lang/StringBuilder
/*      */     //   506: dup
/*      */     //   507: ldc -35
/*      */     //   509: invokespecial 85	java/lang/StringBuilder:<init>	(Ljava/lang/String;)V
/*      */     //   512: iload_2
/*      */     //   513: invokevirtual 123	java/lang/StringBuilder:append	(I)Ljava/lang/StringBuilder;
/*      */     //   516: invokevirtual 92	java/lang/StringBuilder:toString	()Ljava/lang/String;
/*      */     //   519: invokevirtual 151	org/compiere/util/CLogger:fine	(Ljava/lang/String;)V
/*      */     //   522: new 81	java/lang/StringBuilder
/*      */     //   525: dup
/*      */     //   526: ldc -70
/*      */     //   528: invokespecial 85	java/lang/StringBuilder:<init>	(Ljava/lang/String;)V
/*      */     //   531: ldc -47
/*      */     //   533: invokevirtual 88	java/lang/StringBuilder:append	(Ljava/lang/String;)Ljava/lang/StringBuilder;
/*      */     //   536: ldc -33
/*      */     //   538: invokevirtual 88	java/lang/StringBuilder:append	(Ljava/lang/String;)Ljava/lang/StringBuilder;
/*      */     //   541: ldc -31
/*      */     //   543: invokevirtual 88	java/lang/StringBuilder:append	(Ljava/lang/String;)Ljava/lang/StringBuilder;
/*      */     //   546: aload_3
/*      */     //   547: invokevirtual 130	java/lang/StringBuilder:append	(Ljava/lang/CharSequence;)Ljava/lang/StringBuilder;
/*      */     //   550: astore_1
/*      */     //   551: aload_1
/*      */     //   552: invokevirtual 92	java/lang/StringBuilder:toString	()Ljava/lang/String;
/*      */     //   555: aload_0
/*      */     //   556: invokevirtual 133	com/ghintech/puntocom/process/ImportOrder:get_TrxName	()Ljava/lang/String;
/*      */     //   559: invokestatic 136	org/compiere/util/DB:executeUpdate	(Ljava/lang/String;Ljava/lang/String;)I
/*      */     //   562: istore_2
/*      */     //   563: aload_0
/*      */     //   564: getfield 71	com/ghintech/puntocom/process/ImportOrder:log	Lorg/compiere/util/CLogger;
/*      */     //   567: getstatic 142	java/util/logging/Level:FINE	Ljava/util/logging/Level;
/*      */     //   570: invokevirtual 145	org/compiere/util/CLogger:isLoggable	(Ljava/util/logging/Level;)Z
/*      */     //   573: ifeq +26 -> 599
/*      */     //   576: aload_0
/*      */     //   577: getfield 71	com/ghintech/puntocom/process/ImportOrder:log	Lorg/compiere/util/CLogger;
/*      */     //   580: new 81	java/lang/StringBuilder
/*      */     //   583: dup
/*      */     //   584: ldc -29
/*      */     //   586: invokespecial 85	java/lang/StringBuilder:<init>	(Ljava/lang/String;)V
/*      */     //   589: iload_2
/*      */     //   590: invokevirtual 123	java/lang/StringBuilder:append	(I)Ljava/lang/StringBuilder;
/*      */     //   593: invokevirtual 92	java/lang/StringBuilder:toString	()Ljava/lang/String;
/*      */     //   596: invokevirtual 151	org/compiere/util/CLogger:fine	(Ljava/lang/String;)V
/*      */     //   599: new 81	java/lang/StringBuilder
/*      */     //   602: dup
/*      */     //   603: ldc -102
/*      */     //   605: invokespecial 85	java/lang/StringBuilder:<init>	(Ljava/lang/String;)V
/*      */     //   608: ldc -27
/*      */     //   610: invokevirtual 88	java/lang/StringBuilder:append	(Ljava/lang/String;)Ljava/lang/StringBuilder;
/*      */     //   613: ldc -25
/*      */     //   615: invokevirtual 88	java/lang/StringBuilder:append	(Ljava/lang/String;)Ljava/lang/StringBuilder;
/*      */     //   618: ldc -54
/*      */     //   620: invokevirtual 88	java/lang/StringBuilder:append	(Ljava/lang/String;)Ljava/lang/StringBuilder;
/*      */     //   623: aload_3
/*      */     //   624: invokevirtual 130	java/lang/StringBuilder:append	(Ljava/lang/CharSequence;)Ljava/lang/StringBuilder;
/*      */     //   627: astore_1
/*      */     //   628: aload_1
/*      */     //   629: invokevirtual 92	java/lang/StringBuilder:toString	()Ljava/lang/String;
/*      */     //   632: aload_0
/*      */     //   633: invokevirtual 133	com/ghintech/puntocom/process/ImportOrder:get_TrxName	()Ljava/lang/String;
/*      */     //   636: invokestatic 136	org/compiere/util/DB:executeUpdate	(Ljava/lang/String;Ljava/lang/String;)I
/*      */     //   639: istore_2
/*      */     //   640: iload_2
/*      */     //   641: ifeq +26 -> 667
/*      */     //   644: aload_0
/*      */     //   645: getfield 71	com/ghintech/puntocom/process/ImportOrder:log	Lorg/compiere/util/CLogger;
/*      */     //   648: new 81	java/lang/StringBuilder
/*      */     //   651: dup
/*      */     //   652: ldc -23
/*      */     //   654: invokespecial 85	java/lang/StringBuilder:<init>	(Ljava/lang/String;)V
/*      */     //   657: iload_2
/*      */     //   658: invokevirtual 123	java/lang/StringBuilder:append	(I)Ljava/lang/StringBuilder;
/*      */     //   661: invokevirtual 92	java/lang/StringBuilder:toString	()Ljava/lang/String;
/*      */     //   664: invokevirtual 206	org/compiere/util/CLogger:warning	(Ljava/lang/String;)V
/*      */     //   667: new 81	java/lang/StringBuilder
/*      */     //   670: dup
/*      */     //   671: ldc -70
/*      */     //   673: invokespecial 85	java/lang/StringBuilder:<init>	(Ljava/lang/String;)V
/*      */     //   676: ldc -21
/*      */     //   678: invokevirtual 88	java/lang/StringBuilder:append	(Ljava/lang/String;)Ljava/lang/StringBuilder;
/*      */     //   681: ldc -45
/*      */     //   683: invokevirtual 88	java/lang/StringBuilder:append	(Ljava/lang/String;)Ljava/lang/StringBuilder;
/*      */     //   686: ldc -19
/*      */     //   688: invokevirtual 88	java/lang/StringBuilder:append	(Ljava/lang/String;)Ljava/lang/StringBuilder;
/*      */     //   691: aload_3
/*      */     //   692: invokevirtual 130	java/lang/StringBuilder:append	(Ljava/lang/CharSequence;)Ljava/lang/StringBuilder;
/*      */     //   695: astore_1
/*      */     //   696: aload_1
/*      */     //   697: invokevirtual 92	java/lang/StringBuilder:toString	()Ljava/lang/String;
/*      */     //   700: aload_0
/*      */     //   701: invokevirtual 133	com/ghintech/puntocom/process/ImportOrder:get_TrxName	()Ljava/lang/String;
/*      */     //   704: invokestatic 136	org/compiere/util/DB:executeUpdate	(Ljava/lang/String;Ljava/lang/String;)I
/*      */     //   707: istore_2
/*      */     //   708: aload_0
/*      */     //   709: getfield 71	com/ghintech/puntocom/process/ImportOrder:log	Lorg/compiere/util/CLogger;
/*      */     //   712: getstatic 142	java/util/logging/Level:FINE	Ljava/util/logging/Level;
/*      */     //   715: invokevirtual 145	org/compiere/util/CLogger:isLoggable	(Ljava/util/logging/Level;)Z
/*      */     //   718: ifeq +26 -> 744
/*      */     //   721: aload_0
/*      */     //   722: getfield 71	com/ghintech/puntocom/process/ImportOrder:log	Lorg/compiere/util/CLogger;
/*      */     //   725: new 81	java/lang/StringBuilder
/*      */     //   728: dup
/*      */     //   729: ldc -17
/*      */     //   731: invokespecial 85	java/lang/StringBuilder:<init>	(Ljava/lang/String;)V
/*      */     //   734: iload_2
/*      */     //   735: invokevirtual 123	java/lang/StringBuilder:append	(I)Ljava/lang/StringBuilder;
/*      */     //   738: invokevirtual 92	java/lang/StringBuilder:toString	()Ljava/lang/String;
/*      */     //   741: invokevirtual 151	org/compiere/util/CLogger:fine	(Ljava/lang/String;)V
/*      */     //   744: new 81	java/lang/StringBuilder
/*      */     //   747: dup
/*      */     //   748: ldc -70
/*      */     //   750: invokespecial 85	java/lang/StringBuilder:<init>	(Ljava/lang/String;)V
/*      */     //   753: ldc -21
/*      */     //   755: invokevirtual 88	java/lang/StringBuilder:append	(Ljava/lang/String;)Ljava/lang/StringBuilder;
/*      */     //   758: ldc -39
/*      */     //   760: invokevirtual 88	java/lang/StringBuilder:append	(Ljava/lang/String;)Ljava/lang/StringBuilder;
/*      */     //   763: ldc -15
/*      */     //   765: invokevirtual 88	java/lang/StringBuilder:append	(Ljava/lang/String;)Ljava/lang/StringBuilder;
/*      */     //   768: aload_3
/*      */     //   769: invokevirtual 130	java/lang/StringBuilder:append	(Ljava/lang/CharSequence;)Ljava/lang/StringBuilder;
/*      */     //   772: astore_1
/*      */     //   773: aload_1
/*      */     //   774: invokevirtual 92	java/lang/StringBuilder:toString	()Ljava/lang/String;
/*      */     //   777: aload_0
/*      */     //   778: invokevirtual 133	com/ghintech/puntocom/process/ImportOrder:get_TrxName	()Ljava/lang/String;
/*      */     //   781: invokestatic 136	org/compiere/util/DB:executeUpdate	(Ljava/lang/String;Ljava/lang/String;)I
/*      */     //   784: istore_2
/*      */     //   785: aload_0
/*      */     //   786: getfield 71	com/ghintech/puntocom/process/ImportOrder:log	Lorg/compiere/util/CLogger;
/*      */     //   789: getstatic 142	java/util/logging/Level:FINE	Ljava/util/logging/Level;
/*      */     //   792: invokevirtual 145	org/compiere/util/CLogger:isLoggable	(Ljava/util/logging/Level;)Z
/*      */     //   795: ifeq +26 -> 821
/*      */     //   798: aload_0
/*      */     //   799: getfield 71	com/ghintech/puntocom/process/ImportOrder:log	Lorg/compiere/util/CLogger;
/*      */     //   802: new 81	java/lang/StringBuilder
/*      */     //   805: dup
/*      */     //   806: ldc -13
/*      */     //   808: invokespecial 85	java/lang/StringBuilder:<init>	(Ljava/lang/String;)V
/*      */     //   811: iload_2
/*      */     //   812: invokevirtual 123	java/lang/StringBuilder:append	(I)Ljava/lang/StringBuilder;
/*      */     //   815: invokevirtual 92	java/lang/StringBuilder:toString	()Ljava/lang/String;
/*      */     //   818: invokevirtual 151	org/compiere/util/CLogger:fine	(Ljava/lang/String;)V
/*      */     //   821: new 81	java/lang/StringBuilder
/*      */     //   824: dup
/*      */     //   825: ldc -70
/*      */     //   827: invokespecial 85	java/lang/StringBuilder:<init>	(Ljava/lang/String;)V
/*      */     //   830: ldc -21
/*      */     //   832: invokevirtual 88	java/lang/StringBuilder:append	(Ljava/lang/String;)Ljava/lang/StringBuilder;
/*      */     //   835: ldc -11
/*      */     //   837: invokevirtual 88	java/lang/StringBuilder:append	(Ljava/lang/String;)Ljava/lang/StringBuilder;
/*      */     //   840: ldc -9
/*      */     //   842: invokevirtual 88	java/lang/StringBuilder:append	(Ljava/lang/String;)Ljava/lang/StringBuilder;
/*      */     //   845: aload_3
/*      */     //   846: invokevirtual 130	java/lang/StringBuilder:append	(Ljava/lang/CharSequence;)Ljava/lang/StringBuilder;
/*      */     //   849: astore_1
/*      */     //   850: aload_1
/*      */     //   851: invokevirtual 92	java/lang/StringBuilder:toString	()Ljava/lang/String;
/*      */     //   854: aload_0
/*      */     //   855: invokevirtual 133	com/ghintech/puntocom/process/ImportOrder:get_TrxName	()Ljava/lang/String;
/*      */     //   858: invokestatic 136	org/compiere/util/DB:executeUpdate	(Ljava/lang/String;Ljava/lang/String;)I
/*      */     //   861: istore_2
/*      */     //   862: aload_0
/*      */     //   863: getfield 71	com/ghintech/puntocom/process/ImportOrder:log	Lorg/compiere/util/CLogger;
/*      */     //   866: getstatic 142	java/util/logging/Level:FINE	Ljava/util/logging/Level;
/*      */     //   869: invokevirtual 145	org/compiere/util/CLogger:isLoggable	(Ljava/util/logging/Level;)Z
/*      */     //   872: ifeq +26 -> 898
/*      */     //   875: aload_0
/*      */     //   876: getfield 71	com/ghintech/puntocom/process/ImportOrder:log	Lorg/compiere/util/CLogger;
/*      */     //   879: new 81	java/lang/StringBuilder
/*      */     //   882: dup
/*      */     //   883: ldc -7
/*      */     //   885: invokespecial 85	java/lang/StringBuilder:<init>	(Ljava/lang/String;)V
/*      */     //   888: iload_2
/*      */     //   889: invokevirtual 123	java/lang/StringBuilder:append	(I)Ljava/lang/StringBuilder;
/*      */     //   892: invokevirtual 92	java/lang/StringBuilder:toString	()Ljava/lang/String;
/*      */     //   895: invokevirtual 151	org/compiere/util/CLogger:fine	(Ljava/lang/String;)V
/*      */     //   898: new 81	java/lang/StringBuilder
/*      */     //   901: dup
/*      */     //   902: ldc -102
/*      */     //   904: invokespecial 85	java/lang/StringBuilder:<init>	(Ljava/lang/String;)V
/*      */     //   907: ldc -5
/*      */     //   909: invokevirtual 88	java/lang/StringBuilder:append	(Ljava/lang/String;)Ljava/lang/StringBuilder;
/*      */     //   912: ldc -3
/*      */     //   914: invokevirtual 88	java/lang/StringBuilder:append	(Ljava/lang/String;)Ljava/lang/StringBuilder;
/*      */     //   917: ldc -54
/*      */     //   919: invokevirtual 88	java/lang/StringBuilder:append	(Ljava/lang/String;)Ljava/lang/StringBuilder;
/*      */     //   922: aload_3
/*      */     //   923: invokevirtual 130	java/lang/StringBuilder:append	(Ljava/lang/CharSequence;)Ljava/lang/StringBuilder;
/*      */     //   926: astore_1
/*      */     //   927: aload_1
/*      */     //   928: invokevirtual 92	java/lang/StringBuilder:toString	()Ljava/lang/String;
/*      */     //   931: aload_0
/*      */     //   932: invokevirtual 133	com/ghintech/puntocom/process/ImportOrder:get_TrxName	()Ljava/lang/String;
/*      */     //   935: invokestatic 136	org/compiere/util/DB:executeUpdate	(Ljava/lang/String;Ljava/lang/String;)I
/*      */     //   938: istore_2
/*      */     //   939: iload_2
/*      */     //   940: ifeq +26 -> 966
/*      */     //   943: aload_0
/*      */     //   944: getfield 71	com/ghintech/puntocom/process/ImportOrder:log	Lorg/compiere/util/CLogger;
/*      */     //   947: new 81	java/lang/StringBuilder
/*      */     //   950: dup
/*      */     //   951: ldc -1
/*      */     //   953: invokespecial 85	java/lang/StringBuilder:<init>	(Ljava/lang/String;)V
/*      */     //   956: iload_2
/*      */     //   957: invokevirtual 123	java/lang/StringBuilder:append	(I)Ljava/lang/StringBuilder;
/*      */     //   960: invokevirtual 92	java/lang/StringBuilder:toString	()Ljava/lang/String;
/*      */     //   963: invokevirtual 206	org/compiere/util/CLogger:warning	(Ljava/lang/String;)V
/*      */     //   966: new 81	java/lang/StringBuilder
/*      */     //   969: dup
/*      */     //   970: ldc_w 257
/*      */     //   973: invokespecial 85	java/lang/StringBuilder:<init>	(Ljava/lang/String;)V
/*      */     //   976: ldc_w 259
/*      */     //   979: invokevirtual 88	java/lang/StringBuilder:append	(Ljava/lang/String;)Ljava/lang/StringBuilder;
/*      */     //   982: ldc_w 261
/*      */     //   985: invokevirtual 88	java/lang/StringBuilder:append	(Ljava/lang/String;)Ljava/lang/StringBuilder;
/*      */     //   988: ldc -54
/*      */     //   990: invokevirtual 88	java/lang/StringBuilder:append	(Ljava/lang/String;)Ljava/lang/StringBuilder;
/*      */     //   993: aload_3
/*      */     //   994: invokevirtual 130	java/lang/StringBuilder:append	(Ljava/lang/CharSequence;)Ljava/lang/StringBuilder;
/*      */     //   997: astore_1
/*      */     //   998: aload_1
/*      */     //   999: invokevirtual 92	java/lang/StringBuilder:toString	()Ljava/lang/String;
/*      */     //   1002: aload_0
/*      */     //   1003: invokevirtual 133	com/ghintech/puntocom/process/ImportOrder:get_TrxName	()Ljava/lang/String;
/*      */     //   1006: invokestatic 136	org/compiere/util/DB:executeUpdate	(Ljava/lang/String;Ljava/lang/String;)I
/*      */     //   1009: istore_2
/*      */     //   1010: aload_0
/*      */     //   1011: getfield 71	com/ghintech/puntocom/process/ImportOrder:log	Lorg/compiere/util/CLogger;
/*      */     //   1014: getstatic 142	java/util/logging/Level:FINE	Ljava/util/logging/Level;
/*      */     //   1017: invokevirtual 145	org/compiere/util/CLogger:isLoggable	(Ljava/util/logging/Level;)Z
/*      */     //   1020: ifeq +27 -> 1047
/*      */     //   1023: aload_0
/*      */     //   1024: getfield 71	com/ghintech/puntocom/process/ImportOrder:log	Lorg/compiere/util/CLogger;
/*      */     //   1027: new 81	java/lang/StringBuilder
/*      */     //   1030: dup
/*      */     //   1031: ldc_w 263
/*      */     //   1034: invokespecial 85	java/lang/StringBuilder:<init>	(Ljava/lang/String;)V
/*      */     //   1037: iload_2
/*      */     //   1038: invokevirtual 123	java/lang/StringBuilder:append	(I)Ljava/lang/StringBuilder;
/*      */     //   1041: invokevirtual 92	java/lang/StringBuilder:toString	()Ljava/lang/String;
/*      */     //   1044: invokevirtual 151	org/compiere/util/CLogger:fine	(Ljava/lang/String;)V
/*      */     //   1047: new 81	java/lang/StringBuilder
/*      */     //   1050: dup
/*      */     //   1051: ldc_w 265
/*      */     //   1054: invokespecial 85	java/lang/StringBuilder:<init>	(Ljava/lang/String;)V
/*      */     //   1057: ldc_w 267
/*      */     //   1060: invokevirtual 88	java/lang/StringBuilder:append	(Ljava/lang/String;)Ljava/lang/StringBuilder;
/*      */     //   1063: ldc_w 261
/*      */     //   1066: invokevirtual 88	java/lang/StringBuilder:append	(Ljava/lang/String;)Ljava/lang/StringBuilder;
/*      */     //   1069: ldc -54
/*      */     //   1071: invokevirtual 88	java/lang/StringBuilder:append	(Ljava/lang/String;)Ljava/lang/StringBuilder;
/*      */     //   1074: aload_3
/*      */     //   1075: invokevirtual 130	java/lang/StringBuilder:append	(Ljava/lang/CharSequence;)Ljava/lang/StringBuilder;
/*      */     //   1078: astore_1
/*      */     //   1079: aload_1
/*      */     //   1080: invokevirtual 92	java/lang/StringBuilder:toString	()Ljava/lang/String;
/*      */     //   1083: aload_0
/*      */     //   1084: invokevirtual 133	com/ghintech/puntocom/process/ImportOrder:get_TrxName	()Ljava/lang/String;
/*      */     //   1087: invokestatic 136	org/compiere/util/DB:executeUpdate	(Ljava/lang/String;Ljava/lang/String;)I
/*      */     //   1090: istore_2
/*      */     //   1091: aload_0
/*      */     //   1092: getfield 71	com/ghintech/puntocom/process/ImportOrder:log	Lorg/compiere/util/CLogger;
/*      */     //   1095: getstatic 142	java/util/logging/Level:FINE	Ljava/util/logging/Level;
/*      */     //   1098: invokevirtual 145	org/compiere/util/CLogger:isLoggable	(Ljava/util/logging/Level;)Z
/*      */     //   1101: ifeq +27 -> 1128
/*      */     //   1104: aload_0
/*      */     //   1105: getfield 71	com/ghintech/puntocom/process/ImportOrder:log	Lorg/compiere/util/CLogger;
/*      */     //   1108: new 81	java/lang/StringBuilder
/*      */     //   1111: dup
/*      */     //   1112: ldc_w 269
/*      */     //   1115: invokespecial 85	java/lang/StringBuilder:<init>	(Ljava/lang/String;)V
/*      */     //   1118: iload_2
/*      */     //   1119: invokevirtual 123	java/lang/StringBuilder:append	(I)Ljava/lang/StringBuilder;
/*      */     //   1122: invokevirtual 92	java/lang/StringBuilder:toString	()Ljava/lang/String;
/*      */     //   1125: invokevirtual 151	org/compiere/util/CLogger:fine	(Ljava/lang/String;)V
/*      */     //   1128: new 81	java/lang/StringBuilder
/*      */     //   1131: dup
/*      */     //   1132: ldc -70
/*      */     //   1134: invokespecial 85	java/lang/StringBuilder:<init>	(Ljava/lang/String;)V
/*      */     //   1137: ldc_w 271
/*      */     //   1140: invokevirtual 88	java/lang/StringBuilder:append	(Ljava/lang/String;)Ljava/lang/StringBuilder;
/*      */     //   1143: ldc_w 273
/*      */     //   1146: invokevirtual 88	java/lang/StringBuilder:append	(Ljava/lang/String;)Ljava/lang/StringBuilder;
/*      */     //   1149: ldc_w 275
/*      */     //   1152: invokevirtual 88	java/lang/StringBuilder:append	(Ljava/lang/String;)Ljava/lang/StringBuilder;
/*      */     //   1155: aload_3
/*      */     //   1156: invokevirtual 130	java/lang/StringBuilder:append	(Ljava/lang/CharSequence;)Ljava/lang/StringBuilder;
/*      */     //   1159: astore_1
/*      */     //   1160: aload_1
/*      */     //   1161: invokevirtual 92	java/lang/StringBuilder:toString	()Ljava/lang/String;
/*      */     //   1164: aload_0
/*      */     //   1165: invokevirtual 133	com/ghintech/puntocom/process/ImportOrder:get_TrxName	()Ljava/lang/String;
/*      */     //   1168: invokestatic 136	org/compiere/util/DB:executeUpdate	(Ljava/lang/String;Ljava/lang/String;)I
/*      */     //   1171: istore_2
/*      */     //   1172: aload_0
/*      */     //   1173: getfield 71	com/ghintech/puntocom/process/ImportOrder:log	Lorg/compiere/util/CLogger;
/*      */     //   1176: getstatic 142	java/util/logging/Level:FINE	Ljava/util/logging/Level;
/*      */     //   1179: invokevirtual 145	org/compiere/util/CLogger:isLoggable	(Ljava/util/logging/Level;)Z
/*      */     //   1182: ifeq +27 -> 1209
/*      */     //   1185: aload_0
/*      */     //   1186: getfield 71	com/ghintech/puntocom/process/ImportOrder:log	Lorg/compiere/util/CLogger;
/*      */     //   1189: new 81	java/lang/StringBuilder
/*      */     //   1192: dup
/*      */     //   1193: ldc_w 277
/*      */     //   1196: invokespecial 85	java/lang/StringBuilder:<init>	(Ljava/lang/String;)V
/*      */     //   1199: iload_2
/*      */     //   1200: invokevirtual 123	java/lang/StringBuilder:append	(I)Ljava/lang/StringBuilder;
/*      */     //   1203: invokevirtual 92	java/lang/StringBuilder:toString	()Ljava/lang/String;
/*      */     //   1206: invokevirtual 151	org/compiere/util/CLogger:fine	(Ljava/lang/String;)V
/*      */     //   1209: new 81	java/lang/StringBuilder
/*      */     //   1212: dup
/*      */     //   1213: ldc -70
/*      */     //   1215: invokespecial 85	java/lang/StringBuilder:<init>	(Ljava/lang/String;)V
/*      */     //   1218: ldc_w 271
/*      */     //   1221: invokevirtual 88	java/lang/StringBuilder:append	(Ljava/lang/String;)Ljava/lang/StringBuilder;
/*      */     //   1224: ldc_w 279
/*      */     //   1227: invokevirtual 88	java/lang/StringBuilder:append	(Ljava/lang/String;)Ljava/lang/StringBuilder;
/*      */     //   1230: ldc_w 281
/*      */     //   1233: invokevirtual 88	java/lang/StringBuilder:append	(Ljava/lang/String;)Ljava/lang/StringBuilder;
/*      */     //   1236: aload_3
/*      */     //   1237: invokevirtual 130	java/lang/StringBuilder:append	(Ljava/lang/CharSequence;)Ljava/lang/StringBuilder;
/*      */     //   1240: astore_1
/*      */     //   1241: aload_1
/*      */     //   1242: invokevirtual 92	java/lang/StringBuilder:toString	()Ljava/lang/String;
/*      */     //   1245: aload_0
/*      */     //   1246: invokevirtual 133	com/ghintech/puntocom/process/ImportOrder:get_TrxName	()Ljava/lang/String;
/*      */     //   1249: invokestatic 136	org/compiere/util/DB:executeUpdate	(Ljava/lang/String;Ljava/lang/String;)I
/*      */     //   1252: istore_2
/*      */     //   1253: aload_0
/*      */     //   1254: getfield 71	com/ghintech/puntocom/process/ImportOrder:log	Lorg/compiere/util/CLogger;
/*      */     //   1257: getstatic 142	java/util/logging/Level:FINE	Ljava/util/logging/Level;
/*      */     //   1260: invokevirtual 145	org/compiere/util/CLogger:isLoggable	(Ljava/util/logging/Level;)Z
/*      */     //   1263: ifeq +27 -> 1290
/*      */     //   1266: aload_0
/*      */     //   1267: getfield 71	com/ghintech/puntocom/process/ImportOrder:log	Lorg/compiere/util/CLogger;
/*      */     //   1270: new 81	java/lang/StringBuilder
/*      */     //   1273: dup
/*      */     //   1274: ldc_w 283
/*      */     //   1277: invokespecial 85	java/lang/StringBuilder:<init>	(Ljava/lang/String;)V
/*      */     //   1280: iload_2
/*      */     //   1281: invokevirtual 123	java/lang/StringBuilder:append	(I)Ljava/lang/StringBuilder;
/*      */     //   1284: invokevirtual 92	java/lang/StringBuilder:toString	()Ljava/lang/String;
/*      */     //   1287: invokevirtual 151	org/compiere/util/CLogger:fine	(Ljava/lang/String;)V
/*      */     //   1290: new 81	java/lang/StringBuilder
/*      */     //   1293: dup
/*      */     //   1294: ldc -70
/*      */     //   1296: invokespecial 85	java/lang/StringBuilder:<init>	(Ljava/lang/String;)V
/*      */     //   1299: ldc_w 285
/*      */     //   1302: invokevirtual 88	java/lang/StringBuilder:append	(Ljava/lang/String;)Ljava/lang/StringBuilder;
/*      */     //   1305: ldc_w 287
/*      */     //   1308: invokevirtual 88	java/lang/StringBuilder:append	(Ljava/lang/String;)Ljava/lang/StringBuilder;
/*      */     //   1311: ldc_w 275
/*      */     //   1314: invokevirtual 88	java/lang/StringBuilder:append	(Ljava/lang/String;)Ljava/lang/StringBuilder;
/*      */     //   1317: aload_3
/*      */     //   1318: invokevirtual 130	java/lang/StringBuilder:append	(Ljava/lang/CharSequence;)Ljava/lang/StringBuilder;
/*      */     //   1321: astore_1
/*      */     //   1322: aload_1
/*      */     //   1323: invokevirtual 92	java/lang/StringBuilder:toString	()Ljava/lang/String;
/*      */     //   1326: aload_0
/*      */     //   1327: invokevirtual 133	com/ghintech/puntocom/process/ImportOrder:get_TrxName	()Ljava/lang/String;
/*      */     //   1330: invokestatic 136	org/compiere/util/DB:executeUpdate	(Ljava/lang/String;Ljava/lang/String;)I
/*      */     //   1333: istore_2
/*      */     //   1334: aload_0
/*      */     //   1335: getfield 71	com/ghintech/puntocom/process/ImportOrder:log	Lorg/compiere/util/CLogger;
/*      */     //   1338: getstatic 142	java/util/logging/Level:FINE	Ljava/util/logging/Level;
/*      */     //   1341: invokevirtual 145	org/compiere/util/CLogger:isLoggable	(Ljava/util/logging/Level;)Z
/*      */     //   1344: ifeq +27 -> 1371
/*      */     //   1347: aload_0
/*      */     //   1348: getfield 71	com/ghintech/puntocom/process/ImportOrder:log	Lorg/compiere/util/CLogger;
/*      */     //   1351: new 81	java/lang/StringBuilder
/*      */     //   1354: dup
/*      */     //   1355: ldc_w 289
/*      */     //   1358: invokespecial 85	java/lang/StringBuilder:<init>	(Ljava/lang/String;)V
/*      */     //   1361: iload_2
/*      */     //   1362: invokevirtual 123	java/lang/StringBuilder:append	(I)Ljava/lang/StringBuilder;
/*      */     //   1365: invokevirtual 92	java/lang/StringBuilder:toString	()Ljava/lang/String;
/*      */     //   1368: invokevirtual 151	org/compiere/util/CLogger:fine	(Ljava/lang/String;)V
/*      */     //   1371: new 81	java/lang/StringBuilder
/*      */     //   1374: dup
/*      */     //   1375: ldc -70
/*      */     //   1377: invokespecial 85	java/lang/StringBuilder:<init>	(Ljava/lang/String;)V
/*      */     //   1380: ldc_w 285
/*      */     //   1383: invokevirtual 88	java/lang/StringBuilder:append	(Ljava/lang/String;)Ljava/lang/StringBuilder;
/*      */     //   1386: ldc_w 291
/*      */     //   1389: invokevirtual 88	java/lang/StringBuilder:append	(Ljava/lang/String;)Ljava/lang/StringBuilder;
/*      */     //   1392: ldc_w 281
/*      */     //   1395: invokevirtual 88	java/lang/StringBuilder:append	(Ljava/lang/String;)Ljava/lang/StringBuilder;
/*      */     //   1398: aload_3
/*      */     //   1399: invokevirtual 130	java/lang/StringBuilder:append	(Ljava/lang/CharSequence;)Ljava/lang/StringBuilder;
/*      */     //   1402: astore_1
/*      */     //   1403: aload_1
/*      */     //   1404: invokevirtual 92	java/lang/StringBuilder:toString	()Ljava/lang/String;
/*      */     //   1407: aload_0
/*      */     //   1408: invokevirtual 133	com/ghintech/puntocom/process/ImportOrder:get_TrxName	()Ljava/lang/String;
/*      */     //   1411: invokestatic 136	org/compiere/util/DB:executeUpdate	(Ljava/lang/String;Ljava/lang/String;)I
/*      */     //   1414: istore_2
/*      */     //   1415: aload_0
/*      */     //   1416: getfield 71	com/ghintech/puntocom/process/ImportOrder:log	Lorg/compiere/util/CLogger;
/*      */     //   1419: getstatic 142	java/util/logging/Level:FINE	Ljava/util/logging/Level;
/*      */     //   1422: invokevirtual 145	org/compiere/util/CLogger:isLoggable	(Ljava/util/logging/Level;)Z
/*      */     //   1425: ifeq +27 -> 1452
/*      */     //   1428: aload_0
/*      */     //   1429: getfield 71	com/ghintech/puntocom/process/ImportOrder:log	Lorg/compiere/util/CLogger;
/*      */     //   1432: new 81	java/lang/StringBuilder
/*      */     //   1435: dup
/*      */     //   1436: ldc_w 293
/*      */     //   1439: invokespecial 85	java/lang/StringBuilder:<init>	(Ljava/lang/String;)V
/*      */     //   1442: iload_2
/*      */     //   1443: invokevirtual 123	java/lang/StringBuilder:append	(I)Ljava/lang/StringBuilder;
/*      */     //   1446: invokevirtual 92	java/lang/StringBuilder:toString	()Ljava/lang/String;
/*      */     //   1449: invokevirtual 151	org/compiere/util/CLogger:fine	(Ljava/lang/String;)V
/*      */     //   1452: new 81	java/lang/StringBuilder
/*      */     //   1455: dup
/*      */     //   1456: ldc -102
/*      */     //   1458: invokespecial 85	java/lang/StringBuilder:<init>	(Ljava/lang/String;)V
/*      */     //   1461: ldc_w 295
/*      */     //   1464: invokevirtual 88	java/lang/StringBuilder:append	(Ljava/lang/String;)Ljava/lang/StringBuilder;
/*      */     //   1467: ldc_w 297
/*      */     //   1470: invokevirtual 88	java/lang/StringBuilder:append	(Ljava/lang/String;)Ljava/lang/StringBuilder;
/*      */     //   1473: ldc -54
/*      */     //   1475: invokevirtual 88	java/lang/StringBuilder:append	(Ljava/lang/String;)Ljava/lang/StringBuilder;
/*      */     //   1478: aload_3
/*      */     //   1479: invokevirtual 130	java/lang/StringBuilder:append	(Ljava/lang/CharSequence;)Ljava/lang/StringBuilder;
/*      */     //   1482: astore_1
/*      */     //   1483: aload_1
/*      */     //   1484: invokevirtual 92	java/lang/StringBuilder:toString	()Ljava/lang/String;
/*      */     //   1487: aload_0
/*      */     //   1488: invokevirtual 133	com/ghintech/puntocom/process/ImportOrder:get_TrxName	()Ljava/lang/String;
/*      */     //   1491: invokestatic 136	org/compiere/util/DB:executeUpdate	(Ljava/lang/String;Ljava/lang/String;)I
/*      */     //   1494: istore_2
/*      */     //   1495: iload_2
/*      */     //   1496: ifeq +27 -> 1523
/*      */     //   1499: aload_0
/*      */     //   1500: getfield 71	com/ghintech/puntocom/process/ImportOrder:log	Lorg/compiere/util/CLogger;
/*      */     //   1503: new 81	java/lang/StringBuilder
/*      */     //   1506: dup
/*      */     //   1507: ldc_w 299
/*      */     //   1510: invokespecial 85	java/lang/StringBuilder:<init>	(Ljava/lang/String;)V
/*      */     //   1513: iload_2
/*      */     //   1514: invokevirtual 123	java/lang/StringBuilder:append	(I)Ljava/lang/StringBuilder;
/*      */     //   1517: invokevirtual 92	java/lang/StringBuilder:toString	()Ljava/lang/String;
/*      */     //   1520: invokevirtual 206	org/compiere/util/CLogger:warning	(Ljava/lang/String;)V
/*      */     //   1523: new 81	java/lang/StringBuilder
/*      */     //   1526: dup
/*      */     //   1527: ldc -70
/*      */     //   1529: invokespecial 85	java/lang/StringBuilder:<init>	(Ljava/lang/String;)V
/*      */     //   1532: ldc_w 301
/*      */     //   1535: invokevirtual 88	java/lang/StringBuilder:append	(Ljava/lang/String;)Ljava/lang/StringBuilder;
/*      */     //   1538: ldc_w 303
/*      */     //   1541: invokevirtual 88	java/lang/StringBuilder:append	(Ljava/lang/String;)Ljava/lang/StringBuilder;
/*      */     //   1544: ldc_w 305
/*      */     //   1547: invokevirtual 88	java/lang/StringBuilder:append	(Ljava/lang/String;)Ljava/lang/StringBuilder;
/*      */     //   1550: aload_3
/*      */     //   1551: invokevirtual 130	java/lang/StringBuilder:append	(Ljava/lang/CharSequence;)Ljava/lang/StringBuilder;
/*      */     //   1554: astore_1
/*      */     //   1555: aload_1
/*      */     //   1556: invokevirtual 92	java/lang/StringBuilder:toString	()Ljava/lang/String;
/*      */     //   1559: aload_0
/*      */     //   1560: invokevirtual 133	com/ghintech/puntocom/process/ImportOrder:get_TrxName	()Ljava/lang/String;
/*      */     //   1563: invokestatic 136	org/compiere/util/DB:executeUpdate	(Ljava/lang/String;Ljava/lang/String;)I
/*      */     //   1566: istore_2
/*      */     //   1567: aload_0
/*      */     //   1568: getfield 71	com/ghintech/puntocom/process/ImportOrder:log	Lorg/compiere/util/CLogger;
/*      */     //   1571: getstatic 142	java/util/logging/Level:FINE	Ljava/util/logging/Level;
/*      */     //   1574: invokevirtual 145	org/compiere/util/CLogger:isLoggable	(Ljava/util/logging/Level;)Z
/*      */     //   1577: ifeq +27 -> 1604
/*      */     //   1580: aload_0
/*      */     //   1581: getfield 71	com/ghintech/puntocom/process/ImportOrder:log	Lorg/compiere/util/CLogger;
/*      */     //   1584: new 81	java/lang/StringBuilder
/*      */     //   1587: dup
/*      */     //   1588: ldc_w 307
/*      */     //   1591: invokespecial 85	java/lang/StringBuilder:<init>	(Ljava/lang/String;)V
/*      */     //   1594: iload_2
/*      */     //   1595: invokevirtual 123	java/lang/StringBuilder:append	(I)Ljava/lang/StringBuilder;
/*      */     //   1598: invokevirtual 92	java/lang/StringBuilder:toString	()Ljava/lang/String;
/*      */     //   1601: invokevirtual 151	org/compiere/util/CLogger:fine	(Ljava/lang/String;)V
/*      */     //   1604: new 81	java/lang/StringBuilder
/*      */     //   1607: dup
/*      */     //   1608: ldc -102
/*      */     //   1610: invokespecial 85	java/lang/StringBuilder:<init>	(Ljava/lang/String;)V
/*      */     //   1613: ldc_w 309
/*      */     //   1616: invokevirtual 88	java/lang/StringBuilder:append	(Ljava/lang/String;)Ljava/lang/StringBuilder;
/*      */     //   1619: ldc_w 305
/*      */     //   1622: invokevirtual 88	java/lang/StringBuilder:append	(Ljava/lang/String;)Ljava/lang/StringBuilder;
/*      */     //   1625: aload_3
/*      */     //   1626: invokevirtual 130	java/lang/StringBuilder:append	(Ljava/lang/CharSequence;)Ljava/lang/StringBuilder;
/*      */     //   1629: astore_1
/*      */     //   1630: aload_1
/*      */     //   1631: invokevirtual 92	java/lang/StringBuilder:toString	()Ljava/lang/String;
/*      */     //   1634: aload_0
/*      */     //   1635: invokevirtual 133	com/ghintech/puntocom/process/ImportOrder:get_TrxName	()Ljava/lang/String;
/*      */     //   1638: invokestatic 136	org/compiere/util/DB:executeUpdate	(Ljava/lang/String;Ljava/lang/String;)I
/*      */     //   1641: istore_2
/*      */     //   1642: iload_2
/*      */     //   1643: ifeq +27 -> 1670
/*      */     //   1646: aload_0
/*      */     //   1647: getfield 71	com/ghintech/puntocom/process/ImportOrder:log	Lorg/compiere/util/CLogger;
/*      */     //   1650: new 81	java/lang/StringBuilder
/*      */     //   1653: dup
/*      */     //   1654: ldc_w 311
/*      */     //   1657: invokespecial 85	java/lang/StringBuilder:<init>	(Ljava/lang/String;)V
/*      */     //   1660: iload_2
/*      */     //   1661: invokevirtual 123	java/lang/StringBuilder:append	(I)Ljava/lang/StringBuilder;
/*      */     //   1664: invokevirtual 92	java/lang/StringBuilder:toString	()Ljava/lang/String;
/*      */     //   1667: invokevirtual 206	org/compiere/util/CLogger:warning	(Ljava/lang/String;)V
/*      */     //   1670: new 81	java/lang/StringBuilder
/*      */     //   1673: dup
/*      */     //   1674: ldc -70
/*      */     //   1676: invokespecial 85	java/lang/StringBuilder:<init>	(Ljava/lang/String;)V
/*      */     //   1679: ldc_w 313
/*      */     //   1682: invokevirtual 88	java/lang/StringBuilder:append	(Ljava/lang/String;)Ljava/lang/StringBuilder;
/*      */     //   1685: ldc_w 315
/*      */     //   1688: invokevirtual 88	java/lang/StringBuilder:append	(Ljava/lang/String;)Ljava/lang/StringBuilder;
/*      */     //   1691: ldc_w 317
/*      */     //   1694: invokevirtual 88	java/lang/StringBuilder:append	(Ljava/lang/String;)Ljava/lang/StringBuilder;
/*      */     //   1697: aload_3
/*      */     //   1698: invokevirtual 130	java/lang/StringBuilder:append	(Ljava/lang/CharSequence;)Ljava/lang/StringBuilder;
/*      */     //   1701: astore_1
/*      */     //   1702: aload_1
/*      */     //   1703: invokevirtual 92	java/lang/StringBuilder:toString	()Ljava/lang/String;
/*      */     //   1706: aload_0
/*      */     //   1707: invokevirtual 133	com/ghintech/puntocom/process/ImportOrder:get_TrxName	()Ljava/lang/String;
/*      */     //   1710: invokestatic 136	org/compiere/util/DB:executeUpdate	(Ljava/lang/String;Ljava/lang/String;)I
/*      */     //   1713: istore_2
/*      */     //   1714: aload_0
/*      */     //   1715: getfield 71	com/ghintech/puntocom/process/ImportOrder:log	Lorg/compiere/util/CLogger;
/*      */     //   1718: getstatic 142	java/util/logging/Level:FINE	Ljava/util/logging/Level;
/*      */     //   1721: invokevirtual 145	org/compiere/util/CLogger:isLoggable	(Ljava/util/logging/Level;)Z
/*      */     //   1724: ifeq +27 -> 1751
/*      */     //   1727: aload_0
/*      */     //   1728: getfield 71	com/ghintech/puntocom/process/ImportOrder:log	Lorg/compiere/util/CLogger;
/*      */     //   1731: new 81	java/lang/StringBuilder
/*      */     //   1734: dup
/*      */     //   1735: ldc_w 319
/*      */     //   1738: invokespecial 85	java/lang/StringBuilder:<init>	(Ljava/lang/String;)V
/*      */     //   1741: iload_2
/*      */     //   1742: invokevirtual 123	java/lang/StringBuilder:append	(I)Ljava/lang/StringBuilder;
/*      */     //   1745: invokevirtual 92	java/lang/StringBuilder:toString	()Ljava/lang/String;
/*      */     //   1748: invokevirtual 151	org/compiere/util/CLogger:fine	(Ljava/lang/String;)V
/*      */     //   1751: new 81	java/lang/StringBuilder
/*      */     //   1754: dup
/*      */     //   1755: ldc -70
/*      */     //   1757: invokespecial 85	java/lang/StringBuilder:<init>	(Ljava/lang/String;)V
/*      */     //   1760: ldc_w 321
/*      */     //   1763: invokevirtual 88	java/lang/StringBuilder:append	(Ljava/lang/String;)Ljava/lang/StringBuilder;
/*      */     //   1766: ldc_w 323
/*      */     //   1769: invokevirtual 88	java/lang/StringBuilder:append	(Ljava/lang/String;)Ljava/lang/StringBuilder;
/*      */     //   1772: ldc_w 325
/*      */     //   1775: invokevirtual 88	java/lang/StringBuilder:append	(Ljava/lang/String;)Ljava/lang/StringBuilder;
/*      */     //   1778: aload_3
/*      */     //   1779: invokevirtual 130	java/lang/StringBuilder:append	(Ljava/lang/CharSequence;)Ljava/lang/StringBuilder;
/*      */     //   1782: astore_1
/*      */     //   1783: aload_1
/*      */     //   1784: invokevirtual 92	java/lang/StringBuilder:toString	()Ljava/lang/String;
/*      */     //   1787: aload_0
/*      */     //   1788: invokevirtual 133	com/ghintech/puntocom/process/ImportOrder:get_TrxName	()Ljava/lang/String;
/*      */     //   1791: invokestatic 136	org/compiere/util/DB:executeUpdate	(Ljava/lang/String;Ljava/lang/String;)I
/*      */     //   1794: istore_2
/*      */     //   1795: aload_0
/*      */     //   1796: getfield 71	com/ghintech/puntocom/process/ImportOrder:log	Lorg/compiere/util/CLogger;
/*      */     //   1799: getstatic 142	java/util/logging/Level:FINE	Ljava/util/logging/Level;
/*      */     //   1802: invokevirtual 145	org/compiere/util/CLogger:isLoggable	(Ljava/util/logging/Level;)Z
/*      */     //   1805: ifeq +27 -> 1832
/*      */     //   1808: aload_0
/*      */     //   1809: getfield 71	com/ghintech/puntocom/process/ImportOrder:log	Lorg/compiere/util/CLogger;
/*      */     //   1812: new 81	java/lang/StringBuilder
/*      */     //   1815: dup
/*      */     //   1816: ldc_w 327
/*      */     //   1819: invokespecial 85	java/lang/StringBuilder:<init>	(Ljava/lang/String;)V
/*      */     //   1822: iload_2
/*      */     //   1823: invokevirtual 123	java/lang/StringBuilder:append	(I)Ljava/lang/StringBuilder;
/*      */     //   1826: invokevirtual 92	java/lang/StringBuilder:toString	()Ljava/lang/String;
/*      */     //   1829: invokevirtual 151	org/compiere/util/CLogger:fine	(Ljava/lang/String;)V
/*      */     //   1832: new 81	java/lang/StringBuilder
/*      */     //   1835: dup
/*      */     //   1836: ldc -102
/*      */     //   1838: invokespecial 85	java/lang/StringBuilder:<init>	(Ljava/lang/String;)V
/*      */     //   1841: ldc_w 329
/*      */     //   1844: invokevirtual 88	java/lang/StringBuilder:append	(Ljava/lang/String;)Ljava/lang/StringBuilder;
/*      */     //   1847: ldc_w 331
/*      */     //   1850: invokevirtual 88	java/lang/StringBuilder:append	(Ljava/lang/String;)Ljava/lang/StringBuilder;
/*      */     //   1853: ldc -54
/*      */     //   1855: invokevirtual 88	java/lang/StringBuilder:append	(Ljava/lang/String;)Ljava/lang/StringBuilder;
/*      */     //   1858: aload_3
/*      */     //   1859: invokevirtual 130	java/lang/StringBuilder:append	(Ljava/lang/CharSequence;)Ljava/lang/StringBuilder;
/*      */     //   1862: astore_1
/*      */     //   1863: aload_1
/*      */     //   1864: invokevirtual 92	java/lang/StringBuilder:toString	()Ljava/lang/String;
/*      */     //   1867: aload_0
/*      */     //   1868: invokevirtual 133	com/ghintech/puntocom/process/ImportOrder:get_TrxName	()Ljava/lang/String;
/*      */     //   1871: invokestatic 136	org/compiere/util/DB:executeUpdate	(Ljava/lang/String;Ljava/lang/String;)I
/*      */     //   1874: istore_2
/*      */     //   1875: iload_2
/*      */     //   1876: ifeq +27 -> 1903
/*      */     //   1879: aload_0
/*      */     //   1880: getfield 71	com/ghintech/puntocom/process/ImportOrder:log	Lorg/compiere/util/CLogger;
/*      */     //   1883: new 81	java/lang/StringBuilder
/*      */     //   1886: dup
/*      */     //   1887: ldc_w 333
/*      */     //   1890: invokespecial 85	java/lang/StringBuilder:<init>	(Ljava/lang/String;)V
/*      */     //   1893: iload_2
/*      */     //   1894: invokevirtual 123	java/lang/StringBuilder:append	(I)Ljava/lang/StringBuilder;
/*      */     //   1897: invokevirtual 92	java/lang/StringBuilder:toString	()Ljava/lang/String;
/*      */     //   1900: invokevirtual 206	org/compiere/util/CLogger:warning	(Ljava/lang/String;)V
/*      */     //   1903: new 81	java/lang/StringBuilder
/*      */     //   1906: dup
/*      */     //   1907: ldc -70
/*      */     //   1909: invokespecial 85	java/lang/StringBuilder:<init>	(Ljava/lang/String;)V
/*      */     //   1912: ldc_w 335
/*      */     //   1915: invokevirtual 88	java/lang/StringBuilder:append	(Ljava/lang/String;)Ljava/lang/StringBuilder;
/*      */     //   1918: ldc_w 337
/*      */     //   1921: invokevirtual 88	java/lang/StringBuilder:append	(Ljava/lang/String;)Ljava/lang/StringBuilder;
/*      */     //   1924: ldc_w 339
/*      */     //   1927: invokevirtual 88	java/lang/StringBuilder:append	(Ljava/lang/String;)Ljava/lang/StringBuilder;
/*      */     //   1930: aload_3
/*      */     //   1931: invokevirtual 130	java/lang/StringBuilder:append	(Ljava/lang/CharSequence;)Ljava/lang/StringBuilder;
/*      */     //   1934: astore_1
/*      */     //   1935: aload_1
/*      */     //   1936: invokevirtual 92	java/lang/StringBuilder:toString	()Ljava/lang/String;
/*      */     //   1939: aload_0
/*      */     //   1940: invokevirtual 133	com/ghintech/puntocom/process/ImportOrder:get_TrxName	()Ljava/lang/String;
/*      */     //   1943: invokestatic 136	org/compiere/util/DB:executeUpdate	(Ljava/lang/String;Ljava/lang/String;)I
/*      */     //   1946: istore_2
/*      */     //   1947: iload_2
/*      */     //   1948: ifeq +40 -> 1988
/*      */     //   1951: aload_0
/*      */     //   1952: getfield 71	com/ghintech/puntocom/process/ImportOrder:log	Lorg/compiere/util/CLogger;
/*      */     //   1955: getstatic 142	java/util/logging/Level:FINE	Ljava/util/logging/Level;
/*      */     //   1958: invokevirtual 145	org/compiere/util/CLogger:isLoggable	(Ljava/util/logging/Level;)Z
/*      */     //   1961: ifeq +27 -> 1988
/*      */     //   1964: aload_0
/*      */     //   1965: getfield 71	com/ghintech/puntocom/process/ImportOrder:log	Lorg/compiere/util/CLogger;
/*      */     //   1968: new 81	java/lang/StringBuilder
/*      */     //   1971: dup
/*      */     //   1972: ldc_w 341
/*      */     //   1975: invokespecial 85	java/lang/StringBuilder:<init>	(Ljava/lang/String;)V
/*      */     //   1978: iload_2
/*      */     //   1979: invokevirtual 123	java/lang/StringBuilder:append	(I)Ljava/lang/StringBuilder;
/*      */     //   1982: invokevirtual 92	java/lang/StringBuilder:toString	()Ljava/lang/String;
/*      */     //   1985: invokevirtual 151	org/compiere/util/CLogger:fine	(Ljava/lang/String;)V
/*      */     //   1988: new 81	java/lang/StringBuilder
/*      */     //   1991: dup
/*      */     //   1992: ldc -70
/*      */     //   1994: invokespecial 85	java/lang/StringBuilder:<init>	(Ljava/lang/String;)V
/*      */     //   1997: ldc_w 343
/*      */     //   2000: invokevirtual 88	java/lang/StringBuilder:append	(Ljava/lang/String;)Ljava/lang/StringBuilder;
/*      */     //   2003: ldc_w 345
/*      */     //   2006: invokevirtual 88	java/lang/StringBuilder:append	(Ljava/lang/String;)Ljava/lang/StringBuilder;
/*      */     //   2009: ldc_w 347
/*      */     //   2012: invokevirtual 88	java/lang/StringBuilder:append	(Ljava/lang/String;)Ljava/lang/StringBuilder;
/*      */     //   2015: ldc_w 349
/*      */     //   2018: invokevirtual 88	java/lang/StringBuilder:append	(Ljava/lang/String;)Ljava/lang/StringBuilder;
/*      */     //   2021: ldc -54
/*      */     //   2023: invokevirtual 88	java/lang/StringBuilder:append	(Ljava/lang/String;)Ljava/lang/StringBuilder;
/*      */     //   2026: aload_3
/*      */     //   2027: invokevirtual 130	java/lang/StringBuilder:append	(Ljava/lang/CharSequence;)Ljava/lang/StringBuilder;
/*      */     //   2030: astore_1
/*      */     //   2031: aload_1
/*      */     //   2032: invokevirtual 92	java/lang/StringBuilder:toString	()Ljava/lang/String;
/*      */     //   2035: aload_0
/*      */     //   2036: invokevirtual 133	com/ghintech/puntocom/process/ImportOrder:get_TrxName	()Ljava/lang/String;
/*      */     //   2039: invokestatic 136	org/compiere/util/DB:executeUpdate	(Ljava/lang/String;Ljava/lang/String;)I
/*      */     //   2042: istore_2
/*      */     //   2043: iload_2
/*      */     //   2044: ifeq +40 -> 2084
/*      */     //   2047: aload_0
/*      */     //   2048: getfield 71	com/ghintech/puntocom/process/ImportOrder:log	Lorg/compiere/util/CLogger;
/*      */     //   2051: getstatic 142	java/util/logging/Level:FINE	Ljava/util/logging/Level;
/*      */     //   2054: invokevirtual 145	org/compiere/util/CLogger:isLoggable	(Ljava/util/logging/Level;)Z
/*      */     //   2057: ifeq +27 -> 2084
/*      */     //   2060: aload_0
/*      */     //   2061: getfield 71	com/ghintech/puntocom/process/ImportOrder:log	Lorg/compiere/util/CLogger;
/*      */     //   2064: new 81	java/lang/StringBuilder
/*      */     //   2067: dup
/*      */     //   2068: ldc_w 351
/*      */     //   2071: invokespecial 85	java/lang/StringBuilder:<init>	(Ljava/lang/String;)V
/*      */     //   2074: iload_2
/*      */     //   2075: invokevirtual 123	java/lang/StringBuilder:append	(I)Ljava/lang/StringBuilder;
/*      */     //   2078: invokevirtual 92	java/lang/StringBuilder:toString	()Ljava/lang/String;
/*      */     //   2081: invokevirtual 151	org/compiere/util/CLogger:fine	(Ljava/lang/String;)V
/*      */     //   2084: new 81	java/lang/StringBuilder
/*      */     //   2087: dup
/*      */     //   2088: ldc -102
/*      */     //   2090: invokespecial 85	java/lang/StringBuilder:<init>	(Ljava/lang/String;)V
/*      */     //   2093: ldc_w 353
/*      */     //   2096: invokevirtual 88	java/lang/StringBuilder:append	(Ljava/lang/String;)Ljava/lang/StringBuilder;
/*      */     //   2099: ldc_w 347
/*      */     //   2102: invokevirtual 88	java/lang/StringBuilder:append	(Ljava/lang/String;)Ljava/lang/StringBuilder;
/*      */     //   2105: ldc -54
/*      */     //   2107: invokevirtual 88	java/lang/StringBuilder:append	(Ljava/lang/String;)Ljava/lang/StringBuilder;
/*      */     //   2110: aload_3
/*      */     //   2111: invokevirtual 130	java/lang/StringBuilder:append	(Ljava/lang/CharSequence;)Ljava/lang/StringBuilder;
/*      */     //   2114: astore_1
/*      */     //   2115: aload_1
/*      */     //   2116: invokevirtual 92	java/lang/StringBuilder:toString	()Ljava/lang/String;
/*      */     //   2119: aload_0
/*      */     //   2120: invokevirtual 133	com/ghintech/puntocom/process/ImportOrder:get_TrxName	()Ljava/lang/String;
/*      */     //   2123: invokestatic 136	org/compiere/util/DB:executeUpdate	(Ljava/lang/String;Ljava/lang/String;)I
/*      */     //   2126: istore_2
/*      */     //   2127: iload_2
/*      */     //   2128: ifeq +27 -> 2155
/*      */     //   2131: aload_0
/*      */     //   2132: getfield 71	com/ghintech/puntocom/process/ImportOrder:log	Lorg/compiere/util/CLogger;
/*      */     //   2135: new 81	java/lang/StringBuilder
/*      */     //   2138: dup
/*      */     //   2139: ldc_w 355
/*      */     //   2142: invokespecial 85	java/lang/StringBuilder:<init>	(Ljava/lang/String;)V
/*      */     //   2145: iload_2
/*      */     //   2146: invokevirtual 123	java/lang/StringBuilder:append	(I)Ljava/lang/StringBuilder;
/*      */     //   2149: invokevirtual 92	java/lang/StringBuilder:toString	()Ljava/lang/String;
/*      */     //   2152: invokevirtual 206	org/compiere/util/CLogger:warning	(Ljava/lang/String;)V
/*      */     //   2155: new 81	java/lang/StringBuilder
/*      */     //   2158: dup
/*      */     //   2159: ldc -70
/*      */     //   2161: invokespecial 85	java/lang/StringBuilder:<init>	(Ljava/lang/String;)V
/*      */     //   2164: ldc_w 357
/*      */     //   2167: invokevirtual 88	java/lang/StringBuilder:append	(Ljava/lang/String;)Ljava/lang/StringBuilder;
/*      */     //   2170: ldc_w 359
/*      */     //   2173: invokevirtual 88	java/lang/StringBuilder:append	(Ljava/lang/String;)Ljava/lang/StringBuilder;
/*      */     //   2176: ldc_w 361
/*      */     //   2179: invokevirtual 88	java/lang/StringBuilder:append	(Ljava/lang/String;)Ljava/lang/StringBuilder;
/*      */     //   2182: ldc -54
/*      */     //   2184: invokevirtual 88	java/lang/StringBuilder:append	(Ljava/lang/String;)Ljava/lang/StringBuilder;
/*      */     //   2187: aload_3
/*      */     //   2188: invokevirtual 130	java/lang/StringBuilder:append	(Ljava/lang/CharSequence;)Ljava/lang/StringBuilder;
/*      */     //   2191: astore_1
/*      */     //   2192: aload_1
/*      */     //   2193: invokevirtual 92	java/lang/StringBuilder:toString	()Ljava/lang/String;
/*      */     //   2196: aload_0
/*      */     //   2197: invokevirtual 133	com/ghintech/puntocom/process/ImportOrder:get_TrxName	()Ljava/lang/String;
/*      */     //   2200: invokestatic 136	org/compiere/util/DB:executeUpdate	(Ljava/lang/String;Ljava/lang/String;)I
/*      */     //   2203: istore_2
/*      */     //   2204: aload_0
/*      */     //   2205: getfield 71	com/ghintech/puntocom/process/ImportOrder:log	Lorg/compiere/util/CLogger;
/*      */     //   2208: getstatic 142	java/util/logging/Level:FINE	Ljava/util/logging/Level;
/*      */     //   2211: invokevirtual 145	org/compiere/util/CLogger:isLoggable	(Ljava/util/logging/Level;)Z
/*      */     //   2214: ifeq +27 -> 2241
/*      */     //   2217: aload_0
/*      */     //   2218: getfield 71	com/ghintech/puntocom/process/ImportOrder:log	Lorg/compiere/util/CLogger;
/*      */     //   2221: new 81	java/lang/StringBuilder
/*      */     //   2224: dup
/*      */     //   2225: ldc_w 363
/*      */     //   2228: invokespecial 85	java/lang/StringBuilder:<init>	(Ljava/lang/String;)V
/*      */     //   2231: iload_2
/*      */     //   2232: invokevirtual 123	java/lang/StringBuilder:append	(I)Ljava/lang/StringBuilder;
/*      */     //   2235: invokevirtual 92	java/lang/StringBuilder:toString	()Ljava/lang/String;
/*      */     //   2238: invokevirtual 151	org/compiere/util/CLogger:fine	(Ljava/lang/String;)V
/*      */     //   2241: new 81	java/lang/StringBuilder
/*      */     //   2244: dup
/*      */     //   2245: ldc -70
/*      */     //   2247: invokespecial 85	java/lang/StringBuilder:<init>	(Ljava/lang/String;)V
/*      */     //   2250: ldc_w 365
/*      */     //   2253: invokevirtual 88	java/lang/StringBuilder:append	(Ljava/lang/String;)Ljava/lang/StringBuilder;
/*      */     //   2256: ldc_w 367
/*      */     //   2259: invokevirtual 88	java/lang/StringBuilder:append	(Ljava/lang/String;)Ljava/lang/StringBuilder;
/*      */     //   2262: ldc_w 369
/*      */     //   2265: invokevirtual 88	java/lang/StringBuilder:append	(Ljava/lang/String;)Ljava/lang/StringBuilder;
/*      */     //   2268: ldc -54
/*      */     //   2270: invokevirtual 88	java/lang/StringBuilder:append	(Ljava/lang/String;)Ljava/lang/StringBuilder;
/*      */     //   2273: aload_3
/*      */     //   2274: invokevirtual 130	java/lang/StringBuilder:append	(Ljava/lang/CharSequence;)Ljava/lang/StringBuilder;
/*      */     //   2277: astore_1
/*      */     //   2278: aload_1
/*      */     //   2279: invokevirtual 92	java/lang/StringBuilder:toString	()Ljava/lang/String;
/*      */     //   2282: aload_0
/*      */     //   2283: invokevirtual 133	com/ghintech/puntocom/process/ImportOrder:get_TrxName	()Ljava/lang/String;
/*      */     //   2286: invokestatic 136	org/compiere/util/DB:executeUpdate	(Ljava/lang/String;Ljava/lang/String;)I
/*      */     //   2289: istore_2
/*      */     //   2290: aload_0
/*      */     //   2291: getfield 71	com/ghintech/puntocom/process/ImportOrder:log	Lorg/compiere/util/CLogger;
/*      */     //   2294: getstatic 142	java/util/logging/Level:FINE	Ljava/util/logging/Level;
/*      */     //   2297: invokevirtual 145	org/compiere/util/CLogger:isLoggable	(Ljava/util/logging/Level;)Z
/*      */     //   2300: ifeq +27 -> 2327
/*      */     //   2303: aload_0
/*      */     //   2304: getfield 71	com/ghintech/puntocom/process/ImportOrder:log	Lorg/compiere/util/CLogger;
/*      */     //   2307: new 81	java/lang/StringBuilder
/*      */     //   2310: dup
/*      */     //   2311: ldc_w 371
/*      */     //   2314: invokespecial 85	java/lang/StringBuilder:<init>	(Ljava/lang/String;)V
/*      */     //   2317: iload_2
/*      */     //   2318: invokevirtual 123	java/lang/StringBuilder:append	(I)Ljava/lang/StringBuilder;
/*      */     //   2321: invokevirtual 92	java/lang/StringBuilder:toString	()Ljava/lang/String;
/*      */     //   2324: invokevirtual 151	org/compiere/util/CLogger:fine	(Ljava/lang/String;)V
/*      */     //   2327: new 81	java/lang/StringBuilder
/*      */     //   2330: dup
/*      */     //   2331: ldc -70
/*      */     //   2333: invokespecial 85	java/lang/StringBuilder:<init>	(Ljava/lang/String;)V
/*      */     //   2336: ldc_w 373
/*      */     //   2339: invokevirtual 88	java/lang/StringBuilder:append	(Ljava/lang/String;)Ljava/lang/StringBuilder;
/*      */     //   2342: ldc_w 375
/*      */     //   2345: invokevirtual 88	java/lang/StringBuilder:append	(Ljava/lang/String;)Ljava/lang/StringBuilder;
/*      */     //   2348: ldc_w 377
/*      */     //   2351: invokevirtual 88	java/lang/StringBuilder:append	(Ljava/lang/String;)Ljava/lang/StringBuilder;
/*      */     //   2354: ldc_w 379
/*      */     //   2357: invokevirtual 88	java/lang/StringBuilder:append	(Ljava/lang/String;)Ljava/lang/StringBuilder;
/*      */     //   2360: ldc_w 381
/*      */     //   2363: invokevirtual 88	java/lang/StringBuilder:append	(Ljava/lang/String;)Ljava/lang/StringBuilder;
/*      */     //   2366: ldc_w 383
/*      */     //   2369: invokevirtual 88	java/lang/StringBuilder:append	(Ljava/lang/String;)Ljava/lang/StringBuilder;
/*      */     //   2372: ldc_w 385
/*      */     //   2375: invokevirtual 88	java/lang/StringBuilder:append	(Ljava/lang/String;)Ljava/lang/StringBuilder;
/*      */     //   2378: ldc_w 387
/*      */     //   2381: invokevirtual 88	java/lang/StringBuilder:append	(Ljava/lang/String;)Ljava/lang/StringBuilder;
/*      */     //   2384: aload_3
/*      */     //   2385: invokevirtual 130	java/lang/StringBuilder:append	(Ljava/lang/CharSequence;)Ljava/lang/StringBuilder;
/*      */     //   2388: astore_1
/*      */     //   2389: aload_1
/*      */     //   2390: invokevirtual 92	java/lang/StringBuilder:toString	()Ljava/lang/String;
/*      */     //   2393: aload_0
/*      */     //   2394: invokevirtual 133	com/ghintech/puntocom/process/ImportOrder:get_TrxName	()Ljava/lang/String;
/*      */     //   2397: invokestatic 136	org/compiere/util/DB:executeUpdate	(Ljava/lang/String;Ljava/lang/String;)I
/*      */     //   2400: istore_2
/*      */     //   2401: aload_0
/*      */     //   2402: getfield 71	com/ghintech/puntocom/process/ImportOrder:log	Lorg/compiere/util/CLogger;
/*      */     //   2405: getstatic 142	java/util/logging/Level:FINE	Ljava/util/logging/Level;
/*      */     //   2408: invokevirtual 145	org/compiere/util/CLogger:isLoggable	(Ljava/util/logging/Level;)Z
/*      */     //   2411: ifeq +27 -> 2438
/*      */     //   2414: aload_0
/*      */     //   2415: getfield 71	com/ghintech/puntocom/process/ImportOrder:log	Lorg/compiere/util/CLogger;
/*      */     //   2418: new 81	java/lang/StringBuilder
/*      */     //   2421: dup
/*      */     //   2422: ldc_w 389
/*      */     //   2425: invokespecial 85	java/lang/StringBuilder:<init>	(Ljava/lang/String;)V
/*      */     //   2428: iload_2
/*      */     //   2429: invokevirtual 123	java/lang/StringBuilder:append	(I)Ljava/lang/StringBuilder;
/*      */     //   2432: invokevirtual 92	java/lang/StringBuilder:toString	()Ljava/lang/String;
/*      */     //   2435: invokevirtual 151	org/compiere/util/CLogger:fine	(Ljava/lang/String;)V
/*      */     //   2438: new 81	java/lang/StringBuilder
/*      */     //   2441: dup
/*      */     //   2442: ldc -70
/*      */     //   2444: invokespecial 85	java/lang/StringBuilder:<init>	(Ljava/lang/String;)V
/*      */     //   2447: ldc_w 391
/*      */     //   2450: invokevirtual 88	java/lang/StringBuilder:append	(Ljava/lang/String;)Ljava/lang/StringBuilder;
/*      */     //   2453: ldc_w 393
/*      */     //   2456: invokevirtual 88	java/lang/StringBuilder:append	(Ljava/lang/String;)Ljava/lang/StringBuilder;
/*      */     //   2459: ldc_w 395
/*      */     //   2462: invokevirtual 88	java/lang/StringBuilder:append	(Ljava/lang/String;)Ljava/lang/StringBuilder;
/*      */     //   2465: ldc_w 397
/*      */     //   2468: invokevirtual 88	java/lang/StringBuilder:append	(Ljava/lang/String;)Ljava/lang/StringBuilder;
/*      */     //   2471: ldc_w 399
/*      */     //   2474: invokevirtual 88	java/lang/StringBuilder:append	(Ljava/lang/String;)Ljava/lang/StringBuilder;
/*      */     //   2477: ldc -54
/*      */     //   2479: invokevirtual 88	java/lang/StringBuilder:append	(Ljava/lang/String;)Ljava/lang/StringBuilder;
/*      */     //   2482: aload_3
/*      */     //   2483: invokevirtual 130	java/lang/StringBuilder:append	(Ljava/lang/CharSequence;)Ljava/lang/StringBuilder;
/*      */     //   2486: astore_1
/*      */     //   2487: aload_1
/*      */     //   2488: invokevirtual 92	java/lang/StringBuilder:toString	()Ljava/lang/String;
/*      */     //   2491: aload_0
/*      */     //   2492: invokevirtual 133	com/ghintech/puntocom/process/ImportOrder:get_TrxName	()Ljava/lang/String;
/*      */     //   2495: invokestatic 136	org/compiere/util/DB:executeUpdate	(Ljava/lang/String;Ljava/lang/String;)I
/*      */     //   2498: istore_2
/*      */     //   2499: aload_0
/*      */     //   2500: getfield 71	com/ghintech/puntocom/process/ImportOrder:log	Lorg/compiere/util/CLogger;
/*      */     //   2503: getstatic 142	java/util/logging/Level:FINE	Ljava/util/logging/Level;
/*      */     //   2506: invokevirtual 145	org/compiere/util/CLogger:isLoggable	(Ljava/util/logging/Level;)Z
/*      */     //   2509: ifeq +27 -> 2536
/*      */     //   2512: aload_0
/*      */     //   2513: getfield 71	com/ghintech/puntocom/process/ImportOrder:log	Lorg/compiere/util/CLogger;
/*      */     //   2516: new 81	java/lang/StringBuilder
/*      */     //   2519: dup
/*      */     //   2520: ldc_w 401
/*      */     //   2523: invokespecial 85	java/lang/StringBuilder:<init>	(Ljava/lang/String;)V
/*      */     //   2526: iload_2
/*      */     //   2527: invokevirtual 123	java/lang/StringBuilder:append	(I)Ljava/lang/StringBuilder;
/*      */     //   2530: invokevirtual 92	java/lang/StringBuilder:toString	()Ljava/lang/String;
/*      */     //   2533: invokevirtual 151	org/compiere/util/CLogger:fine	(Ljava/lang/String;)V
/*      */     //   2536: new 81	java/lang/StringBuilder
/*      */     //   2539: dup
/*      */     //   2540: ldc -70
/*      */     //   2542: invokespecial 85	java/lang/StringBuilder:<init>	(Ljava/lang/String;)V
/*      */     //   2545: ldc_w 403
/*      */     //   2548: invokevirtual 88	java/lang/StringBuilder:append	(Ljava/lang/String;)Ljava/lang/StringBuilder;
/*      */     //   2551: ldc_w 393
/*      */     //   2554: invokevirtual 88	java/lang/StringBuilder:append	(Ljava/lang/String;)Ljava/lang/StringBuilder;
/*      */     //   2557: ldc_w 405
/*      */     //   2560: invokevirtual 88	java/lang/StringBuilder:append	(Ljava/lang/String;)Ljava/lang/StringBuilder;
/*      */     //   2563: ldc_w 397
/*      */     //   2566: invokevirtual 88	java/lang/StringBuilder:append	(Ljava/lang/String;)Ljava/lang/StringBuilder;
/*      */     //   2569: ldc_w 385
/*      */     //   2572: invokevirtual 88	java/lang/StringBuilder:append	(Ljava/lang/String;)Ljava/lang/StringBuilder;
/*      */     //   2575: ldc -54
/*      */     //   2577: invokevirtual 88	java/lang/StringBuilder:append	(Ljava/lang/String;)Ljava/lang/StringBuilder;
/*      */     //   2580: aload_3
/*      */     //   2581: invokevirtual 130	java/lang/StringBuilder:append	(Ljava/lang/CharSequence;)Ljava/lang/StringBuilder;
/*      */     //   2584: astore_1
/*      */     //   2585: aload_1
/*      */     //   2586: invokevirtual 92	java/lang/StringBuilder:toString	()Ljava/lang/String;
/*      */     //   2589: aload_0
/*      */     //   2590: invokevirtual 133	com/ghintech/puntocom/process/ImportOrder:get_TrxName	()Ljava/lang/String;
/*      */     //   2593: invokestatic 136	org/compiere/util/DB:executeUpdate	(Ljava/lang/String;Ljava/lang/String;)I
/*      */     //   2596: istore_2
/*      */     //   2597: aload_0
/*      */     //   2598: getfield 71	com/ghintech/puntocom/process/ImportOrder:log	Lorg/compiere/util/CLogger;
/*      */     //   2601: getstatic 142	java/util/logging/Level:FINE	Ljava/util/logging/Level;
/*      */     //   2604: invokevirtual 145	org/compiere/util/CLogger:isLoggable	(Ljava/util/logging/Level;)Z
/*      */     //   2607: ifeq +27 -> 2634
/*      */     //   2610: aload_0
/*      */     //   2611: getfield 71	com/ghintech/puntocom/process/ImportOrder:log	Lorg/compiere/util/CLogger;
/*      */     //   2614: new 81	java/lang/StringBuilder
/*      */     //   2617: dup
/*      */     //   2618: ldc_w 407
/*      */     //   2621: invokespecial 85	java/lang/StringBuilder:<init>	(Ljava/lang/String;)V
/*      */     //   2624: iload_2
/*      */     //   2625: invokevirtual 123	java/lang/StringBuilder:append	(I)Ljava/lang/StringBuilder;
/*      */     //   2628: invokevirtual 92	java/lang/StringBuilder:toString	()Ljava/lang/String;
/*      */     //   2631: invokevirtual 151	org/compiere/util/CLogger:fine	(Ljava/lang/String;)V
/*      */     //   2634: new 81	java/lang/StringBuilder
/*      */     //   2637: dup
/*      */     //   2638: ldc -102
/*      */     //   2640: invokespecial 85	java/lang/StringBuilder:<init>	(Ljava/lang/String;)V
/*      */     //   2643: ldc_w 409
/*      */     //   2646: invokevirtual 88	java/lang/StringBuilder:append	(Ljava/lang/String;)Ljava/lang/StringBuilder;
/*      */     //   2649: ldc_w 411
/*      */     //   2652: invokevirtual 88	java/lang/StringBuilder:append	(Ljava/lang/String;)Ljava/lang/StringBuilder;
/*      */     //   2655: ldc -54
/*      */     //   2657: invokevirtual 88	java/lang/StringBuilder:append	(Ljava/lang/String;)Ljava/lang/StringBuilder;
/*      */     //   2660: aload_3
/*      */     //   2661: invokevirtual 130	java/lang/StringBuilder:append	(Ljava/lang/CharSequence;)Ljava/lang/StringBuilder;
/*      */     //   2664: astore_1
/*      */     //   2665: aload_1
/*      */     //   2666: invokevirtual 92	java/lang/StringBuilder:toString	()Ljava/lang/String;
/*      */     //   2669: aload_0
/*      */     //   2670: invokevirtual 133	com/ghintech/puntocom/process/ImportOrder:get_TrxName	()Ljava/lang/String;
/*      */     //   2673: invokestatic 136	org/compiere/util/DB:executeUpdate	(Ljava/lang/String;Ljava/lang/String;)I
/*      */     //   2676: istore_2
/*      */     //   2677: iload_2
/*      */     //   2678: ifeq +27 -> 2705
/*      */     //   2681: aload_0
/*      */     //   2682: getfield 71	com/ghintech/puntocom/process/ImportOrder:log	Lorg/compiere/util/CLogger;
/*      */     //   2685: new 81	java/lang/StringBuilder
/*      */     //   2688: dup
/*      */     //   2689: ldc_w 413
/*      */     //   2692: invokespecial 85	java/lang/StringBuilder:<init>	(Ljava/lang/String;)V
/*      */     //   2695: iload_2
/*      */     //   2696: invokevirtual 123	java/lang/StringBuilder:append	(I)Ljava/lang/StringBuilder;
/*      */     //   2699: invokevirtual 92	java/lang/StringBuilder:toString	()Ljava/lang/String;
/*      */     //   2702: invokevirtual 206	org/compiere/util/CLogger:warning	(Ljava/lang/String;)V
/*      */     //   2705: new 81	java/lang/StringBuilder
/*      */     //   2708: dup
/*      */     //   2709: ldc -70
/*      */     //   2711: invokespecial 85	java/lang/StringBuilder:<init>	(Ljava/lang/String;)V
/*      */     //   2714: ldc_w 415
/*      */     //   2717: invokevirtual 88	java/lang/StringBuilder:append	(Ljava/lang/String;)Ljava/lang/StringBuilder;
/*      */     //   2720: ldc_w 417
/*      */     //   2723: invokevirtual 88	java/lang/StringBuilder:append	(Ljava/lang/String;)Ljava/lang/StringBuilder;
/*      */     //   2726: ldc_w 419
/*      */     //   2729: invokevirtual 88	java/lang/StringBuilder:append	(Ljava/lang/String;)Ljava/lang/StringBuilder;
/*      */     //   2732: ldc -54
/*      */     //   2734: invokevirtual 88	java/lang/StringBuilder:append	(Ljava/lang/String;)Ljava/lang/StringBuilder;
/*      */     //   2737: aload_3
/*      */     //   2738: invokevirtual 130	java/lang/StringBuilder:append	(Ljava/lang/CharSequence;)Ljava/lang/StringBuilder;
/*      */     //   2741: astore_1
/*      */     //   2742: aload_1
/*      */     //   2743: invokevirtual 92	java/lang/StringBuilder:toString	()Ljava/lang/String;
/*      */     //   2746: aload_0
/*      */     //   2747: invokevirtual 133	com/ghintech/puntocom/process/ImportOrder:get_TrxName	()Ljava/lang/String;
/*      */     //   2750: invokestatic 136	org/compiere/util/DB:executeUpdate	(Ljava/lang/String;Ljava/lang/String;)I
/*      */     //   2753: istore_2
/*      */     //   2754: aload_0
/*      */     //   2755: getfield 71	com/ghintech/puntocom/process/ImportOrder:log	Lorg/compiere/util/CLogger;
/*      */     //   2758: getstatic 142	java/util/logging/Level:FINE	Ljava/util/logging/Level;
/*      */     //   2761: invokevirtual 145	org/compiere/util/CLogger:isLoggable	(Ljava/util/logging/Level;)Z
/*      */     //   2764: ifeq +27 -> 2791
/*      */     //   2767: aload_0
/*      */     //   2768: getfield 71	com/ghintech/puntocom/process/ImportOrder:log	Lorg/compiere/util/CLogger;
/*      */     //   2771: new 81	java/lang/StringBuilder
/*      */     //   2774: dup
/*      */     //   2775: ldc_w 421
/*      */     //   2778: invokespecial 85	java/lang/StringBuilder:<init>	(Ljava/lang/String;)V
/*      */     //   2781: iload_2
/*      */     //   2782: invokevirtual 123	java/lang/StringBuilder:append	(I)Ljava/lang/StringBuilder;
/*      */     //   2785: invokevirtual 92	java/lang/StringBuilder:toString	()Ljava/lang/String;
/*      */     //   2788: invokevirtual 151	org/compiere/util/CLogger:fine	(Ljava/lang/String;)V
/*      */     //   2791: new 81	java/lang/StringBuilder
/*      */     //   2794: dup
/*      */     //   2795: ldc -102
/*      */     //   2797: invokespecial 85	java/lang/StringBuilder:<init>	(Ljava/lang/String;)V
/*      */     //   2800: ldc_w 423
/*      */     //   2803: invokevirtual 88	java/lang/StringBuilder:append	(Ljava/lang/String;)Ljava/lang/StringBuilder;
/*      */     //   2806: ldc_w 425
/*      */     //   2809: invokevirtual 88	java/lang/StringBuilder:append	(Ljava/lang/String;)Ljava/lang/StringBuilder;
/*      */     //   2812: ldc -54
/*      */     //   2814: invokevirtual 88	java/lang/StringBuilder:append	(Ljava/lang/String;)Ljava/lang/StringBuilder;
/*      */     //   2817: aload_3
/*      */     //   2818: invokevirtual 130	java/lang/StringBuilder:append	(Ljava/lang/CharSequence;)Ljava/lang/StringBuilder;
/*      */     //   2821: astore_1
/*      */     //   2822: aload_1
/*      */     //   2823: invokevirtual 92	java/lang/StringBuilder:toString	()Ljava/lang/String;
/*      */     //   2826: aload_0
/*      */     //   2827: invokevirtual 133	com/ghintech/puntocom/process/ImportOrder:get_TrxName	()Ljava/lang/String;
/*      */     //   2830: invokestatic 136	org/compiere/util/DB:executeUpdate	(Ljava/lang/String;Ljava/lang/String;)I
/*      */     //   2833: istore_2
/*      */     //   2834: iload_2
/*      */     //   2835: ifeq +27 -> 2862
/*      */     //   2838: aload_0
/*      */     //   2839: getfield 71	com/ghintech/puntocom/process/ImportOrder:log	Lorg/compiere/util/CLogger;
/*      */     //   2842: new 81	java/lang/StringBuilder
/*      */     //   2845: dup
/*      */     //   2846: ldc_w 427
/*      */     //   2849: invokespecial 85	java/lang/StringBuilder:<init>	(Ljava/lang/String;)V
/*      */     //   2852: iload_2
/*      */     //   2853: invokevirtual 123	java/lang/StringBuilder:append	(I)Ljava/lang/StringBuilder;
/*      */     //   2856: invokevirtual 92	java/lang/StringBuilder:toString	()Ljava/lang/String;
/*      */     //   2859: invokevirtual 206	org/compiere/util/CLogger:warning	(Ljava/lang/String;)V
/*      */     //   2862: new 81	java/lang/StringBuilder
/*      */     //   2865: dup
/*      */     //   2866: ldc -70
/*      */     //   2868: invokespecial 85	java/lang/StringBuilder:<init>	(Ljava/lang/String;)V
/*      */     //   2871: ldc_w 429
/*      */     //   2874: invokevirtual 88	java/lang/StringBuilder:append	(Ljava/lang/String;)Ljava/lang/StringBuilder;
/*      */     //   2877: ldc_w 431
/*      */     //   2880: invokevirtual 88	java/lang/StringBuilder:append	(Ljava/lang/String;)Ljava/lang/StringBuilder;
/*      */     //   2883: ldc_w 433
/*      */     //   2886: invokevirtual 88	java/lang/StringBuilder:append	(Ljava/lang/String;)Ljava/lang/StringBuilder;
/*      */     //   2889: ldc_w 435
/*      */     //   2892: invokevirtual 88	java/lang/StringBuilder:append	(Ljava/lang/String;)Ljava/lang/StringBuilder;
/*      */     //   2895: ldc -54
/*      */     //   2897: invokevirtual 88	java/lang/StringBuilder:append	(Ljava/lang/String;)Ljava/lang/StringBuilder;
/*      */     //   2900: aload_3
/*      */     //   2901: invokevirtual 130	java/lang/StringBuilder:append	(Ljava/lang/CharSequence;)Ljava/lang/StringBuilder;
/*      */     //   2904: astore_1
/*      */     //   2905: aload_1
/*      */     //   2906: invokevirtual 92	java/lang/StringBuilder:toString	()Ljava/lang/String;
/*      */     //   2909: aload_0
/*      */     //   2910: invokevirtual 133	com/ghintech/puntocom/process/ImportOrder:get_TrxName	()Ljava/lang/String;
/*      */     //   2913: invokestatic 136	org/compiere/util/DB:executeUpdate	(Ljava/lang/String;Ljava/lang/String;)I
/*      */     //   2916: istore_2
/*      */     //   2917: aload_0
/*      */     //   2918: getfield 71	com/ghintech/puntocom/process/ImportOrder:log	Lorg/compiere/util/CLogger;
/*      */     //   2921: getstatic 142	java/util/logging/Level:FINE	Ljava/util/logging/Level;
/*      */     //   2924: invokevirtual 145	org/compiere/util/CLogger:isLoggable	(Ljava/util/logging/Level;)Z
/*      */     //   2927: ifeq +27 -> 2954
/*      */     //   2930: aload_0
/*      */     //   2931: getfield 71	com/ghintech/puntocom/process/ImportOrder:log	Lorg/compiere/util/CLogger;
/*      */     //   2934: new 81	java/lang/StringBuilder
/*      */     //   2937: dup
/*      */     //   2938: ldc_w 437
/*      */     //   2941: invokespecial 85	java/lang/StringBuilder:<init>	(Ljava/lang/String;)V
/*      */     //   2944: iload_2
/*      */     //   2945: invokevirtual 123	java/lang/StringBuilder:append	(I)Ljava/lang/StringBuilder;
/*      */     //   2948: invokevirtual 92	java/lang/StringBuilder:toString	()Ljava/lang/String;
/*      */     //   2951: invokevirtual 151	org/compiere/util/CLogger:fine	(Ljava/lang/String;)V
/*      */     //   2954: new 81	java/lang/StringBuilder
/*      */     //   2957: dup
/*      */     //   2958: ldc -70
/*      */     //   2960: invokespecial 85	java/lang/StringBuilder:<init>	(Ljava/lang/String;)V
/*      */     //   2963: ldc_w 439
/*      */     //   2966: invokevirtual 88	java/lang/StringBuilder:append	(Ljava/lang/String;)Ljava/lang/StringBuilder;
/*      */     //   2969: ldc_w 441
/*      */     //   2972: invokevirtual 88	java/lang/StringBuilder:append	(Ljava/lang/String;)Ljava/lang/StringBuilder;
/*      */     //   2975: ldc_w 433
/*      */     //   2978: invokevirtual 88	java/lang/StringBuilder:append	(Ljava/lang/String;)Ljava/lang/StringBuilder;
/*      */     //   2981: ldc_w 443
/*      */     //   2984: invokevirtual 88	java/lang/StringBuilder:append	(Ljava/lang/String;)Ljava/lang/StringBuilder;
/*      */     //   2987: ldc -54
/*      */     //   2989: invokevirtual 88	java/lang/StringBuilder:append	(Ljava/lang/String;)Ljava/lang/StringBuilder;
/*      */     //   2992: aload_3
/*      */     //   2993: invokevirtual 130	java/lang/StringBuilder:append	(Ljava/lang/CharSequence;)Ljava/lang/StringBuilder;
/*      */     //   2996: astore_1
/*      */     //   2997: aload_1
/*      */     //   2998: invokevirtual 92	java/lang/StringBuilder:toString	()Ljava/lang/String;
/*      */     //   3001: aload_0
/*      */     //   3002: invokevirtual 133	com/ghintech/puntocom/process/ImportOrder:get_TrxName	()Ljava/lang/String;
/*      */     //   3005: invokestatic 136	org/compiere/util/DB:executeUpdate	(Ljava/lang/String;Ljava/lang/String;)I
/*      */     //   3008: istore_2
/*      */     //   3009: aload_0
/*      */     //   3010: getfield 71	com/ghintech/puntocom/process/ImportOrder:log	Lorg/compiere/util/CLogger;
/*      */     //   3013: getstatic 142	java/util/logging/Level:FINE	Ljava/util/logging/Level;
/*      */     //   3016: invokevirtual 145	org/compiere/util/CLogger:isLoggable	(Ljava/util/logging/Level;)Z
/*      */     //   3019: ifeq +27 -> 3046
/*      */     //   3022: aload_0
/*      */     //   3023: getfield 71	com/ghintech/puntocom/process/ImportOrder:log	Lorg/compiere/util/CLogger;
/*      */     //   3026: new 81	java/lang/StringBuilder
/*      */     //   3029: dup
/*      */     //   3030: ldc_w 445
/*      */     //   3033: invokespecial 85	java/lang/StringBuilder:<init>	(Ljava/lang/String;)V
/*      */     //   3036: iload_2
/*      */     //   3037: invokevirtual 123	java/lang/StringBuilder:append	(I)Ljava/lang/StringBuilder;
/*      */     //   3040: invokevirtual 92	java/lang/StringBuilder:toString	()Ljava/lang/String;
/*      */     //   3043: invokevirtual 151	org/compiere/util/CLogger:fine	(Ljava/lang/String;)V
/*      */     //   3046: new 81	java/lang/StringBuilder
/*      */     //   3049: dup
/*      */     //   3050: ldc -70
/*      */     //   3052: invokespecial 85	java/lang/StringBuilder:<init>	(Ljava/lang/String;)V
/*      */     //   3055: ldc_w 447
/*      */     //   3058: invokevirtual 88	java/lang/StringBuilder:append	(Ljava/lang/String;)Ljava/lang/StringBuilder;
/*      */     //   3061: ldc_w 449
/*      */     //   3064: invokevirtual 88	java/lang/StringBuilder:append	(Ljava/lang/String;)Ljava/lang/StringBuilder;
/*      */     //   3067: ldc_w 451
/*      */     //   3070: invokevirtual 88	java/lang/StringBuilder:append	(Ljava/lang/String;)Ljava/lang/StringBuilder;
/*      */     //   3073: ldc_w 453
/*      */     //   3076: invokevirtual 88	java/lang/StringBuilder:append	(Ljava/lang/String;)Ljava/lang/StringBuilder;
/*      */     //   3079: ldc -54
/*      */     //   3081: invokevirtual 88	java/lang/StringBuilder:append	(Ljava/lang/String;)Ljava/lang/StringBuilder;
/*      */     //   3084: aload_3
/*      */     //   3085: invokevirtual 130	java/lang/StringBuilder:append	(Ljava/lang/CharSequence;)Ljava/lang/StringBuilder;
/*      */     //   3088: astore_1
/*      */     //   3089: aload_1
/*      */     //   3090: invokevirtual 92	java/lang/StringBuilder:toString	()Ljava/lang/String;
/*      */     //   3093: aload_0
/*      */     //   3094: invokevirtual 133	com/ghintech/puntocom/process/ImportOrder:get_TrxName	()Ljava/lang/String;
/*      */     //   3097: invokestatic 136	org/compiere/util/DB:executeUpdate	(Ljava/lang/String;Ljava/lang/String;)I
/*      */     //   3100: istore_2
/*      */     //   3101: iload_2
/*      */     //   3102: ifeq +27 -> 3129
/*      */     //   3105: aload_0
/*      */     //   3106: getfield 71	com/ghintech/puntocom/process/ImportOrder:log	Lorg/compiere/util/CLogger;
/*      */     //   3109: new 81	java/lang/StringBuilder
/*      */     //   3112: dup
/*      */     //   3113: ldc_w 455
/*      */     //   3116: invokespecial 85	java/lang/StringBuilder:<init>	(Ljava/lang/String;)V
/*      */     //   3119: iload_2
/*      */     //   3120: invokevirtual 123	java/lang/StringBuilder:append	(I)Ljava/lang/StringBuilder;
/*      */     //   3123: invokevirtual 92	java/lang/StringBuilder:toString	()Ljava/lang/String;
/*      */     //   3126: invokevirtual 206	org/compiere/util/CLogger:warning	(Ljava/lang/String;)V
/*      */     //   3129: new 81	java/lang/StringBuilder
/*      */     //   3132: dup
/*      */     //   3133: ldc -70
/*      */     //   3135: invokespecial 85	java/lang/StringBuilder:<init>	(Ljava/lang/String;)V
/*      */     //   3138: ldc_w 457
/*      */     //   3141: invokevirtual 88	java/lang/StringBuilder:append	(Ljava/lang/String;)Ljava/lang/StringBuilder;
/*      */     //   3144: ldc_w 459
/*      */     //   3147: invokevirtual 88	java/lang/StringBuilder:append	(Ljava/lang/String;)Ljava/lang/StringBuilder;
/*      */     //   3150: ldc_w 461
/*      */     //   3153: invokevirtual 88	java/lang/StringBuilder:append	(Ljava/lang/String;)Ljava/lang/StringBuilder;
/*      */     //   3156: ldc -54
/*      */     //   3158: invokevirtual 88	java/lang/StringBuilder:append	(Ljava/lang/String;)Ljava/lang/StringBuilder;
/*      */     //   3161: aload_3
/*      */     //   3162: invokevirtual 130	java/lang/StringBuilder:append	(Ljava/lang/CharSequence;)Ljava/lang/StringBuilder;
/*      */     //   3165: astore_1
/*      */     //   3166: aload_1
/*      */     //   3167: invokevirtual 92	java/lang/StringBuilder:toString	()Ljava/lang/String;
/*      */     //   3170: aload_0
/*      */     //   3171: invokevirtual 133	com/ghintech/puntocom/process/ImportOrder:get_TrxName	()Ljava/lang/String;
/*      */     //   3174: invokestatic 136	org/compiere/util/DB:executeUpdate	(Ljava/lang/String;Ljava/lang/String;)I
/*      */     //   3177: istore_2
/*      */     //   3178: aload_0
/*      */     //   3179: getfield 71	com/ghintech/puntocom/process/ImportOrder:log	Lorg/compiere/util/CLogger;
/*      */     //   3182: getstatic 142	java/util/logging/Level:FINE	Ljava/util/logging/Level;
/*      */     //   3185: invokevirtual 145	org/compiere/util/CLogger:isLoggable	(Ljava/util/logging/Level;)Z
/*      */     //   3188: ifeq +27 -> 3215
/*      */     //   3191: aload_0
/*      */     //   3192: getfield 71	com/ghintech/puntocom/process/ImportOrder:log	Lorg/compiere/util/CLogger;
/*      */     //   3195: new 81	java/lang/StringBuilder
/*      */     //   3198: dup
/*      */     //   3199: ldc_w 463
/*      */     //   3202: invokespecial 85	java/lang/StringBuilder:<init>	(Ljava/lang/String;)V
/*      */     //   3205: iload_2
/*      */     //   3206: invokevirtual 123	java/lang/StringBuilder:append	(I)Ljava/lang/StringBuilder;
/*      */     //   3209: invokevirtual 92	java/lang/StringBuilder:toString	()Ljava/lang/String;
/*      */     //   3212: invokevirtual 151	org/compiere/util/CLogger:fine	(Ljava/lang/String;)V
/*      */     //   3215: new 81	java/lang/StringBuilder
/*      */     //   3218: dup
/*      */     //   3219: ldc -70
/*      */     //   3221: invokespecial 85	java/lang/StringBuilder:<init>	(Ljava/lang/String;)V
/*      */     //   3224: ldc_w 457
/*      */     //   3227: invokevirtual 88	java/lang/StringBuilder:append	(Ljava/lang/String;)Ljava/lang/StringBuilder;
/*      */     //   3230: ldc_w 465
/*      */     //   3233: invokevirtual 88	java/lang/StringBuilder:append	(Ljava/lang/String;)Ljava/lang/StringBuilder;
/*      */     //   3236: ldc_w 467
/*      */     //   3239: invokevirtual 88	java/lang/StringBuilder:append	(Ljava/lang/String;)Ljava/lang/StringBuilder;
/*      */     //   3242: ldc -54
/*      */     //   3244: invokevirtual 88	java/lang/StringBuilder:append	(Ljava/lang/String;)Ljava/lang/StringBuilder;
/*      */     //   3247: aload_3
/*      */     //   3248: invokevirtual 130	java/lang/StringBuilder:append	(Ljava/lang/CharSequence;)Ljava/lang/StringBuilder;
/*      */     //   3251: astore_1
/*      */     //   3252: aload_1
/*      */     //   3253: invokevirtual 92	java/lang/StringBuilder:toString	()Ljava/lang/String;
/*      */     //   3256: aload_0
/*      */     //   3257: invokevirtual 133	com/ghintech/puntocom/process/ImportOrder:get_TrxName	()Ljava/lang/String;
/*      */     //   3260: invokestatic 136	org/compiere/util/DB:executeUpdate	(Ljava/lang/String;Ljava/lang/String;)I
/*      */     //   3263: istore_2
/*      */     //   3264: aload_0
/*      */     //   3265: getfield 71	com/ghintech/puntocom/process/ImportOrder:log	Lorg/compiere/util/CLogger;
/*      */     //   3268: getstatic 142	java/util/logging/Level:FINE	Ljava/util/logging/Level;
/*      */     //   3271: invokevirtual 145	org/compiere/util/CLogger:isLoggable	(Ljava/util/logging/Level;)Z
/*      */     //   3274: ifeq +27 -> 3301
/*      */     //   3277: aload_0
/*      */     //   3278: getfield 71	com/ghintech/puntocom/process/ImportOrder:log	Lorg/compiere/util/CLogger;
/*      */     //   3281: new 81	java/lang/StringBuilder
/*      */     //   3284: dup
/*      */     //   3285: ldc_w 469
/*      */     //   3288: invokespecial 85	java/lang/StringBuilder:<init>	(Ljava/lang/String;)V
/*      */     //   3291: iload_2
/*      */     //   3292: invokevirtual 123	java/lang/StringBuilder:append	(I)Ljava/lang/StringBuilder;
/*      */     //   3295: invokevirtual 92	java/lang/StringBuilder:toString	()Ljava/lang/String;
/*      */     //   3298: invokevirtual 151	org/compiere/util/CLogger:fine	(Ljava/lang/String;)V
/*      */     //   3301: new 81	java/lang/StringBuilder
/*      */     //   3304: dup
/*      */     //   3305: ldc -70
/*      */     //   3307: invokespecial 85	java/lang/StringBuilder:<init>	(Ljava/lang/String;)V
/*      */     //   3310: ldc_w 457
/*      */     //   3313: invokevirtual 88	java/lang/StringBuilder:append	(Ljava/lang/String;)Ljava/lang/StringBuilder;
/*      */     //   3316: ldc_w 471
/*      */     //   3319: invokevirtual 88	java/lang/StringBuilder:append	(Ljava/lang/String;)Ljava/lang/StringBuilder;
/*      */     //   3322: ldc_w 473
/*      */     //   3325: invokevirtual 88	java/lang/StringBuilder:append	(Ljava/lang/String;)Ljava/lang/StringBuilder;
/*      */     //   3328: ldc -54
/*      */     //   3330: invokevirtual 88	java/lang/StringBuilder:append	(Ljava/lang/String;)Ljava/lang/StringBuilder;
/*      */     //   3333: aload_3
/*      */     //   3334: invokevirtual 130	java/lang/StringBuilder:append	(Ljava/lang/CharSequence;)Ljava/lang/StringBuilder;
/*      */     //   3337: astore_1
/*      */     //   3338: aload_1
/*      */     //   3339: invokevirtual 92	java/lang/StringBuilder:toString	()Ljava/lang/String;
/*      */     //   3342: aload_0
/*      */     //   3343: invokevirtual 133	com/ghintech/puntocom/process/ImportOrder:get_TrxName	()Ljava/lang/String;
/*      */     //   3346: invokestatic 136	org/compiere/util/DB:executeUpdate	(Ljava/lang/String;Ljava/lang/String;)I
/*      */     //   3349: istore_2
/*      */     //   3350: aload_0
/*      */     //   3351: getfield 71	com/ghintech/puntocom/process/ImportOrder:log	Lorg/compiere/util/CLogger;
/*      */     //   3354: getstatic 142	java/util/logging/Level:FINE	Ljava/util/logging/Level;
/*      */     //   3357: invokevirtual 145	org/compiere/util/CLogger:isLoggable	(Ljava/util/logging/Level;)Z
/*      */     //   3360: ifeq +27 -> 3387
/*      */     //   3363: aload_0
/*      */     //   3364: getfield 71	com/ghintech/puntocom/process/ImportOrder:log	Lorg/compiere/util/CLogger;
/*      */     //   3367: new 81	java/lang/StringBuilder
/*      */     //   3370: dup
/*      */     //   3371: ldc_w 475
/*      */     //   3374: invokespecial 85	java/lang/StringBuilder:<init>	(Ljava/lang/String;)V
/*      */     //   3377: iload_2
/*      */     //   3378: invokevirtual 123	java/lang/StringBuilder:append	(I)Ljava/lang/StringBuilder;
/*      */     //   3381: invokevirtual 92	java/lang/StringBuilder:toString	()Ljava/lang/String;
/*      */     //   3384: invokevirtual 151	org/compiere/util/CLogger:fine	(Ljava/lang/String;)V
/*      */     //   3387: new 81	java/lang/StringBuilder
/*      */     //   3390: dup
/*      */     //   3391: ldc -102
/*      */     //   3393: invokespecial 85	java/lang/StringBuilder:<init>	(Ljava/lang/String;)V
/*      */     //   3396: ldc_w 477
/*      */     //   3399: invokevirtual 88	java/lang/StringBuilder:append	(Ljava/lang/String;)Ljava/lang/StringBuilder;
/*      */     //   3402: ldc_w 479
/*      */     //   3405: invokevirtual 88	java/lang/StringBuilder:append	(Ljava/lang/String;)Ljava/lang/StringBuilder;
/*      */     //   3408: ldc -54
/*      */     //   3410: invokevirtual 88	java/lang/StringBuilder:append	(Ljava/lang/String;)Ljava/lang/StringBuilder;
/*      */     //   3413: aload_3
/*      */     //   3414: invokevirtual 130	java/lang/StringBuilder:append	(Ljava/lang/CharSequence;)Ljava/lang/StringBuilder;
/*      */     //   3417: astore_1
/*      */     //   3418: aload_1
/*      */     //   3419: invokevirtual 92	java/lang/StringBuilder:toString	()Ljava/lang/String;
/*      */     //   3422: aload_0
/*      */     //   3423: invokevirtual 133	com/ghintech/puntocom/process/ImportOrder:get_TrxName	()Ljava/lang/String;
/*      */     //   3426: invokestatic 136	org/compiere/util/DB:executeUpdate	(Ljava/lang/String;Ljava/lang/String;)I
/*      */     //   3429: istore_2
/*      */     //   3430: iload_2
/*      */     //   3431: ifeq +27 -> 3458
/*      */     //   3434: aload_0
/*      */     //   3435: getfield 71	com/ghintech/puntocom/process/ImportOrder:log	Lorg/compiere/util/CLogger;
/*      */     //   3438: new 81	java/lang/StringBuilder
/*      */     //   3441: dup
/*      */     //   3442: ldc_w 481
/*      */     //   3445: invokespecial 85	java/lang/StringBuilder:<init>	(Ljava/lang/String;)V
/*      */     //   3448: iload_2
/*      */     //   3449: invokevirtual 123	java/lang/StringBuilder:append	(I)Ljava/lang/StringBuilder;
/*      */     //   3452: invokevirtual 92	java/lang/StringBuilder:toString	()Ljava/lang/String;
/*      */     //   3455: invokevirtual 206	org/compiere/util/CLogger:warning	(Ljava/lang/String;)V
/*      */     //   3458: new 81	java/lang/StringBuilder
/*      */     //   3461: dup
/*      */     //   3462: ldc -70
/*      */     //   3464: invokespecial 85	java/lang/StringBuilder:<init>	(Ljava/lang/String;)V
/*      */     //   3467: ldc_w 483
/*      */     //   3470: invokevirtual 88	java/lang/StringBuilder:append	(Ljava/lang/String;)Ljava/lang/StringBuilder;
/*      */     //   3473: ldc_w 485
/*      */     //   3476: invokevirtual 88	java/lang/StringBuilder:append	(Ljava/lang/String;)Ljava/lang/StringBuilder;
/*      */     //   3479: ldc_w 487
/*      */     //   3482: invokevirtual 88	java/lang/StringBuilder:append	(Ljava/lang/String;)Ljava/lang/StringBuilder;
/*      */     //   3485: aload_3
/*      */     //   3486: invokevirtual 130	java/lang/StringBuilder:append	(Ljava/lang/CharSequence;)Ljava/lang/StringBuilder;
/*      */     //   3489: astore_1
/*      */     //   3490: aload_1
/*      */     //   3491: invokevirtual 92	java/lang/StringBuilder:toString	()Ljava/lang/String;
/*      */     //   3494: aload_0
/*      */     //   3495: invokevirtual 133	com/ghintech/puntocom/process/ImportOrder:get_TrxName	()Ljava/lang/String;
/*      */     //   3498: invokestatic 136	org/compiere/util/DB:executeUpdate	(Ljava/lang/String;Ljava/lang/String;)I
/*      */     //   3501: istore_2
/*      */     //   3502: aload_0
/*      */     //   3503: getfield 71	com/ghintech/puntocom/process/ImportOrder:log	Lorg/compiere/util/CLogger;
/*      */     //   3506: getstatic 142	java/util/logging/Level:FINE	Ljava/util/logging/Level;
/*      */     //   3509: invokevirtual 145	org/compiere/util/CLogger:isLoggable	(Ljava/util/logging/Level;)Z
/*      */     //   3512: ifeq +27 -> 3539
/*      */     //   3515: aload_0
/*      */     //   3516: getfield 71	com/ghintech/puntocom/process/ImportOrder:log	Lorg/compiere/util/CLogger;
/*      */     //   3519: new 81	java/lang/StringBuilder
/*      */     //   3522: dup
/*      */     //   3523: ldc_w 489
/*      */     //   3526: invokespecial 85	java/lang/StringBuilder:<init>	(Ljava/lang/String;)V
/*      */     //   3529: iload_2
/*      */     //   3530: invokevirtual 123	java/lang/StringBuilder:append	(I)Ljava/lang/StringBuilder;
/*      */     //   3533: invokevirtual 92	java/lang/StringBuilder:toString	()Ljava/lang/String;
/*      */     //   3536: invokevirtual 151	org/compiere/util/CLogger:fine	(Ljava/lang/String;)V
/*      */     //   3539: new 81	java/lang/StringBuilder
/*      */     //   3542: dup
/*      */     //   3543: ldc -102
/*      */     //   3545: invokespecial 85	java/lang/StringBuilder:<init>	(Ljava/lang/String;)V
/*      */     //   3548: ldc_w 491
/*      */     //   3551: invokevirtual 88	java/lang/StringBuilder:append	(Ljava/lang/String;)Ljava/lang/StringBuilder;
/*      */     //   3554: ldc_w 493
/*      */     //   3557: invokevirtual 88	java/lang/StringBuilder:append	(Ljava/lang/String;)Ljava/lang/StringBuilder;
/*      */     //   3560: ldc -54
/*      */     //   3562: invokevirtual 88	java/lang/StringBuilder:append	(Ljava/lang/String;)Ljava/lang/StringBuilder;
/*      */     //   3565: aload_3
/*      */     //   3566: invokevirtual 130	java/lang/StringBuilder:append	(Ljava/lang/CharSequence;)Ljava/lang/StringBuilder;
/*      */     //   3569: astore_1
/*      */     //   3570: aload_1
/*      */     //   3571: invokevirtual 92	java/lang/StringBuilder:toString	()Ljava/lang/String;
/*      */     //   3574: aload_0
/*      */     //   3575: invokevirtual 133	com/ghintech/puntocom/process/ImportOrder:get_TrxName	()Ljava/lang/String;
/*      */     //   3578: invokestatic 136	org/compiere/util/DB:executeUpdate	(Ljava/lang/String;Ljava/lang/String;)I
/*      */     //   3581: istore_2
/*      */     //   3582: iload_2
/*      */     //   3583: ifeq +27 -> 3610
/*      */     //   3586: aload_0
/*      */     //   3587: getfield 71	com/ghintech/puntocom/process/ImportOrder:log	Lorg/compiere/util/CLogger;
/*      */     //   3590: new 81	java/lang/StringBuilder
/*      */     //   3593: dup
/*      */     //   3594: ldc_w 495
/*      */     //   3597: invokespecial 85	java/lang/StringBuilder:<init>	(Ljava/lang/String;)V
/*      */     //   3600: iload_2
/*      */     //   3601: invokevirtual 123	java/lang/StringBuilder:append	(I)Ljava/lang/StringBuilder;
/*      */     //   3604: invokevirtual 92	java/lang/StringBuilder:toString	()Ljava/lang/String;
/*      */     //   3607: invokevirtual 206	org/compiere/util/CLogger:warning	(Ljava/lang/String;)V
/*      */     //   3610: new 81	java/lang/StringBuilder
/*      */     //   3613: dup
/*      */     //   3614: ldc -102
/*      */     //   3616: invokespecial 85	java/lang/StringBuilder:<init>	(Ljava/lang/String;)V
/*      */     //   3619: ldc_w 497
/*      */     //   3622: invokevirtual 88	java/lang/StringBuilder:append	(Ljava/lang/String;)Ljava/lang/StringBuilder;
/*      */     //   3625: ldc_w 499
/*      */     //   3628: invokevirtual 88	java/lang/StringBuilder:append	(Ljava/lang/String;)Ljava/lang/StringBuilder;
/*      */     //   3631: ldc -54
/*      */     //   3633: invokevirtual 88	java/lang/StringBuilder:append	(Ljava/lang/String;)Ljava/lang/StringBuilder;
/*      */     //   3636: aload_3
/*      */     //   3637: invokevirtual 130	java/lang/StringBuilder:append	(Ljava/lang/CharSequence;)Ljava/lang/StringBuilder;
/*      */     //   3640: astore_1
/*      */     //   3641: aload_1
/*      */     //   3642: invokevirtual 92	java/lang/StringBuilder:toString	()Ljava/lang/String;
/*      */     //   3645: aload_0
/*      */     //   3646: invokevirtual 133	com/ghintech/puntocom/process/ImportOrder:get_TrxName	()Ljava/lang/String;
/*      */     //   3649: invokestatic 136	org/compiere/util/DB:executeUpdate	(Ljava/lang/String;Ljava/lang/String;)I
/*      */     //   3652: istore_2
/*      */     //   3653: iload_2
/*      */     //   3654: ifeq +27 -> 3681
/*      */     //   3657: aload_0
/*      */     //   3658: getfield 71	com/ghintech/puntocom/process/ImportOrder:log	Lorg/compiere/util/CLogger;
/*      */     //   3661: new 81	java/lang/StringBuilder
/*      */     //   3664: dup
/*      */     //   3665: ldc_w 501
/*      */     //   3668: invokespecial 85	java/lang/StringBuilder:<init>	(Ljava/lang/String;)V
/*      */     //   3671: iload_2
/*      */     //   3672: invokevirtual 123	java/lang/StringBuilder:append	(I)Ljava/lang/StringBuilder;
/*      */     //   3675: invokevirtual 92	java/lang/StringBuilder:toString	()Ljava/lang/String;
/*      */     //   3678: invokevirtual 206	org/compiere/util/CLogger:warning	(Ljava/lang/String;)V
/*      */     //   3681: new 81	java/lang/StringBuilder
/*      */     //   3684: dup
/*      */     //   3685: ldc -70
/*      */     //   3687: invokespecial 85	java/lang/StringBuilder:<init>	(Ljava/lang/String;)V
/*      */     //   3690: ldc_w 503
/*      */     //   3693: invokevirtual 88	java/lang/StringBuilder:append	(Ljava/lang/String;)Ljava/lang/StringBuilder;
/*      */     //   3696: ldc_w 505
/*      */     //   3699: invokevirtual 88	java/lang/StringBuilder:append	(Ljava/lang/String;)Ljava/lang/StringBuilder;
/*      */     //   3702: ldc_w 507
/*      */     //   3705: invokevirtual 88	java/lang/StringBuilder:append	(Ljava/lang/String;)Ljava/lang/StringBuilder;
/*      */     //   3708: ldc -54
/*      */     //   3710: invokevirtual 88	java/lang/StringBuilder:append	(Ljava/lang/String;)Ljava/lang/StringBuilder;
/*      */     //   3713: aload_3
/*      */     //   3714: invokevirtual 130	java/lang/StringBuilder:append	(Ljava/lang/CharSequence;)Ljava/lang/StringBuilder;
/*      */     //   3717: astore_1
/*      */     //   3718: aload_1
/*      */     //   3719: invokevirtual 92	java/lang/StringBuilder:toString	()Ljava/lang/String;
/*      */     //   3722: aload_0
/*      */     //   3723: invokevirtual 133	com/ghintech/puntocom/process/ImportOrder:get_TrxName	()Ljava/lang/String;
/*      */     //   3726: invokestatic 136	org/compiere/util/DB:executeUpdate	(Ljava/lang/String;Ljava/lang/String;)I
/*      */     //   3729: istore_2
/*      */     //   3730: aload_0
/*      */     //   3731: getfield 71	com/ghintech/puntocom/process/ImportOrder:log	Lorg/compiere/util/CLogger;
/*      */     //   3734: getstatic 142	java/util/logging/Level:FINE	Ljava/util/logging/Level;
/*      */     //   3737: invokevirtual 145	org/compiere/util/CLogger:isLoggable	(Ljava/util/logging/Level;)Z
/*      */     //   3740: ifeq +27 -> 3767
/*      */     //   3743: aload_0
/*      */     //   3744: getfield 71	com/ghintech/puntocom/process/ImportOrder:log	Lorg/compiere/util/CLogger;
/*      */     //   3747: new 81	java/lang/StringBuilder
/*      */     //   3750: dup
/*      */     //   3751: ldc_w 509
/*      */     //   3754: invokespecial 85	java/lang/StringBuilder:<init>	(Ljava/lang/String;)V
/*      */     //   3757: iload_2
/*      */     //   3758: invokevirtual 123	java/lang/StringBuilder:append	(I)Ljava/lang/StringBuilder;
/*      */     //   3761: invokevirtual 92	java/lang/StringBuilder:toString	()Ljava/lang/String;
/*      */     //   3764: invokevirtual 151	org/compiere/util/CLogger:fine	(Ljava/lang/String;)V
/*      */     //   3767: new 81	java/lang/StringBuilder
/*      */     //   3770: dup
/*      */     //   3771: ldc -102
/*      */     //   3773: invokespecial 85	java/lang/StringBuilder:<init>	(Ljava/lang/String;)V
/*      */     //   3776: ldc_w 511
/*      */     //   3779: invokevirtual 88	java/lang/StringBuilder:append	(Ljava/lang/String;)Ljava/lang/StringBuilder;
/*      */     //   3782: ldc_w 507
/*      */     //   3785: invokevirtual 88	java/lang/StringBuilder:append	(Ljava/lang/String;)Ljava/lang/StringBuilder;
/*      */     //   3788: ldc -54
/*      */     //   3790: invokevirtual 88	java/lang/StringBuilder:append	(Ljava/lang/String;)Ljava/lang/StringBuilder;
/*      */     //   3793: aload_3
/*      */     //   3794: invokevirtual 130	java/lang/StringBuilder:append	(Ljava/lang/CharSequence;)Ljava/lang/StringBuilder;
/*      */     //   3797: astore_1
/*      */     //   3798: aload_1
/*      */     //   3799: invokevirtual 92	java/lang/StringBuilder:toString	()Ljava/lang/String;
/*      */     //   3802: aload_0
/*      */     //   3803: invokevirtual 133	com/ghintech/puntocom/process/ImportOrder:get_TrxName	()Ljava/lang/String;
/*      */     //   3806: invokestatic 136	org/compiere/util/DB:executeUpdate	(Ljava/lang/String;Ljava/lang/String;)I
/*      */     //   3809: istore_2
/*      */     //   3810: iload_2
/*      */     //   3811: ifeq +27 -> 3838
/*      */     //   3814: aload_0
/*      */     //   3815: getfield 71	com/ghintech/puntocom/process/ImportOrder:log	Lorg/compiere/util/CLogger;
/*      */     //   3818: new 81	java/lang/StringBuilder
/*      */     //   3821: dup
/*      */     //   3822: ldc_w 513
/*      */     //   3825: invokespecial 85	java/lang/StringBuilder:<init>	(Ljava/lang/String;)V
/*      */     //   3828: iload_2
/*      */     //   3829: invokevirtual 123	java/lang/StringBuilder:append	(I)Ljava/lang/StringBuilder;
/*      */     //   3832: invokevirtual 92	java/lang/StringBuilder:toString	()Ljava/lang/String;
/*      */     //   3835: invokevirtual 206	org/compiere/util/CLogger:warning	(Ljava/lang/String;)V
/*      */     //   3838: new 81	java/lang/StringBuilder
/*      */     //   3841: dup
/*      */     //   3842: ldc -102
/*      */     //   3844: invokespecial 85	java/lang/StringBuilder:<init>	(Ljava/lang/String;)V
/*      */     //   3847: ldc_w 515
/*      */     //   3850: invokevirtual 88	java/lang/StringBuilder:append	(Ljava/lang/String;)Ljava/lang/StringBuilder;
/*      */     //   3853: ldc_w 517
/*      */     //   3856: invokevirtual 88	java/lang/StringBuilder:append	(Ljava/lang/String;)Ljava/lang/StringBuilder;
/*      */     //   3859: ldc -54
/*      */     //   3861: invokevirtual 88	java/lang/StringBuilder:append	(Ljava/lang/String;)Ljava/lang/StringBuilder;
/*      */     //   3864: aload_3
/*      */     //   3865: invokevirtual 130	java/lang/StringBuilder:append	(Ljava/lang/CharSequence;)Ljava/lang/StringBuilder;
/*      */     //   3868: astore_1
/*      */     //   3869: aload_1
/*      */     //   3870: invokevirtual 92	java/lang/StringBuilder:toString	()Ljava/lang/String;
/*      */     //   3873: aload_0
/*      */     //   3874: invokevirtual 133	com/ghintech/puntocom/process/ImportOrder:get_TrxName	()Ljava/lang/String;
/*      */     //   3877: invokestatic 136	org/compiere/util/DB:executeUpdate	(Ljava/lang/String;Ljava/lang/String;)I
/*      */     //   3880: istore_2
/*      */     //   3881: iload_2
/*      */     //   3882: ifeq +27 -> 3909
/*      */     //   3885: aload_0
/*      */     //   3886: getfield 71	com/ghintech/puntocom/process/ImportOrder:log	Lorg/compiere/util/CLogger;
/*      */     //   3889: new 81	java/lang/StringBuilder
/*      */     //   3892: dup
/*      */     //   3893: ldc_w 519
/*      */     //   3896: invokespecial 85	java/lang/StringBuilder:<init>	(Ljava/lang/String;)V
/*      */     //   3899: iload_2
/*      */     //   3900: invokevirtual 123	java/lang/StringBuilder:append	(I)Ljava/lang/StringBuilder;
/*      */     //   3903: invokevirtual 92	java/lang/StringBuilder:toString	()Ljava/lang/String;
/*      */     //   3906: invokevirtual 206	org/compiere/util/CLogger:warning	(Ljava/lang/String;)V
/*      */     //   3909: aload_0
/*      */     //   3910: invokevirtual 521	com/ghintech/puntocom/process/ImportOrder:commitEx	()V
/*      */     //   3913: aconst_null
/*      */     //   3914: astore 4
/*      */     //   3916: aconst_null
/*      */     //   3917: astore 5
/*      */     //   3919: new 524	org/compiere/model/Query
/*      */     //   3922: dup
/*      */     //   3923: aload_0
/*      */     //   3924: invokevirtual 526	com/ghintech/puntocom/process/ImportOrder:getCtx	()Ljava/util/Properties;
/*      */     //   3927: ldc_w 530
/*      */     //   3930: ldc_w 532
/*      */     //   3933: aload_0
/*      */     //   3934: invokevirtual 133	com/ghintech/puntocom/process/ImportOrder:get_TrxName	()Ljava/lang/String;
/*      */     //   3937: invokespecial 534	org/compiere/model/Query:<init>	(Ljava/util/Properties;Ljava/lang/String;Ljava/lang/String;Ljava/lang/String;)V
/*      */     //   3940: ldc_w 537
/*      */     //   3943: invokevirtual 539	org/compiere/model/Query:setOrderBy	(Ljava/lang/String;)Lorg/compiere/model/Query;
/*      */     //   3946: invokevirtual 543	org/compiere/model/Query:list	()Ljava/util/List;
/*      */     //   3949: astore 6
/*      */     //   3951: aload 6
/*      */     //   3953: ifnull +1100 -> 5053
/*      */     //   3956: aload 6
/*      */     //   3958: invokeinterface 547 1 0
/*      */     //   3963: astore 8
/*      */     //   3965: goto +1078 -> 5043
/*      */     //   3968: aload 8
/*      */     //   3970: invokeinterface 553 1 0
/*      */     //   3975: checkcast 558	org/compiere/model/X_I_Order
/*      */     //   3978: astore 7
/*      */     //   3980: aload 7
/*      */     //   3982: invokevirtual 560	org/compiere/model/X_I_Order:getBPartnerValue	()Ljava/lang/String;
/*      */     //   3985: ifnonnull +42 -> 4027
/*      */     //   3988: aload 7
/*      */     //   3990: invokevirtual 563	org/compiere/model/X_I_Order:getEMail	()Ljava/lang/String;
/*      */     //   3993: ifnull +16 -> 4009
/*      */     //   3996: aload 7
/*      */     //   3998: aload 7
/*      */     //   4000: invokevirtual 563	org/compiere/model/X_I_Order:getEMail	()Ljava/lang/String;
/*      */     //   4003: invokevirtual 566	org/compiere/model/X_I_Order:setBPartnerValue	(Ljava/lang/String;)V
/*      */     //   4006: goto +21 -> 4027
/*      */     //   4009: aload 7
/*      */     //   4011: invokevirtual 569	org/compiere/model/X_I_Order:getName	()Ljava/lang/String;
/*      */     //   4014: ifnull +1029 -> 5043
/*      */     //   4017: aload 7
/*      */     //   4019: aload 7
/*      */     //   4021: invokevirtual 569	org/compiere/model/X_I_Order:getName	()Ljava/lang/String;
/*      */     //   4024: invokevirtual 566	org/compiere/model/X_I_Order:setBPartnerValue	(Ljava/lang/String;)V
/*      */     //   4027: aload 7
/*      */     //   4029: invokevirtual 569	org/compiere/model/X_I_Order:getName	()Ljava/lang/String;
/*      */     //   4032: ifnonnull +34 -> 4066
/*      */     //   4035: aload 7
/*      */     //   4037: invokevirtual 572	org/compiere/model/X_I_Order:getContactName	()Ljava/lang/String;
/*      */     //   4040: ifnull +16 -> 4056
/*      */     //   4043: aload 7
/*      */     //   4045: aload 7
/*      */     //   4047: invokevirtual 572	org/compiere/model/X_I_Order:getContactName	()Ljava/lang/String;
/*      */     //   4050: invokevirtual 575	org/compiere/model/X_I_Order:setName	(Ljava/lang/String;)V
/*      */     //   4053: goto +13 -> 4066
/*      */     //   4056: aload 7
/*      */     //   4058: aload 7
/*      */     //   4060: invokevirtual 560	org/compiere/model/X_I_Order:getBPartnerValue	()Ljava/lang/String;
/*      */     //   4063: invokevirtual 575	org/compiere/model/X_I_Order:setName	(Ljava/lang/String;)V
/*      */     //   4066: aload_0
/*      */     //   4067: invokevirtual 526	com/ghintech/puntocom/process/ImportOrder:getCtx	()Ljava/util/Properties;
/*      */     //   4070: aload 7
/*      */     //   4072: invokevirtual 560	org/compiere/model/X_I_Order:getBPartnerValue	()Ljava/lang/String;
/*      */     //   4075: invokestatic 578	org/compiere/model/MBPartner:get	(Ljava/util/Properties;Ljava/lang/String;)Lorg/compiere/model/MBPartner;
/*      */     //   4078: astore 9
/*      */     //   4080: aload 9
/*      */     //   4082: ifnonnull +346 -> 4428
/*      */     //   4085: new 579	org/compiere/model/MBPartner
/*      */     //   4088: dup
/*      */     //   4089: aload_0
/*      */     //   4090: invokevirtual 526	com/ghintech/puntocom/process/ImportOrder:getCtx	()Ljava/util/Properties;
/*      */     //   4093: iconst_m1
/*      */     //   4094: aload_0
/*      */     //   4095: invokevirtual 133	com/ghintech/puntocom/process/ImportOrder:get_TrxName	()Ljava/lang/String;
/*      */     //   4098: invokespecial 584	org/compiere/model/MBPartner:<init>	(Ljava/util/Properties;ILjava/lang/String;)V
/*      */     //   4101: astore 9
/*      */     //   4103: aload 9
/*      */     //   4105: aload 7
/*      */     //   4107: invokevirtual 587	org/compiere/model/X_I_Order:getAD_Client_ID	()I
/*      */     //   4110: aload 7
/*      */     //   4112: invokevirtual 590	org/compiere/model/X_I_Order:getAD_Org_ID	()I
/*      */     //   4115: invokevirtual 593	org/compiere/model/MBPartner:setClientOrg	(II)V
/*      */     //   4118: aload 9
/*      */     //   4120: aload 7
/*      */     //   4122: invokevirtual 560	org/compiere/model/X_I_Order:getBPartnerValue	()Ljava/lang/String;
/*      */     //   4125: invokevirtual 597	org/compiere/model/MBPartner:setValue	(Ljava/lang/String;)V
/*      */     //   4128: aload 9
/*      */     //   4130: aload 7
/*      */     //   4132: invokevirtual 560	org/compiere/model/X_I_Order:getBPartnerValue	()Ljava/lang/String;
/*      */     //   4135: invokevirtual 600	org/compiere/model/MBPartner:setTaxID	(Ljava/lang/String;)V
/*      */     //   4138: ldc_w 603
/*      */     //   4141: invokestatic 605	org/compiere/model/MSysConfig:getValue	(Ljava/lang/String;)Ljava/lang/String;
/*      */     //   4144: ldc 67
/*      */     //   4146: invokevirtual 611	java/lang/String:compareTo	(Ljava/lang/String;)I
/*      */     //   4149: ifne +118 -> 4267
/*      */     //   4152: aload 7
/*      */     //   4154: invokevirtual 560	org/compiere/model/X_I_Order:getBPartnerValue	()Ljava/lang/String;
/*      */     //   4157: iconst_0
/*      */     //   4158: invokevirtual 615	java/lang/String:charAt	(I)C
/*      */     //   4161: invokestatic 619	java/lang/String:valueOf	(C)Ljava/lang/String;
/*      */     //   4164: ldc_w 623
/*      */     //   4167: invokevirtual 625	java/lang/String:contains	(Ljava/lang/CharSequence;)Z
/*      */     //   4170: ifne +66 -> 4236
/*      */     //   4173: aload 7
/*      */     //   4175: invokevirtual 560	org/compiere/model/X_I_Order:getBPartnerValue	()Ljava/lang/String;
/*      */     //   4178: iconst_0
/*      */     //   4179: invokevirtual 615	java/lang/String:charAt	(I)C
/*      */     //   4182: invokestatic 619	java/lang/String:valueOf	(C)Ljava/lang/String;
/*      */     //   4185: ldc_w 629
/*      */     //   4188: invokevirtual 625	java/lang/String:contains	(Ljava/lang/CharSequence;)Z
/*      */     //   4191: ifne +45 -> 4236
/*      */     //   4194: aload 7
/*      */     //   4196: invokevirtual 560	org/compiere/model/X_I_Order:getBPartnerValue	()Ljava/lang/String;
/*      */     //   4199: iconst_0
/*      */     //   4200: invokevirtual 615	java/lang/String:charAt	(I)C
/*      */     //   4203: invokestatic 619	java/lang/String:valueOf	(C)Ljava/lang/String;
/*      */     //   4206: ldc_w 631
/*      */     //   4209: invokevirtual 625	java/lang/String:contains	(Ljava/lang/CharSequence;)Z
/*      */     //   4212: ifne +24 -> 4236
/*      */     //   4215: aload 7
/*      */     //   4217: invokevirtual 560	org/compiere/model/X_I_Order:getBPartnerValue	()Ljava/lang/String;
/*      */     //   4220: iconst_0
/*      */     //   4221: invokevirtual 615	java/lang/String:charAt	(I)C
/*      */     //   4224: invokestatic 619	java/lang/String:valueOf	(C)Ljava/lang/String;
/*      */     //   4227: ldc_w 633
/*      */     //   4230: invokevirtual 625	java/lang/String:contains	(Ljava/lang/CharSequence;)Z
/*      */     //   4233: ifeq +20 -> 4253
/*      */     //   4236: aload 9
/*      */     //   4238: ldc_w 635
/*      */     //   4241: ldc_w 637
/*      */     //   4244: invokestatic 638	java/lang/Integer:valueOf	(I)Ljava/lang/Integer;
/*      */     //   4247: invokevirtual 643	org/compiere/model/MBPartner:set_CustomColumn	(Ljava/lang/String;Ljava/lang/Object;)V
/*      */     //   4250: goto +17 -> 4267
/*      */     //   4253: aload 9
/*      */     //   4255: ldc_w 635
/*      */     //   4258: ldc_w 647
/*      */     //   4261: invokestatic 638	java/lang/Integer:valueOf	(I)Ljava/lang/Integer;
/*      */     //   4264: invokevirtual 643	org/compiere/model/MBPartner:set_CustomColumn	(Ljava/lang/String;Ljava/lang/Object;)V
/*      */     //   4267: aload 9
/*      */     //   4269: aload 7
/*      */     //   4271: invokevirtual 569	org/compiere/model/X_I_Order:getName	()Ljava/lang/String;
/*      */     //   4274: invokevirtual 648	org/compiere/model/MBPartner:setName	(Ljava/lang/String;)V
/*      */     //   4277: aload 9
/*      */     //   4279: iconst_1
/*      */     //   4280: invokevirtual 649	org/compiere/model/MBPartner:setIsCustomer	(Z)V
/*      */     //   4283: ldc_w 653
/*      */     //   4286: iconst_0
/*      */     //   4287: aload_0
/*      */     //   4288: invokevirtual 655	com/ghintech/puntocom/process/ImportOrder:getProcessInfo	()Lorg/compiere/process/ProcessInfo;
/*      */     //   4291: invokevirtual 659	org/compiere/process/ProcessInfo:getAD_Client_ID	()Ljava/lang/Integer;
/*      */     //   4294: invokevirtual 664	java/lang/Integer:intValue	()I
/*      */     //   4297: invokestatic 665	org/compiere/model/MSysConfig:getBooleanValue	(Ljava/lang/String;ZI)Z
/*      */     //   4300: istore 10
/*      */     //   4302: iload 10
/*      */     //   4304: ifeq +21 -> 4325
/*      */     //   4307: aload 9
/*      */     //   4309: invokevirtual 669	org/compiere/model/MBPartner:getSalesRep_ID	()I
/*      */     //   4312: ifne +13 -> 4325
/*      */     //   4315: aload 9
/*      */     //   4317: aload 7
/*      */     //   4319: invokevirtual 672	org/compiere/model/X_I_Order:getSalesRep_ID	()I
/*      */     //   4322: invokevirtual 673	org/compiere/model/MBPartner:setSalesRep_ID	(I)V
/*      */     //   4325: aload 7
/*      */     //   4327: ldc_w 677
/*      */     //   4330: invokevirtual 679	org/compiere/model/X_I_Order:get_ValueAsString	(Ljava/lang/String;)Ljava/lang/String;
/*      */     //   4333: ifnonnull +17 -> 4350
/*      */     //   4336: aload 7
/*      */     //   4338: ldc_w 677
/*      */     //   4341: invokevirtual 679	org/compiere/model/X_I_Order:get_ValueAsString	(Ljava/lang/String;)Ljava/lang/String;
/*      */     //   4344: invokevirtual 682	java/lang/String:isEmpty	()Z
/*      */     //   4347: ifne +70 -> 4417
/*      */     //   4350: new 524	org/compiere/model/Query
/*      */     //   4353: dup
/*      */     //   4354: aload_0
/*      */     //   4355: invokevirtual 526	com/ghintech/puntocom/process/ImportOrder:getCtx	()Ljava/util/Properties;
/*      */     //   4358: ldc_w 686
/*      */     //   4361: new 81	java/lang/StringBuilder
/*      */     //   4364: dup
/*      */     //   4365: ldc_w 688
/*      */     //   4368: invokespecial 85	java/lang/StringBuilder:<init>	(Ljava/lang/String;)V
/*      */     //   4371: aload 7
/*      */     //   4373: ldc_w 677
/*      */     //   4376: invokevirtual 679	org/compiere/model/X_I_Order:get_ValueAsString	(Ljava/lang/String;)Ljava/lang/String;
/*      */     //   4379: invokevirtual 88	java/lang/StringBuilder:append	(Ljava/lang/String;)Ljava/lang/StringBuilder;
/*      */     //   4382: ldc_w 690
/*      */     //   4385: invokevirtual 88	java/lang/StringBuilder:append	(Ljava/lang/String;)Ljava/lang/StringBuilder;
/*      */     //   4388: invokevirtual 92	java/lang/StringBuilder:toString	()Ljava/lang/String;
/*      */     //   4391: aload_0
/*      */     //   4392: invokevirtual 133	com/ghintech/puntocom/process/ImportOrder:get_TrxName	()Ljava/lang/String;
/*      */     //   4395: invokespecial 534	org/compiere/model/Query:<init>	(Ljava/util/Properties;Ljava/lang/String;Ljava/lang/String;Ljava/lang/String;)V
/*      */     //   4398: invokevirtual 692	org/compiere/model/Query:first	()Lorg/compiere/model/PO;
/*      */     //   4401: checkcast 696	org/compiere/model/MBPGroup
/*      */     //   4404: astore 11
/*      */     //   4406: aload 9
/*      */     //   4408: aload 11
/*      */     //   4410: invokevirtual 698	org/compiere/model/MBPartner:setBPGroup	(Lorg/compiere/model/MBPGroup;)V
/*      */     //   4413: goto +4 -> 4417
/*      */     //   4416: pop
/*      */     //   4417: aload 9
/*      */     //   4419: invokevirtual 702	org/compiere/model/MBPartner:save	()Z
/*      */     //   4422: ifne +6 -> 4428
/*      */     //   4425: goto +618 -> 5043
/*      */     //   4428: aload 7
/*      */     //   4430: aload 9
/*      */     //   4432: invokevirtual 705	org/compiere/model/MBPartner:getC_BPartner_ID	()I
/*      */     //   4435: invokevirtual 708	org/compiere/model/X_I_Order:setC_BPartner_ID	(I)V
/*      */     //   4438: aconst_null
/*      */     //   4439: astore 10
/*      */     //   4441: aload 9
/*      */     //   4443: iconst_1
/*      */     //   4444: invokevirtual 711	org/compiere/model/MBPartner:getLocations	(Z)[Lorg/compiere/model/MBPartnerLocation;
/*      */     //   4447: astore 11
/*      */     //   4449: iconst_0
/*      */     //   4450: istore 12
/*      */     //   4452: goto +154 -> 4606
/*      */     //   4455: aload 7
/*      */     //   4457: invokevirtual 715	org/compiere/model/X_I_Order:getCity	()Ljava/lang/String;
/*      */     //   4460: aload 11
/*      */     //   4462: iload 12
/*      */     //   4464: aaload
/*      */     //   4465: invokevirtual 718	org/compiere/model/MBPartnerLocation:getName	()Ljava/lang/String;
/*      */     //   4468: invokevirtual 611	java/lang/String:compareTo	(Ljava/lang/String;)I
/*      */     //   4471: ifne +13 -> 4484
/*      */     //   4474: aload 11
/*      */     //   4476: iload 12
/*      */     //   4478: aaload
/*      */     //   4479: astore 10
/*      */     //   4481: goto +122 -> 4603
/*      */     //   4484: aload 7
/*      */     //   4486: invokevirtual 721	org/compiere/model/X_I_Order:getC_BPartner_Location_ID	()I
/*      */     //   4489: aload 11
/*      */     //   4491: iload 12
/*      */     //   4493: aaload
/*      */     //   4494: invokevirtual 724	org/compiere/model/MBPartnerLocation:getC_BPartner_Location_ID	()I
/*      */     //   4497: if_icmpne +13 -> 4510
/*      */     //   4500: aload 11
/*      */     //   4502: iload 12
/*      */     //   4504: aaload
/*      */     //   4505: astore 10
/*      */     //   4507: goto +96 -> 4603
/*      */     //   4510: aload 7
/*      */     //   4512: invokevirtual 725	org/compiere/model/X_I_Order:getC_Location_ID	()I
/*      */     //   4515: aload 11
/*      */     //   4517: iload 12
/*      */     //   4519: aaload
/*      */     //   4520: invokevirtual 728	org/compiere/model/MBPartnerLocation:getC_Location_ID	()I
/*      */     //   4523: if_icmpne +13 -> 4536
/*      */     //   4526: aload 11
/*      */     //   4528: iload 12
/*      */     //   4530: aaload
/*      */     //   4531: astore 10
/*      */     //   4533: goto +70 -> 4603
/*      */     //   4536: aload 7
/*      */     //   4538: invokevirtual 725	org/compiere/model/X_I_Order:getC_Location_ID	()I
/*      */     //   4541: ifne +62 -> 4603
/*      */     //   4544: aload 11
/*      */     //   4546: iload 12
/*      */     //   4548: aaload
/*      */     //   4549: iconst_0
/*      */     //   4550: invokevirtual 729	org/compiere/model/MBPartnerLocation:getLocation	(Z)Lorg/compiere/model/MLocation;
/*      */     //   4553: astore 13
/*      */     //   4555: aload 13
/*      */     //   4557: aload 7
/*      */     //   4559: invokevirtual 733	org/compiere/model/X_I_Order:getC_Country_ID	()I
/*      */     //   4562: aload 7
/*      */     //   4564: invokevirtual 736	org/compiere/model/X_I_Order:getC_Region_ID	()I
/*      */     //   4567: aload 7
/*      */     //   4569: invokevirtual 739	org/compiere/model/X_I_Order:getPostal	()Ljava/lang/String;
/*      */     //   4572: ldc_w 742
/*      */     //   4575: aload 7
/*      */     //   4577: invokevirtual 715	org/compiere/model/X_I_Order:getCity	()Ljava/lang/String;
/*      */     //   4580: aload 7
/*      */     //   4582: invokevirtual 744	org/compiere/model/X_I_Order:getAddress1	()Ljava/lang/String;
/*      */     //   4585: aload 7
/*      */     //   4587: invokevirtual 747	org/compiere/model/X_I_Order:getAddress2	()Ljava/lang/String;
/*      */     //   4590: invokevirtual 750	org/compiere/model/MLocation:equals	(IILjava/lang/String;Ljava/lang/String;Ljava/lang/String;Ljava/lang/String;Ljava/lang/String;)Z
/*      */     //   4593: ifeq +10 -> 4603
/*      */     //   4596: aload 11
/*      */     //   4598: iload 12
/*      */     //   4600: aaload
/*      */     //   4601: astore 10
/*      */     //   4603: iinc 12 1
/*      */     //   4606: aload 10
/*      */     //   4608: ifnonnull +11 -> 4619
/*      */     //   4611: iload 12
/*      */     //   4613: aload 11
/*      */     //   4615: arraylength
/*      */     //   4616: if_icmplt -161 -> 4455
/*      */     //   4619: aload 10
/*      */     //   4621: ifnonnull +132 -> 4753
/*      */     //   4624: new 751	org/compiere/model/MLocation
/*      */     //   4627: dup
/*      */     //   4628: aload_0
/*      */     //   4629: invokevirtual 526	com/ghintech/puntocom/process/ImportOrder:getCtx	()Ljava/util/Properties;
/*      */     //   4632: iconst_0
/*      */     //   4633: aload_0
/*      */     //   4634: invokevirtual 133	com/ghintech/puntocom/process/ImportOrder:get_TrxName	()Ljava/lang/String;
/*      */     //   4637: invokespecial 755	org/compiere/model/MLocation:<init>	(Ljava/util/Properties;ILjava/lang/String;)V
/*      */     //   4640: astore 12
/*      */     //   4642: aload 12
/*      */     //   4644: aload 7
/*      */     //   4646: invokevirtual 744	org/compiere/model/X_I_Order:getAddress1	()Ljava/lang/String;
/*      */     //   4649: invokevirtual 756	org/compiere/model/MLocation:setAddress1	(Ljava/lang/String;)V
/*      */     //   4652: aload 12
/*      */     //   4654: aload 7
/*      */     //   4656: invokevirtual 747	org/compiere/model/X_I_Order:getAddress2	()Ljava/lang/String;
/*      */     //   4659: invokevirtual 759	org/compiere/model/MLocation:setAddress2	(Ljava/lang/String;)V
/*      */     //   4662: aload 12
/*      */     //   4664: aload 7
/*      */     //   4666: invokevirtual 715	org/compiere/model/X_I_Order:getCity	()Ljava/lang/String;
/*      */     //   4669: invokevirtual 762	org/compiere/model/MLocation:setCity	(Ljava/lang/String;)V
/*      */     //   4672: aload 12
/*      */     //   4674: aload 7
/*      */     //   4676: invokevirtual 739	org/compiere/model/X_I_Order:getPostal	()Ljava/lang/String;
/*      */     //   4679: invokevirtual 765	org/compiere/model/MLocation:setPostal	(Ljava/lang/String;)V
/*      */     //   4682: aload 7
/*      */     //   4684: invokevirtual 736	org/compiere/model/X_I_Order:getC_Region_ID	()I
/*      */     //   4687: ifeq +13 -> 4700
/*      */     //   4690: aload 12
/*      */     //   4692: aload 7
/*      */     //   4694: invokevirtual 736	org/compiere/model/X_I_Order:getC_Region_ID	()I
/*      */     //   4697: invokevirtual 768	org/compiere/model/MLocation:setC_Region_ID	(I)V
/*      */     //   4700: aload 12
/*      */     //   4702: aload 7
/*      */     //   4704: invokevirtual 733	org/compiere/model/X_I_Order:getC_Country_ID	()I
/*      */     //   4707: invokevirtual 771	org/compiere/model/MLocation:setC_Country_ID	(I)V
/*      */     //   4710: aload 12
/*      */     //   4712: invokevirtual 774	org/compiere/model/MLocation:save	()Z
/*      */     //   4715: ifne +6 -> 4721
/*      */     //   4718: goto +325 -> 5043
/*      */     //   4721: new 719	org/compiere/model/MBPartnerLocation
/*      */     //   4724: dup
/*      */     //   4725: aload 9
/*      */     //   4727: invokespecial 775	org/compiere/model/MBPartnerLocation:<init>	(Lorg/compiere/model/MBPartner;)V
/*      */     //   4730: astore 10
/*      */     //   4732: aload 10
/*      */     //   4734: aload 12
/*      */     //   4736: invokevirtual 778	org/compiere/model/MLocation:getC_Location_ID	()I
/*      */     //   4739: invokevirtual 779	org/compiere/model/MBPartnerLocation:setC_Location_ID	(I)V
/*      */     //   4742: aload 10
/*      */     //   4744: invokevirtual 782	org/compiere/model/MBPartnerLocation:save	()Z
/*      */     //   4747: ifne +6 -> 4753
/*      */     //   4750: goto +293 -> 5043
/*      */     //   4753: aload 7
/*      */     //   4755: aload 10
/*      */     //   4757: invokevirtual 728	org/compiere/model/MBPartnerLocation:getC_Location_ID	()I
/*      */     //   4760: invokevirtual 783	org/compiere/model/X_I_Order:setC_Location_ID	(I)V
/*      */     //   4763: aload 7
/*      */     //   4765: aload 10
/*      */     //   4767: invokevirtual 724	org/compiere/model/MBPartnerLocation:getC_BPartner_Location_ID	()I
/*      */     //   4770: invokevirtual 784	org/compiere/model/X_I_Order:setBillTo_ID	(I)V
/*      */     //   4773: aload 7
/*      */     //   4775: aload 10
/*      */     //   4777: invokevirtual 724	org/compiere/model/MBPartnerLocation:getC_BPartner_Location_ID	()I
/*      */     //   4780: invokevirtual 787	org/compiere/model/X_I_Order:setC_BPartner_Location_ID	(I)V
/*      */     //   4783: aload 7
/*      */     //   4785: invokevirtual 572	org/compiere/model/X_I_Order:getContactName	()Ljava/lang/String;
/*      */     //   4788: ifnonnull +19 -> 4807
/*      */     //   4791: aload 7
/*      */     //   4793: invokevirtual 563	org/compiere/model/X_I_Order:getEMail	()Ljava/lang/String;
/*      */     //   4796: ifnonnull +11 -> 4807
/*      */     //   4799: aload 7
/*      */     //   4801: invokevirtual 790	org/compiere/model/X_I_Order:getPhone	()Ljava/lang/String;
/*      */     //   4804: ifnull +229 -> 5033
/*      */     //   4807: aload 9
/*      */     //   4809: iconst_1
/*      */     //   4810: invokevirtual 793	org/compiere/model/MBPartner:getContacts	(Z)[Lorg/compiere/model/MUser;
/*      */     //   4813: astore 12
/*      */     //   4815: aconst_null
/*      */     //   4816: astore 13
/*      */     //   4818: iconst_0
/*      */     //   4819: istore 14
/*      */     //   4821: goto +59 -> 4880
/*      */     //   4824: aload 12
/*      */     //   4826: iload 14
/*      */     //   4828: aaload
/*      */     //   4829: invokevirtual 797	org/compiere/model/MUser:getName	()Ljava/lang/String;
/*      */     //   4832: astore 15
/*      */     //   4834: aload 15
/*      */     //   4836: aload 7
/*      */     //   4838: invokevirtual 572	org/compiere/model/X_I_Order:getContactName	()Ljava/lang/String;
/*      */     //   4841: invokevirtual 48	java/lang/String:equals	(Ljava/lang/Object;)Z
/*      */     //   4844: ifne +16 -> 4860
/*      */     //   4847: aload 15
/*      */     //   4849: aload 7
/*      */     //   4851: invokevirtual 569	org/compiere/model/X_I_Order:getName	()Ljava/lang/String;
/*      */     //   4854: invokevirtual 48	java/lang/String:equals	(Ljava/lang/Object;)Z
/*      */     //   4857: ifeq +20 -> 4877
/*      */     //   4860: aload 12
/*      */     //   4862: iload 14
/*      */     //   4864: aaload
/*      */     //   4865: astore 13
/*      */     //   4867: aload 7
/*      */     //   4869: aload 13
/*      */     //   4871: invokevirtual 800	org/compiere/model/MUser:getAD_User_ID	()I
/*      */     //   4874: invokevirtual 803	org/compiere/model/X_I_Order:setAD_User_ID	(I)V
/*      */     //   4877: iinc 14 1
/*      */     //   4880: aload 13
/*      */     //   4882: ifnonnull +11 -> 4893
/*      */     //   4885: iload 14
/*      */     //   4887: aload 12
/*      */     //   4889: arraylength
/*      */     //   4890: if_icmplt -66 -> 4824
/*      */     //   4893: aload 13
/*      */     //   4895: ifnonnull +138 -> 5033
/*      */     //   4898: new 798	org/compiere/model/MUser
/*      */     //   4901: dup
/*      */     //   4902: aload 9
/*      */     //   4904: invokespecial 806	org/compiere/model/MUser:<init>	(Lorg/compiere/model/X_C_BPartner;)V
/*      */     //   4907: astore 13
/*      */     //   4909: aload 7
/*      */     //   4911: invokevirtual 572	org/compiere/model/X_I_Order:getContactName	()Ljava/lang/String;
/*      */     //   4914: ifnonnull +16 -> 4930
/*      */     //   4917: aload 13
/*      */     //   4919: aload 7
/*      */     //   4921: invokevirtual 569	org/compiere/model/X_I_Order:getName	()Ljava/lang/String;
/*      */     //   4924: invokevirtual 809	org/compiere/model/MUser:setName	(Ljava/lang/String;)V
/*      */     //   4927: goto +13 -> 4940
/*      */     //   4930: aload 13
/*      */     //   4932: aload 7
/*      */     //   4934: invokevirtual 572	org/compiere/model/X_I_Order:getContactName	()Ljava/lang/String;
/*      */     //   4937: invokevirtual 809	org/compiere/model/MUser:setName	(Ljava/lang/String;)V
/*      */     //   4940: aload 13
/*      */     //   4942: aload 7
/*      */     //   4944: invokevirtual 563	org/compiere/model/X_I_Order:getEMail	()Ljava/lang/String;
/*      */     //   4947: invokevirtual 810	org/compiere/model/MUser:setEMail	(Ljava/lang/String;)V
/*      */     //   4950: aload 13
/*      */     //   4952: aload 7
/*      */     //   4954: invokevirtual 790	org/compiere/model/X_I_Order:getPhone	()Ljava/lang/String;
/*      */     //   4957: invokevirtual 813	org/compiere/model/MUser:setPhone	(Ljava/lang/String;)V
/*      */     //   4960: aload 7
/*      */     //   4962: ldc_w 816
/*      */     //   4965: invokevirtual 679	org/compiere/model/X_I_Order:get_ValueAsString	(Ljava/lang/String;)Ljava/lang/String;
/*      */     //   4968: ifnull +16 -> 4984
/*      */     //   4971: aload 13
/*      */     //   4973: aload 7
/*      */     //   4975: ldc_w 816
/*      */     //   4978: invokevirtual 679	org/compiere/model/X_I_Order:get_ValueAsString	(Ljava/lang/String;)Ljava/lang/String;
/*      */     //   4981: invokevirtual 818	org/compiere/model/MUser:setPhone2	(Ljava/lang/String;)V
/*      */     //   4984: aload 7
/*      */     //   4986: ldc_w 821
/*      */     //   4989: invokevirtual 823	org/compiere/model/X_I_Order:get_Value	(Ljava/lang/String;)Ljava/lang/Object;
/*      */     //   4992: ifnull +23 -> 5015
/*      */     //   4995: aload 13
/*      */     //   4997: aload 7
/*      */     //   4999: ldc_w 821
/*      */     //   5002: invokevirtual 823	org/compiere/model/X_I_Order:get_Value	(Ljava/lang/String;)Ljava/lang/Object;
/*      */     //   5005: checkcast 100	java/sql/Timestamp
/*      */     //   5008: invokevirtual 827	org/compiere/model/MUser:setBirthday	(Ljava/sql/Timestamp;)V
/*      */     //   5011: goto +4 -> 5015
/*      */     //   5014: pop
/*      */     //   5015: aload 13
/*      */     //   5017: invokevirtual 831	org/compiere/model/MUser:save	()Z
/*      */     //   5020: ifeq +13 -> 5033
/*      */     //   5023: aload 7
/*      */     //   5025: aload 13
/*      */     //   5027: invokevirtual 800	org/compiere/model/MUser:getAD_User_ID	()I
/*      */     //   5030: invokevirtual 803	org/compiere/model/X_I_Order:setAD_User_ID	(I)V
/*      */     //   5033: aload 7
/*      */     //   5035: invokevirtual 832	org/compiere/model/X_I_Order:save	()Z
/*      */     //   5038: pop
/*      */     //   5039: aload_0
/*      */     //   5040: invokevirtual 521	com/ghintech/puntocom/process/ImportOrder:commitEx	()V
/*      */     //   5043: aload 8
/*      */     //   5045: invokeinterface 833 1 0
/*      */     //   5050: ifne -1082 -> 3968
/*      */     //   5053: new 81	java/lang/StringBuilder
/*      */     //   5056: dup
/*      */     //   5057: ldc -102
/*      */     //   5059: invokespecial 85	java/lang/StringBuilder:<init>	(Ljava/lang/String;)V
/*      */     //   5062: ldc_w 836
/*      */     //   5065: invokevirtual 88	java/lang/StringBuilder:append	(Ljava/lang/String;)Ljava/lang/StringBuilder;
/*      */     //   5068: ldc_w 838
/*      */     //   5071: invokevirtual 88	java/lang/StringBuilder:append	(Ljava/lang/String;)Ljava/lang/StringBuilder;
/*      */     //   5074: ldc -54
/*      */     //   5076: invokevirtual 88	java/lang/StringBuilder:append	(Ljava/lang/String;)Ljava/lang/StringBuilder;
/*      */     //   5079: aload_3
/*      */     //   5080: invokevirtual 130	java/lang/StringBuilder:append	(Ljava/lang/CharSequence;)Ljava/lang/StringBuilder;
/*      */     //   5083: astore_1
/*      */     //   5084: aload_1
/*      */     //   5085: invokevirtual 92	java/lang/StringBuilder:toString	()Ljava/lang/String;
/*      */     //   5088: aload_0
/*      */     //   5089: invokevirtual 133	com/ghintech/puntocom/process/ImportOrder:get_TrxName	()Ljava/lang/String;
/*      */     //   5092: invokestatic 136	org/compiere/util/DB:executeUpdate	(Ljava/lang/String;Ljava/lang/String;)I
/*      */     //   5095: istore_2
/*      */     //   5096: iload_2
/*      */     //   5097: ifeq +27 -> 5124
/*      */     //   5100: aload_0
/*      */     //   5101: getfield 71	com/ghintech/puntocom/process/ImportOrder:log	Lorg/compiere/util/CLogger;
/*      */     //   5104: new 81	java/lang/StringBuilder
/*      */     //   5107: dup
/*      */     //   5108: ldc_w 840
/*      */     //   5111: invokespecial 85	java/lang/StringBuilder:<init>	(Ljava/lang/String;)V
/*      */     //   5114: iload_2
/*      */     //   5115: invokevirtual 123	java/lang/StringBuilder:append	(I)Ljava/lang/StringBuilder;
/*      */     //   5118: invokevirtual 92	java/lang/StringBuilder:toString	()Ljava/lang/String;
/*      */     //   5121: invokevirtual 206	org/compiere/util/CLogger:warning	(Ljava/lang/String;)V
/*      */     //   5124: aload_0
/*      */     //   5125: invokevirtual 521	com/ghintech/puntocom/process/ImportOrder:commitEx	()V
/*      */     //   5128: iconst_0
/*      */     //   5129: istore 7
/*      */     //   5131: iconst_0
/*      */     //   5132: istore 8
/*      */     //   5134: new 81	java/lang/StringBuilder
/*      */     //   5137: dup
/*      */     //   5138: ldc_w 842
/*      */     //   5141: invokespecial 85	java/lang/StringBuilder:<init>	(Ljava/lang/String;)V
/*      */     //   5144: ldc_w 844
/*      */     //   5147: invokevirtual 88	java/lang/StringBuilder:append	(Ljava/lang/String;)Ljava/lang/StringBuilder;
/*      */     //   5150: ldc_w 846
/*      */     //   5153: invokevirtual 88	java/lang/StringBuilder:append	(Ljava/lang/String;)Ljava/lang/StringBuilder;
/*      */     //   5156: ldc_w 848
/*      */     //   5159: invokevirtual 88	java/lang/StringBuilder:append	(Ljava/lang/String;)Ljava/lang/StringBuilder;
/*      */     //   5162: aload_3
/*      */     //   5163: invokevirtual 130	java/lang/StringBuilder:append	(Ljava/lang/CharSequence;)Ljava/lang/StringBuilder;
/*      */     //   5166: ldc_w 850
/*      */     //   5169: invokevirtual 88	java/lang/StringBuilder:append	(Ljava/lang/String;)Ljava/lang/StringBuilder;
/*      */     //   5172: astore_1
/*      */     //   5173: aload_1
/*      */     //   5174: invokevirtual 92	java/lang/StringBuilder:toString	()Ljava/lang/String;
/*      */     //   5177: aload_0
/*      */     //   5178: invokevirtual 133	com/ghintech/puntocom/process/ImportOrder:get_TrxName	()Ljava/lang/String;
/*      */     //   5181: invokestatic 852	org/compiere/util/DB:prepareStatement	(Ljava/lang/String;Ljava/lang/String;)Lorg/compiere/util/CPreparedStatement;
/*      */     //   5184: astore 4
/*      */     //   5186: aload 4
/*      */     //   5188: invokeinterface 856 1 0
/*      */     //   5193: astore 5
/*      */     //   5195: iconst_0
/*      */     //   5196: istore 9
/*      */     //   5198: iconst_0
/*      */     //   5199: istore 10
/*      */     //   5201: iconst_0
/*      */     //   5202: istore 11
/*      */     //   5204: ldc_w 742
/*      */     //   5207: astore 12
/*      */     //   5209: aconst_null
/*      */     //   5210: astore 13
/*      */     //   5212: aconst_null
/*      */     //   5213: astore 14
/*      */     //   5215: iconst_0
/*      */     //   5216: istore 15
/*      */     //   5218: goto +1069 -> 6287
/*      */     //   5221: new 558	org/compiere/model/X_I_Order
/*      */     //   5224: dup
/*      */     //   5225: aload_0
/*      */     //   5226: invokevirtual 526	com/ghintech/puntocom/process/ImportOrder:getCtx	()Ljava/util/Properties;
/*      */     //   5229: aload 5
/*      */     //   5231: aload_0
/*      */     //   5232: invokevirtual 133	com/ghintech/puntocom/process/ImportOrder:get_TrxName	()Ljava/lang/String;
/*      */     //   5235: invokespecial 862	org/compiere/model/X_I_Order:<init>	(Ljava/util/Properties;Ljava/sql/ResultSet;Ljava/lang/String;)V
/*      */     //   5238: astore 16
/*      */     //   5240: aload 16
/*      */     //   5242: invokevirtual 865	org/compiere/model/X_I_Order:getDocumentNo	()Ljava/lang/String;
/*      */     //   5245: astore 17
/*      */     //   5247: aload 17
/*      */     //   5249: ifnonnull +8 -> 5257
/*      */     //   5252: ldc_w 742
/*      */     //   5255: astore 17
/*      */     //   5257: iload 9
/*      */     //   5259: aload 16
/*      */     //   5261: invokevirtual 868	org/compiere/model/X_I_Order:getC_BPartner_ID	()I
/*      */     //   5264: if_icmpne +33 -> 5297
/*      */     //   5267: iload 11
/*      */     //   5269: aload 16
/*      */     //   5271: invokevirtual 721	org/compiere/model/X_I_Order:getC_BPartner_Location_ID	()I
/*      */     //   5274: if_icmpne +23 -> 5297
/*      */     //   5277: iload 10
/*      */     //   5279: aload 16
/*      */     //   5281: invokevirtual 869	org/compiere/model/X_I_Order:getBillTo_ID	()I
/*      */     //   5284: if_icmpne +13 -> 5297
/*      */     //   5287: aload 12
/*      */     //   5289: aload 17
/*      */     //   5291: invokevirtual 48	java/lang/String:equals	(Ljava/lang/Object;)Z
/*      */     //   5294: ifne +746 -> 6040
/*      */     //   5297: aload 13
/*      */     //   5299: ifnull +132 -> 5431
/*      */     //   5302: aload_0
/*      */     //   5303: getfield 27	com/ghintech/puntocom/process/ImportOrder:m_docAction	Ljava/lang/String;
/*      */     //   5306: ifnull +113 -> 5419
/*      */     //   5309: aload_0
/*      */     //   5310: getfield 27	com/ghintech/puntocom/process/ImportOrder:m_docAction	Ljava/lang/String;
/*      */     //   5313: invokevirtual 872	java/lang/String:length	()I
/*      */     //   5316: ifle +103 -> 5419
/*      */     //   5319: aload 13
/*      */     //   5321: aload_0
/*      */     //   5322: getfield 27	com/ghintech/puntocom/process/ImportOrder:m_docAction	Ljava/lang/String;
/*      */     //   5325: invokevirtual 875	org/compiere/model/MOrder:setDocAction	(Ljava/lang/String;)V
/*      */     //   5328: aload 13
/*      */     //   5330: aload_0
/*      */     //   5331: getfield 27	com/ghintech/puntocom/process/ImportOrder:m_docAction	Ljava/lang/String;
/*      */     //   5334: invokevirtual 880	org/compiere/model/MOrder:processIt	(Ljava/lang/String;)Z
/*      */     //   5337: ifne +82 -> 5419
/*      */     //   5340: aload_0
/*      */     //   5341: getfield 71	com/ghintech/puntocom/process/ImportOrder:log	Lorg/compiere/util/CLogger;
/*      */     //   5344: new 81	java/lang/StringBuilder
/*      */     //   5347: dup
/*      */     //   5348: ldc_w 884
/*      */     //   5351: invokespecial 85	java/lang/StringBuilder:<init>	(Ljava/lang/String;)V
/*      */     //   5354: aload 13
/*      */     //   5356: invokevirtual 886	java/lang/StringBuilder:append	(Ljava/lang/Object;)Ljava/lang/StringBuilder;
/*      */     //   5359: ldc_w 889
/*      */     //   5362: invokevirtual 88	java/lang/StringBuilder:append	(Ljava/lang/String;)Ljava/lang/StringBuilder;
/*      */     //   5365: aload 13
/*      */     //   5367: invokevirtual 891	org/compiere/model/MOrder:getProcessMsg	()Ljava/lang/String;
/*      */     //   5370: invokevirtual 88	java/lang/StringBuilder:append	(Ljava/lang/String;)Ljava/lang/StringBuilder;
/*      */     //   5373: invokevirtual 92	java/lang/StringBuilder:toString	()Ljava/lang/String;
/*      */     //   5376: invokevirtual 206	org/compiere/util/CLogger:warning	(Ljava/lang/String;)V
/*      */     //   5379: new 894	java/lang/IllegalStateException
/*      */     //   5382: dup
/*      */     //   5383: new 81	java/lang/StringBuilder
/*      */     //   5386: dup
/*      */     //   5387: ldc_w 884
/*      */     //   5390: invokespecial 85	java/lang/StringBuilder:<init>	(Ljava/lang/String;)V
/*      */     //   5393: aload 13
/*      */     //   5395: invokevirtual 886	java/lang/StringBuilder:append	(Ljava/lang/Object;)Ljava/lang/StringBuilder;
/*      */     //   5398: ldc_w 889
/*      */     //   5401: invokevirtual 88	java/lang/StringBuilder:append	(Ljava/lang/String;)Ljava/lang/StringBuilder;
/*      */     //   5404: aload 13
/*      */     //   5406: invokevirtual 891	org/compiere/model/MOrder:getProcessMsg	()Ljava/lang/String;
/*      */     //   5409: invokevirtual 88	java/lang/StringBuilder:append	(Ljava/lang/String;)Ljava/lang/StringBuilder;
/*      */     //   5412: invokevirtual 92	java/lang/StringBuilder:toString	()Ljava/lang/String;
/*      */     //   5415: invokespecial 896	java/lang/IllegalStateException:<init>	(Ljava/lang/String;)V
/*      */     //   5418: athrow
/*      */     //   5419: aload 13
/*      */     //   5421: invokevirtual 897	org/compiere/model/MOrder:saveEx	()V
/*      */     //   5424: aload_0
/*      */     //   5425: aload 13
/*      */     //   5427: invokespecial 900	com/ghintech/puntocom/process/ImportOrder:createAllocation	(Lorg/compiere/model/MOrder;)Ljava/lang/String;
/*      */     //   5430: pop
/*      */     //   5431: aload 16
/*      */     //   5433: invokevirtual 868	org/compiere/model/X_I_Order:getC_BPartner_ID	()I
/*      */     //   5436: istore 9
/*      */     //   5438: aload 16
/*      */     //   5440: invokevirtual 721	org/compiere/model/X_I_Order:getC_BPartner_Location_ID	()I
/*      */     //   5443: istore 11
/*      */     //   5445: aload 16
/*      */     //   5447: invokevirtual 869	org/compiere/model/X_I_Order:getBillTo_ID	()I
/*      */     //   5450: istore 10
/*      */     //   5452: aload 16
/*      */     //   5454: invokevirtual 865	org/compiere/model/X_I_Order:getDocumentNo	()Ljava/lang/String;
/*      */     //   5457: astore 12
/*      */     //   5459: aload 12
/*      */     //   5461: ifnonnull +8 -> 5469
/*      */     //   5464: ldc_w 742
/*      */     //   5467: astore 12
/*      */     //   5469: new 876	org/compiere/model/MOrder
/*      */     //   5472: dup
/*      */     //   5473: aload_0
/*      */     //   5474: invokevirtual 526	com/ghintech/puntocom/process/ImportOrder:getCtx	()Ljava/util/Properties;
/*      */     //   5477: iconst_0
/*      */     //   5478: aload_0
/*      */     //   5479: invokevirtual 133	com/ghintech/puntocom/process/ImportOrder:get_TrxName	()Ljava/lang/String;
/*      */     //   5482: invokespecial 904	org/compiere/model/MOrder:<init>	(Ljava/util/Properties;ILjava/lang/String;)V
/*      */     //   5485: astore 13
/*      */     //   5487: aload 13
/*      */     //   5489: aload 16
/*      */     //   5491: invokevirtual 587	org/compiere/model/X_I_Order:getAD_Client_ID	()I
/*      */     //   5494: aload 16
/*      */     //   5496: invokevirtual 590	org/compiere/model/X_I_Order:getAD_Org_ID	()I
/*      */     //   5499: invokevirtual 905	org/compiere/model/MOrder:setClientOrg	(II)V
/*      */     //   5502: aload 13
/*      */     //   5504: aload 16
/*      */     //   5506: invokevirtual 906	org/compiere/model/X_I_Order:getC_DocType_ID	()I
/*      */     //   5509: invokevirtual 909	org/compiere/model/MOrder:setC_DocTypeTarget_ID	(I)V
/*      */     //   5512: aload 13
/*      */     //   5514: aload 16
/*      */     //   5516: invokevirtual 912	org/compiere/model/X_I_Order:isSOTrx	()Z
/*      */     //   5519: invokevirtual 915	org/compiere/model/MOrder:setIsSOTrx	(Z)V
/*      */     //   5522: aload 16
/*      */     //   5524: invokevirtual 918	org/compiere/model/X_I_Order:getDeliveryRule	()Ljava/lang/String;
/*      */     //   5527: ifnull +13 -> 5540
/*      */     //   5530: aload 13
/*      */     //   5532: aload 16
/*      */     //   5534: invokevirtual 918	org/compiere/model/X_I_Order:getDeliveryRule	()Ljava/lang/String;
/*      */     //   5537: invokevirtual 921	org/compiere/model/MOrder:setDeliveryRule	(Ljava/lang/String;)V
/*      */     //   5540: aload 16
/*      */     //   5542: ldc_w 924
/*      */     //   5545: invokevirtual 823	org/compiere/model/X_I_Order:get_Value	(Ljava/lang/String;)Ljava/lang/Object;
/*      */     //   5548: ifnull +19 -> 5567
/*      */     //   5551: aload 13
/*      */     //   5553: ldc_w 924
/*      */     //   5556: aload 16
/*      */     //   5558: ldc_w 924
/*      */     //   5561: invokevirtual 823	org/compiere/model/X_I_Order:get_Value	(Ljava/lang/String;)Ljava/lang/Object;
/*      */     //   5564: invokevirtual 926	org/compiere/model/MOrder:set_CustomColumn	(Ljava/lang/String;Ljava/lang/Object;)V
/*      */     //   5567: aload 16
/*      */     //   5569: invokevirtual 865	org/compiere/model/X_I_Order:getDocumentNo	()Ljava/lang/String;
/*      */     //   5572: ifnull +13 -> 5585
/*      */     //   5575: aload 13
/*      */     //   5577: aload 16
/*      */     //   5579: invokevirtual 865	org/compiere/model/X_I_Order:getDocumentNo	()Ljava/lang/String;
/*      */     //   5582: invokevirtual 927	org/compiere/model/MOrder:setDocumentNo	(Ljava/lang/String;)V
/*      */     //   5585: aload 13
/*      */     //   5587: aload 16
/*      */     //   5589: invokevirtual 868	org/compiere/model/X_I_Order:getC_BPartner_ID	()I
/*      */     //   5592: invokevirtual 930	org/compiere/model/MOrder:setC_BPartner_ID	(I)V
/*      */     //   5595: aload 13
/*      */     //   5597: aload 16
/*      */     //   5599: invokevirtual 721	org/compiere/model/X_I_Order:getC_BPartner_Location_ID	()I
/*      */     //   5602: invokevirtual 931	org/compiere/model/MOrder:setC_BPartner_Location_ID	(I)V
/*      */     //   5605: aload 16
/*      */     //   5607: invokevirtual 932	org/compiere/model/X_I_Order:getAD_User_ID	()I
/*      */     //   5610: ifeq +13 -> 5623
/*      */     //   5613: aload 13
/*      */     //   5615: aload 16
/*      */     //   5617: invokevirtual 932	org/compiere/model/X_I_Order:getAD_User_ID	()I
/*      */     //   5620: invokevirtual 933	org/compiere/model/MOrder:setAD_User_ID	(I)V
/*      */     //   5623: aload 13
/*      */     //   5625: aload 16
/*      */     //   5627: invokevirtual 868	org/compiere/model/X_I_Order:getC_BPartner_ID	()I
/*      */     //   5630: invokevirtual 934	org/compiere/model/MOrder:setBill_BPartner_ID	(I)V
/*      */     //   5633: aload 13
/*      */     //   5635: aload 16
/*      */     //   5637: invokevirtual 869	org/compiere/model/X_I_Order:getBillTo_ID	()I
/*      */     //   5640: invokevirtual 937	org/compiere/model/MOrder:setBill_Location_ID	(I)V
/*      */     //   5643: aload 16
/*      */     //   5645: invokevirtual 940	org/compiere/model/X_I_Order:getDescription	()Ljava/lang/String;
/*      */     //   5648: ifnull +13 -> 5661
/*      */     //   5651: aload 13
/*      */     //   5653: aload 16
/*      */     //   5655: invokevirtual 940	org/compiere/model/X_I_Order:getDescription	()Ljava/lang/String;
/*      */     //   5658: invokevirtual 943	org/compiere/model/MOrder:setDescription	(Ljava/lang/String;)V
/*      */     //   5661: aload 13
/*      */     //   5663: aload 16
/*      */     //   5665: invokevirtual 946	org/compiere/model/X_I_Order:getC_PaymentTerm_ID	()I
/*      */     //   5668: invokevirtual 949	org/compiere/model/MOrder:setC_PaymentTerm_ID	(I)V
/*      */     //   5671: aload 13
/*      */     //   5673: aload 16
/*      */     //   5675: invokevirtual 952	org/compiere/model/X_I_Order:getM_PriceList_ID	()I
/*      */     //   5678: invokevirtual 955	org/compiere/model/MOrder:setM_PriceList_ID	(I)V
/*      */     //   5681: aload 13
/*      */     //   5683: aload 16
/*      */     //   5685: invokevirtual 958	org/compiere/model/X_I_Order:getM_Warehouse_ID	()I
/*      */     //   5688: invokevirtual 961	org/compiere/model/MOrder:setM_Warehouse_ID	(I)V
/*      */     //   5691: aload 16
/*      */     //   5693: invokevirtual 964	org/compiere/model/X_I_Order:getM_Shipper_ID	()I
/*      */     //   5696: ifeq +13 -> 5709
/*      */     //   5699: aload 13
/*      */     //   5701: aload 16
/*      */     //   5703: invokevirtual 964	org/compiere/model/X_I_Order:getM_Shipper_ID	()I
/*      */     //   5706: invokevirtual 967	org/compiere/model/MOrder:setM_Shipper_ID	(I)V
/*      */     //   5709: aload 16
/*      */     //   5711: invokevirtual 672	org/compiere/model/X_I_Order:getSalesRep_ID	()I
/*      */     //   5714: ifeq +13 -> 5727
/*      */     //   5717: aload 13
/*      */     //   5719: aload 16
/*      */     //   5721: invokevirtual 672	org/compiere/model/X_I_Order:getSalesRep_ID	()I
/*      */     //   5724: invokevirtual 970	org/compiere/model/MOrder:setSalesRep_ID	(I)V
/*      */     //   5727: aload 13
/*      */     //   5729: invokevirtual 971	org/compiere/model/MOrder:getSalesRep_ID	()I
/*      */     //   5732: ifne +12 -> 5744
/*      */     //   5735: aload 13
/*      */     //   5737: aload_0
/*      */     //   5738: invokevirtual 972	com/ghintech/puntocom/process/ImportOrder:getAD_User_ID	()I
/*      */     //   5741: invokevirtual 970	org/compiere/model/MOrder:setSalesRep_ID	(I)V
/*      */     //   5744: aload 16
/*      */     //   5746: invokevirtual 973	org/compiere/model/X_I_Order:getAD_OrgTrx_ID	()I
/*      */     //   5749: ifeq +13 -> 5762
/*      */     //   5752: aload 13
/*      */     //   5754: aload 16
/*      */     //   5756: invokevirtual 973	org/compiere/model/X_I_Order:getAD_OrgTrx_ID	()I
/*      */     //   5759: invokevirtual 976	org/compiere/model/MOrder:setAD_OrgTrx_ID	(I)V
/*      */     //   5762: aload 16
/*      */     //   5764: invokevirtual 979	org/compiere/model/X_I_Order:getC_Activity_ID	()I
/*      */     //   5767: ifeq +13 -> 5780
/*      */     //   5770: aload 13
/*      */     //   5772: aload 16
/*      */     //   5774: invokevirtual 979	org/compiere/model/X_I_Order:getC_Activity_ID	()I
/*      */     //   5777: invokevirtual 982	org/compiere/model/MOrder:setC_Activity_ID	(I)V
/*      */     //   5780: aload 16
/*      */     //   5782: invokevirtual 985	org/compiere/model/X_I_Order:getC_Campaign_ID	()I
/*      */     //   5785: ifeq +13 -> 5798
/*      */     //   5788: aload 13
/*      */     //   5790: aload 16
/*      */     //   5792: invokevirtual 985	org/compiere/model/X_I_Order:getC_Campaign_ID	()I
/*      */     //   5795: invokevirtual 988	org/compiere/model/MOrder:setC_Campaign_ID	(I)V
/*      */     //   5798: aload 16
/*      */     //   5800: invokevirtual 991	org/compiere/model/X_I_Order:getC_Project_ID	()I
/*      */     //   5803: ifeq +13 -> 5816
/*      */     //   5806: aload 13
/*      */     //   5808: aload 16
/*      */     //   5810: invokevirtual 991	org/compiere/model/X_I_Order:getC_Project_ID	()I
/*      */     //   5813: invokevirtual 994	org/compiere/model/MOrder:setC_Project_ID	(I)V
/*      */     //   5816: aload 16
/*      */     //   5818: invokevirtual 997	org/compiere/model/X_I_Order:getDateOrdered	()Ljava/sql/Timestamp;
/*      */     //   5821: ifnull +13 -> 5834
/*      */     //   5824: aload 13
/*      */     //   5826: aload 16
/*      */     //   5828: invokevirtual 997	org/compiere/model/X_I_Order:getDateOrdered	()Ljava/sql/Timestamp;
/*      */     //   5831: invokevirtual 1001	org/compiere/model/MOrder:setDateOrdered	(Ljava/sql/Timestamp;)V
/*      */     //   5834: aload 16
/*      */     //   5836: invokevirtual 1004	org/compiere/model/X_I_Order:getDateAcct	()Ljava/sql/Timestamp;
/*      */     //   5839: ifnull +13 -> 5852
/*      */     //   5842: aload 13
/*      */     //   5844: aload 16
/*      */     //   5846: invokevirtual 1004	org/compiere/model/X_I_Order:getDateAcct	()Ljava/sql/Timestamp;
/*      */     //   5849: invokevirtual 1007	org/compiere/model/MOrder:setDateAcct	(Ljava/sql/Timestamp;)V
/*      */     //   5852: aload 16
/*      */     //   5854: invokevirtual 1010	org/compiere/model/X_I_Order:getC_OrderSource	()Lorg/compiere/model/I_C_OrderSource;
/*      */     //   5857: ifnull +13 -> 5870
/*      */     //   5860: aload 13
/*      */     //   5862: aload 16
/*      */     //   5864: invokevirtual 1014	org/compiere/model/X_I_Order:getC_OrderSource_ID	()I
/*      */     //   5867: invokevirtual 1017	org/compiere/model/MOrder:setC_OrderSource_ID	(I)V
/*      */     //   5870: aload 13
/*      */     //   5872: invokevirtual 897	org/compiere/model/MOrder:saveEx	()V
/*      */     //   5875: new 1020	com/ghintech/puntocom/model/M_C_Invoice_Fiscal
/*      */     //   5878: dup
/*      */     //   5879: aload_0
/*      */     //   5880: invokevirtual 526	com/ghintech/puntocom/process/ImportOrder:getCtx	()Ljava/util/Properties;
/*      */     //   5883: iconst_0
/*      */     //   5884: aload_0
/*      */     //   5885: invokevirtual 133	com/ghintech/puntocom/process/ImportOrder:get_TrxName	()Ljava/lang/String;
/*      */     //   5888: invokespecial 1022	com/ghintech/puntocom/model/M_C_Invoice_Fiscal:<init>	(Ljava/util/Properties;ILjava/lang/String;)V
/*      */     //   5891: astore 14
/*      */     //   5893: aload 16
/*      */     //   5895: ldc_w 1023
/*      */     //   5898: invokevirtual 679	org/compiere/model/X_I_Order:get_ValueAsString	(Ljava/lang/String;)Ljava/lang/String;
/*      */     //   5901: invokevirtual 682	java/lang/String:isEmpty	()Z
/*      */     //   5904: ifne +102 -> 6006
/*      */     //   5907: aload 14
/*      */     //   5909: aload 16
/*      */     //   5911: ldc_w 1023
/*      */     //   5914: invokevirtual 679	org/compiere/model/X_I_Order:get_ValueAsString	(Ljava/lang/String;)Ljava/lang/String;
/*      */     //   5917: invokevirtual 1025	com/ghintech/puntocom/model/M_C_Invoice_Fiscal:setfiscal_invoicenumber	(Ljava/lang/String;)V
/*      */     //   5920: aload 14
/*      */     //   5922: aload 16
/*      */     //   5924: ldc_w 1028
/*      */     //   5927: invokevirtual 679	org/compiere/model/X_I_Order:get_ValueAsString	(Ljava/lang/String;)Ljava/lang/String;
/*      */     //   5930: invokevirtual 1030	com/ghintech/puntocom/model/M_C_Invoice_Fiscal:setfiscalprint_serial	(Ljava/lang/String;)V
/*      */     //   5933: aload 14
/*      */     //   5935: aload 16
/*      */     //   5937: ldc_w 1033
/*      */     //   5940: invokevirtual 679	org/compiere/model/X_I_Order:get_ValueAsString	(Ljava/lang/String;)Ljava/lang/String;
/*      */     //   5943: invokevirtual 1035	com/ghintech/puntocom/model/M_C_Invoice_Fiscal:setfiscal_zreport	(Ljava/lang/String;)V
/*      */     //   5946: aload 14
/*      */     //   5948: aload 13
/*      */     //   5950: invokevirtual 1038	org/compiere/model/MOrder:getC_Order_ID	()I
/*      */     //   5953: invokevirtual 1041	com/ghintech/puntocom/model/M_C_Invoice_Fiscal:setC_Order_ID	(I)V
/*      */     //   5956: aload 14
/*      */     //   5958: aload 13
/*      */     //   5960: invokevirtual 1044	org/compiere/model/MOrder:getAD_Org_ID	()I
/*      */     //   5963: invokevirtual 1045	com/ghintech/puntocom/model/M_C_Invoice_Fiscal:setAD_Org_ID	(I)V
/*      */     //   5966: aload 14
/*      */     //   5968: invokevirtual 1048	com/ghintech/puntocom/model/M_C_Invoice_Fiscal:save	()Z
/*      */     //   5971: pop
/*      */     //   5972: goto +61 -> 6033
/*      */     //   5975: pop
/*      */     //   5976: getstatic 1049	java/lang/System:out	Ljava/io/PrintStream;
/*      */     //   5979: new 81	java/lang/StringBuilder
/*      */     //   5982: dup
/*      */     //   5983: ldc_w 1053
/*      */     //   5986: invokespecial 85	java/lang/StringBuilder:<init>	(Ljava/lang/String;)V
/*      */     //   5989: aload 13
/*      */     //   5991: invokevirtual 1055	org/compiere/model/MOrder:getDocumentNo	()Ljava/lang/String;
/*      */     //   5994: invokevirtual 88	java/lang/StringBuilder:append	(Ljava/lang/String;)Ljava/lang/StringBuilder;
/*      */     //   5997: invokevirtual 92	java/lang/StringBuilder:toString	()Ljava/lang/String;
/*      */     //   6000: invokevirtual 1056	java/io/PrintStream:println	(Ljava/lang/String;)V
/*      */     //   6003: goto +30 -> 6033
/*      */     //   6006: getstatic 1049	java/lang/System:out	Ljava/io/PrintStream;
/*      */     //   6009: new 81	java/lang/StringBuilder
/*      */     //   6012: dup
/*      */     //   6013: ldc_w 1061
/*      */     //   6016: invokespecial 85	java/lang/StringBuilder:<init>	(Ljava/lang/String;)V
/*      */     //   6019: aload 13
/*      */     //   6021: invokevirtual 1055	org/compiere/model/MOrder:getDocumentNo	()Ljava/lang/String;
/*      */     //   6024: invokevirtual 88	java/lang/StringBuilder:append	(Ljava/lang/String;)Ljava/lang/StringBuilder;
/*      */     //   6027: invokevirtual 92	java/lang/StringBuilder:toString	()Ljava/lang/String;
/*      */     //   6030: invokevirtual 1056	java/io/PrintStream:println	(Ljava/lang/String;)V
/*      */     //   6033: iinc 7 1
/*      */     //   6036: bipush 10
/*      */     //   6038: istore 15
/*      */     //   6040: aload 16
/*      */     //   6042: aload 13
/*      */     //   6044: invokevirtual 1038	org/compiere/model/MOrder:getC_Order_ID	()I
/*      */     //   6047: invokevirtual 1063	org/compiere/model/X_I_Order:setC_Order_ID	(I)V
/*      */     //   6050: new 1064	org/compiere/model/MOrderLine
/*      */     //   6053: dup
/*      */     //   6054: aload 13
/*      */     //   6056: invokespecial 1066	org/compiere/model/MOrderLine:<init>	(Lorg/compiere/model/MOrder;)V
/*      */     //   6059: astore 18
/*      */     //   6061: aload 18
/*      */     //   6063: iload 15
/*      */     //   6065: invokevirtual 1069	org/compiere/model/MOrderLine:setLine	(I)V
/*      */     //   6068: iinc 15 10
/*      */     //   6071: aload 16
/*      */     //   6073: invokevirtual 1072	org/compiere/model/X_I_Order:getM_Product_ID	()I
/*      */     //   6076: ifeq +14 -> 6090
/*      */     //   6079: aload 18
/*      */     //   6081: aload 16
/*      */     //   6083: invokevirtual 1072	org/compiere/model/X_I_Order:getM_Product_ID	()I
/*      */     //   6086: iconst_1
/*      */     //   6087: invokevirtual 1075	org/compiere/model/MOrderLine:setM_Product_ID	(IZ)V
/*      */     //   6090: aload 16
/*      */     //   6092: invokevirtual 1079	org/compiere/model/X_I_Order:getC_Charge_ID	()I
/*      */     //   6095: ifeq +13 -> 6108
/*      */     //   6098: aload 18
/*      */     //   6100: aload 16
/*      */     //   6102: invokevirtual 1079	org/compiere/model/X_I_Order:getC_Charge_ID	()I
/*      */     //   6105: invokevirtual 1082	org/compiere/model/MOrderLine:setC_Charge_ID	(I)V
/*      */     //   6108: aload 18
/*      */     //   6110: aload 16
/*      */     //   6112: invokevirtual 1085	org/compiere/model/X_I_Order:getQtyOrdered	()Ljava/math/BigDecimal;
/*      */     //   6115: invokevirtual 1089	org/compiere/model/MOrderLine:setQty	(Ljava/math/BigDecimal;)V
/*      */     //   6118: aload 18
/*      */     //   6120: invokevirtual 1093	org/compiere/model/MOrderLine:setPrice	()V
/*      */     //   6123: aload 16
/*      */     //   6125: invokevirtual 1096	org/compiere/model/X_I_Order:getPriceActual	()Ljava/math/BigDecimal;
/*      */     //   6128: getstatic 1099	org/compiere/util/Env:ZERO	Ljava/math/BigDecimal;
/*      */     //   6131: invokevirtual 1105	java/math/BigDecimal:compareTo	(Ljava/math/BigDecimal;)I
/*      */     //   6134: ifeq +14 -> 6148
/*      */     //   6137: aload 18
/*      */     //   6139: ldc2_w 1108
/*      */     //   6142: invokestatic 1110	java/math/BigDecimal:valueOf	(J)Ljava/math/BigDecimal;
/*      */     //   6145: invokevirtual 1113	org/compiere/model/MOrderLine:setDiscount	(Ljava/math/BigDecimal;)V
/*      */     //   6148: aload 18
/*      */     //   6150: aload 16
/*      */     //   6152: invokevirtual 1096	org/compiere/model/X_I_Order:getPriceActual	()Ljava/math/BigDecimal;
/*      */     //   6155: invokevirtual 1116	org/compiere/model/MOrderLine:setPrice	(Ljava/math/BigDecimal;)V
/*      */     //   6158: aload 16
/*      */     //   6160: invokevirtual 1118	org/compiere/model/X_I_Order:getC_Tax_ID	()I
/*      */     //   6163: ifeq +16 -> 6179
/*      */     //   6166: aload 18
/*      */     //   6168: aload 16
/*      */     //   6170: invokevirtual 1118	org/compiere/model/X_I_Order:getC_Tax_ID	()I
/*      */     //   6173: invokevirtual 1121	org/compiere/model/MOrderLine:setC_Tax_ID	(I)V
/*      */     //   6176: goto +19 -> 6195
/*      */     //   6179: aload 18
/*      */     //   6181: invokevirtual 1124	org/compiere/model/MOrderLine:setTax	()Z
/*      */     //   6184: pop
/*      */     //   6185: aload 16
/*      */     //   6187: aload 18
/*      */     //   6189: invokevirtual 1127	org/compiere/model/MOrderLine:getC_Tax_ID	()I
/*      */     //   6192: invokevirtual 1128	org/compiere/model/X_I_Order:setC_Tax_ID	(I)V
/*      */     //   6195: aload 16
/*      */     //   6197: invokevirtual 1129	org/compiere/model/X_I_Order:getFreightAmt	()Ljava/math/BigDecimal;
/*      */     //   6200: ifnull +13 -> 6213
/*      */     //   6203: aload 18
/*      */     //   6205: aload 16
/*      */     //   6207: invokevirtual 1129	org/compiere/model/X_I_Order:getFreightAmt	()Ljava/math/BigDecimal;
/*      */     //   6210: invokevirtual 1132	org/compiere/model/MOrderLine:setFreightAmt	(Ljava/math/BigDecimal;)V
/*      */     //   6213: aload 16
/*      */     //   6215: invokevirtual 1135	org/compiere/model/X_I_Order:getLineDescription	()Ljava/lang/String;
/*      */     //   6218: ifnull +13 -> 6231
/*      */     //   6221: aload 18
/*      */     //   6223: aload 16
/*      */     //   6225: invokevirtual 1135	org/compiere/model/X_I_Order:getLineDescription	()Ljava/lang/String;
/*      */     //   6228: invokevirtual 1138	org/compiere/model/MOrderLine:setDescription	(Ljava/lang/String;)V
/*      */     //   6231: aload 18
/*      */     //   6233: aload 18
/*      */     //   6235: invokevirtual 1139	org/compiere/model/MOrderLine:getQtyEntered	()Ljava/math/BigDecimal;
/*      */     //   6238: aload 18
/*      */     //   6240: invokevirtual 1142	org/compiere/model/MOrderLine:getPriceEntered	()Ljava/math/BigDecimal;
/*      */     //   6243: invokevirtual 1145	java/math/BigDecimal:multiply	(Ljava/math/BigDecimal;)Ljava/math/BigDecimal;
/*      */     //   6246: invokevirtual 1149	org/compiere/model/MOrderLine:setLineNetAmt	(Ljava/math/BigDecimal;)V
/*      */     //   6249: aload 18
/*      */     //   6251: invokevirtual 1152	org/compiere/model/MOrderLine:saveEx	()V
/*      */     //   6254: aload 16
/*      */     //   6256: aload 18
/*      */     //   6258: invokevirtual 1153	org/compiere/model/MOrderLine:getC_OrderLine_ID	()I
/*      */     //   6261: invokevirtual 1156	org/compiere/model/X_I_Order:setC_OrderLine_ID	(I)V
/*      */     //   6264: aload 16
/*      */     //   6266: iconst_1
/*      */     //   6267: invokevirtual 1159	org/compiere/model/X_I_Order:setI_IsImported	(Z)V
/*      */     //   6270: aload 16
/*      */     //   6272: iconst_1
/*      */     //   6273: invokevirtual 1162	org/compiere/model/X_I_Order:setProcessed	(Z)V
/*      */     //   6276: aload 16
/*      */     //   6278: invokevirtual 832	org/compiere/model/X_I_Order:save	()Z
/*      */     //   6281: ifeq +6 -> 6287
/*      */     //   6284: iinc 8 1
/*      */     //   6287: aload 5
/*      */     //   6289: invokeinterface 1165 1 0
/*      */     //   6294: ifne -1073 -> 5221
/*      */     //   6297: aload 13
/*      */     //   6299: ifnull +235 -> 6534
/*      */     //   6302: aload_0
/*      */     //   6303: getfield 27	com/ghintech/puntocom/process/ImportOrder:m_docAction	Ljava/lang/String;
/*      */     //   6306: ifnull +113 -> 6419
/*      */     //   6309: aload_0
/*      */     //   6310: getfield 27	com/ghintech/puntocom/process/ImportOrder:m_docAction	Ljava/lang/String;
/*      */     //   6313: invokevirtual 872	java/lang/String:length	()I
/*      */     //   6316: ifle +103 -> 6419
/*      */     //   6319: aload 13
/*      */     //   6321: aload_0
/*      */     //   6322: getfield 27	com/ghintech/puntocom/process/ImportOrder:m_docAction	Ljava/lang/String;
/*      */     //   6325: invokevirtual 875	org/compiere/model/MOrder:setDocAction	(Ljava/lang/String;)V
/*      */     //   6328: aload 13
/*      */     //   6330: aload_0
/*      */     //   6331: getfield 27	com/ghintech/puntocom/process/ImportOrder:m_docAction	Ljava/lang/String;
/*      */     //   6334: invokevirtual 880	org/compiere/model/MOrder:processIt	(Ljava/lang/String;)Z
/*      */     //   6337: ifne +82 -> 6419
/*      */     //   6340: aload_0
/*      */     //   6341: getfield 71	com/ghintech/puntocom/process/ImportOrder:log	Lorg/compiere/util/CLogger;
/*      */     //   6344: new 81	java/lang/StringBuilder
/*      */     //   6347: dup
/*      */     //   6348: ldc_w 884
/*      */     //   6351: invokespecial 85	java/lang/StringBuilder:<init>	(Ljava/lang/String;)V
/*      */     //   6354: aload 13
/*      */     //   6356: invokevirtual 886	java/lang/StringBuilder:append	(Ljava/lang/Object;)Ljava/lang/StringBuilder;
/*      */     //   6359: ldc_w 889
/*      */     //   6362: invokevirtual 88	java/lang/StringBuilder:append	(Ljava/lang/String;)Ljava/lang/StringBuilder;
/*      */     //   6365: aload 13
/*      */     //   6367: invokevirtual 891	org/compiere/model/MOrder:getProcessMsg	()Ljava/lang/String;
/*      */     //   6370: invokevirtual 88	java/lang/StringBuilder:append	(Ljava/lang/String;)Ljava/lang/StringBuilder;
/*      */     //   6373: invokevirtual 92	java/lang/StringBuilder:toString	()Ljava/lang/String;
/*      */     //   6376: invokevirtual 206	org/compiere/util/CLogger:warning	(Ljava/lang/String;)V
/*      */     //   6379: new 894	java/lang/IllegalStateException
/*      */     //   6382: dup
/*      */     //   6383: new 81	java/lang/StringBuilder
/*      */     //   6386: dup
/*      */     //   6387: ldc_w 884
/*      */     //   6390: invokespecial 85	java/lang/StringBuilder:<init>	(Ljava/lang/String;)V
/*      */     //   6393: aload 13
/*      */     //   6395: invokevirtual 886	java/lang/StringBuilder:append	(Ljava/lang/Object;)Ljava/lang/StringBuilder;
/*      */     //   6398: ldc_w 889
/*      */     //   6401: invokevirtual 88	java/lang/StringBuilder:append	(Ljava/lang/String;)Ljava/lang/StringBuilder;
/*      */     //   6404: aload 13
/*      */     //   6406: invokevirtual 891	org/compiere/model/MOrder:getProcessMsg	()Ljava/lang/String;
/*      */     //   6409: invokevirtual 88	java/lang/StringBuilder:append	(Ljava/lang/String;)Ljava/lang/StringBuilder;
/*      */     //   6412: invokevirtual 92	java/lang/StringBuilder:toString	()Ljava/lang/String;
/*      */     //   6415: invokespecial 896	java/lang/IllegalStateException:<init>	(Ljava/lang/String;)V
/*      */     //   6418: athrow
/*      */     //   6419: aload 14
/*      */     //   6421: invokevirtual 1169	com/ghintech/puntocom/model/M_C_Invoice_Fiscal:getfiscal_invoicenumber	()Ljava/lang/String;
/*      */     //   6424: ifnull +23 -> 6447
/*      */     //   6427: aload 14
/*      */     //   6429: aload 13
/*      */     //   6431: invokevirtual 1172	org/compiere/model/MOrder:getC_Invoice_ID	()I
/*      */     //   6434: invokevirtual 1175	com/ghintech/puntocom/model/M_C_Invoice_Fiscal:setC_Invoice_ID	(I)V
/*      */     //   6437: aload 14
/*      */     //   6439: invokevirtual 1048	com/ghintech/puntocom/model/M_C_Invoice_Fiscal:save	()Z
/*      */     //   6442: pop
/*      */     //   6443: goto +4 -> 6447
/*      */     //   6446: pop
/*      */     //   6447: aload 13
/*      */     //   6449: invokevirtual 897	org/compiere/model/MOrder:saveEx	()V
/*      */     //   6452: aload_0
/*      */     //   6453: invokevirtual 521	com/ghintech/puntocom/process/ImportOrder:commitEx	()V
/*      */     //   6456: aload_0
/*      */     //   6457: aload 13
/*      */     //   6459: invokespecial 900	com/ghintech/puntocom/process/ImportOrder:createAllocation	(Lorg/compiere/model/MOrder;)Ljava/lang/String;
/*      */     //   6462: pop
/*      */     //   6463: goto +71 -> 6534
/*      */     //   6466: astore 9
/*      */     //   6468: aload_0
/*      */     //   6469: getfield 71	com/ghintech/puntocom/process/ImportOrder:log	Lorg/compiere/util/CLogger;
/*      */     //   6472: getstatic 75	java/util/logging/Level:SEVERE	Ljava/util/logging/Level;
/*      */     //   6475: new 81	java/lang/StringBuilder
/*      */     //   6478: dup
/*      */     //   6479: ldc_w 1178
/*      */     //   6482: invokespecial 85	java/lang/StringBuilder:<init>	(Ljava/lang/String;)V
/*      */     //   6485: aload_1
/*      */     //   6486: invokevirtual 92	java/lang/StringBuilder:toString	()Ljava/lang/String;
/*      */     //   6489: invokevirtual 88	java/lang/StringBuilder:append	(Ljava/lang/String;)Ljava/lang/StringBuilder;
/*      */     //   6492: invokevirtual 92	java/lang/StringBuilder:toString	()Ljava/lang/String;
/*      */     //   6495: aload 9
/*      */     //   6497: invokevirtual 1180	org/compiere/util/CLogger:log	(Ljava/util/logging/Level;Ljava/lang/String;Ljava/lang/Throwable;)V
/*      */     //   6500: aload 5
/*      */     //   6502: aload 4
/*      */     //   6504: invokestatic 1183	org/compiere/util/DB:close	(Ljava/sql/ResultSet;Ljava/sql/Statement;)V
/*      */     //   6507: aconst_null
/*      */     //   6508: astore 5
/*      */     //   6510: aconst_null
/*      */     //   6511: astore 4
/*      */     //   6513: goto +34 -> 6547
/*      */     //   6516: astore 19
/*      */     //   6518: aload 5
/*      */     //   6520: aload 4
/*      */     //   6522: invokestatic 1183	org/compiere/util/DB:close	(Ljava/sql/ResultSet;Ljava/sql/Statement;)V
/*      */     //   6525: aconst_null
/*      */     //   6526: astore 5
/*      */     //   6528: aconst_null
/*      */     //   6529: astore 4
/*      */     //   6531: aload 19
/*      */     //   6533: athrow
/*      */     //   6534: aload 5
/*      */     //   6536: aload 4
/*      */     //   6538: invokestatic 1183	org/compiere/util/DB:close	(Ljava/sql/ResultSet;Ljava/sql/Statement;)V
/*      */     //   6541: aconst_null
/*      */     //   6542: astore 5
/*      */     //   6544: aconst_null
/*      */     //   6545: astore 4
/*      */     //   6547: new 81	java/lang/StringBuilder
/*      */     //   6550: dup
/*      */     //   6551: ldc -102
/*      */     //   6553: invokespecial 85	java/lang/StringBuilder:<init>	(Ljava/lang/String;)V
/*      */     //   6556: ldc_w 1187
/*      */     //   6559: invokevirtual 88	java/lang/StringBuilder:append	(Ljava/lang/String;)Ljava/lang/StringBuilder;
/*      */     //   6562: ldc_w 1189
/*      */     //   6565: invokevirtual 88	java/lang/StringBuilder:append	(Ljava/lang/String;)Ljava/lang/StringBuilder;
/*      */     //   6568: aload_3
/*      */     //   6569: invokevirtual 130	java/lang/StringBuilder:append	(Ljava/lang/CharSequence;)Ljava/lang/StringBuilder;
/*      */     //   6572: astore_1
/*      */     //   6573: aload_1
/*      */     //   6574: invokevirtual 92	java/lang/StringBuilder:toString	()Ljava/lang/String;
/*      */     //   6577: aload_0
/*      */     //   6578: invokevirtual 133	com/ghintech/puntocom/process/ImportOrder:get_TrxName	()Ljava/lang/String;
/*      */     //   6581: invokestatic 136	org/compiere/util/DB:executeUpdate	(Ljava/lang/String;Ljava/lang/String;)I
/*      */     //   6584: istore_2
/*      */     //   6585: aload_0
/*      */     //   6586: iconst_0
/*      */     //   6587: aconst_null
/*      */     //   6588: new 57	java/math/BigDecimal
/*      */     //   6591: dup
/*      */     //   6592: iload_2
/*      */     //   6593: invokespecial 1191	java/math/BigDecimal:<init>	(I)V
/*      */     //   6596: ldc_w 1193
/*      */     //   6599: invokevirtual 1195	com/ghintech/puntocom/process/ImportOrder:addLog	(ILjava/sql/Timestamp;Ljava/math/BigDecimal;Ljava/lang/String;)V
/*      */     //   6602: aload_0
/*      */     //   6603: iconst_0
/*      */     //   6604: aconst_null
/*      */     //   6605: new 57	java/math/BigDecimal
/*      */     //   6608: dup
/*      */     //   6609: iload 7
/*      */     //   6611: invokespecial 1191	java/math/BigDecimal:<init>	(I)V
/*      */     //   6614: ldc_w 1199
/*      */     //   6617: invokevirtual 1195	com/ghintech/puntocom/process/ImportOrder:addLog	(ILjava/sql/Timestamp;Ljava/math/BigDecimal;Ljava/lang/String;)V
/*      */     //   6620: aload_0
/*      */     //   6621: iconst_0
/*      */     //   6622: aconst_null
/*      */     //   6623: new 57	java/math/BigDecimal
/*      */     //   6626: dup
/*      */     //   6627: iload 8
/*      */     //   6629: invokespecial 1191	java/math/BigDecimal:<init>	(I)V
/*      */     //   6632: ldc_w 1201
/*      */     //   6635: invokevirtual 1195	com/ghintech/puntocom/process/ImportOrder:addLog	(ILjava/sql/Timestamp;Ljava/math/BigDecimal;Ljava/lang/String;)V
/*      */     //   6638: new 81	java/lang/StringBuilder
/*      */     //   6641: dup
/*      */     //   6642: ldc_w 1203
/*      */     //   6645: invokespecial 85	java/lang/StringBuilder:<init>	(Ljava/lang/String;)V
/*      */     //   6648: iload 7
/*      */     //   6650: invokevirtual 123	java/lang/StringBuilder:append	(I)Ljava/lang/StringBuilder;
/*      */     //   6653: ldc_w 1205
/*      */     //   6656: invokevirtual 88	java/lang/StringBuilder:append	(Ljava/lang/String;)Ljava/lang/StringBuilder;
/*      */     //   6659: iload 8
/*      */     //   6661: invokevirtual 123	java/lang/StringBuilder:append	(I)Ljava/lang/StringBuilder;
/*      */     //   6664: astore 9
/*      */     //   6666: aload 9
/*      */     //   6668: invokevirtual 92	java/lang/StringBuilder:toString	()Ljava/lang/String;
/*      */     //   6671: areturn
/*      */     // Line number table:
/*      */     //   Java source line #103	-> byte code offset #0
/*      */     //   Java source line #104	-> byte code offset #2
/*      */     //   Java source line #105	-> byte code offset #4
/*      */     //   Java source line #110	-> byte code offset #21
/*      */     //   Java source line #112	-> byte code offset #28
/*      */     //   Java source line #113	-> byte code offset #37
/*      */     //   Java source line #112	-> byte code offset #46
/*      */     //   Java source line #114	-> byte code offset #47
/*      */     //   Java source line #115	-> byte code offset #59
/*      */     //   Java source line #119	-> byte code offset #95
/*      */     //   Java source line #120	-> byte code offset #104
/*      */     //   Java source line #121	-> byte code offset #121
/*      */     //   Java source line #122	-> byte code offset #138
/*      */     //   Java source line #123	-> byte code offset #143
/*      */     //   Java source line #124	-> byte code offset #148
/*      */     //   Java source line #125	-> byte code offset #153
/*      */     //   Java source line #126	-> byte code offset #158
/*      */     //   Java source line #127	-> byte code offset #163
/*      */     //   Java source line #128	-> byte code offset #168
/*      */     //   Java source line #129	-> byte code offset #173
/*      */     //   Java source line #119	-> byte code offset #178
/*      */     //   Java source line #130	-> byte code offset #179
/*      */     //   Java source line #131	-> byte code offset #191
/*      */     //   Java source line #134	-> byte code offset #227
/*      */     //   Java source line #135	-> byte code offset #236
/*      */     //   Java source line #136	-> byte code offset #241
/*      */     //   Java source line #137	-> byte code offset #246
/*      */     //   Java source line #134	-> byte code offset #255
/*      */     //   Java source line #138	-> byte code offset #256
/*      */     //   Java source line #139	-> byte code offset #268
/*      */     //   Java source line #140	-> byte code offset #272
/*      */     //   Java source line #144	-> byte code offset #295
/*      */     //   Java source line #145	-> byte code offset #304
/*      */     //   Java source line #146	-> byte code offset #309
/*      */     //   Java source line #147	-> byte code offset #314
/*      */     //   Java source line #148	-> byte code offset #319
/*      */     //   Java source line #144	-> byte code offset #328
/*      */     //   Java source line #149	-> byte code offset #329
/*      */     //   Java source line #150	-> byte code offset #341
/*      */     //   Java source line #151	-> byte code offset #345
/*      */     //   Java source line #154	-> byte code offset #368
/*      */     //   Java source line #155	-> byte code offset #377
/*      */     //   Java source line #156	-> byte code offset #382
/*      */     //   Java source line #157	-> byte code offset #387
/*      */     //   Java source line #154	-> byte code offset #396
/*      */     //   Java source line #158	-> byte code offset #397
/*      */     //   Java source line #159	-> byte code offset #409
/*      */     //   Java source line #160	-> byte code offset #445
/*      */     //   Java source line #161	-> byte code offset #454
/*      */     //   Java source line #162	-> byte code offset #459
/*      */     //   Java source line #163	-> byte code offset #464
/*      */     //   Java source line #160	-> byte code offset #473
/*      */     //   Java source line #164	-> byte code offset #474
/*      */     //   Java source line #165	-> byte code offset #486
/*      */     //   Java source line #166	-> byte code offset #522
/*      */     //   Java source line #167	-> byte code offset #531
/*      */     //   Java source line #168	-> byte code offset #536
/*      */     //   Java source line #170	-> byte code offset #541
/*      */     //   Java source line #166	-> byte code offset #550
/*      */     //   Java source line #171	-> byte code offset #551
/*      */     //   Java source line #172	-> byte code offset #563
/*      */     //   Java source line #173	-> byte code offset #599
/*      */     //   Java source line #174	-> byte code offset #608
/*      */     //   Java source line #175	-> byte code offset #613
/*      */     //   Java source line #176	-> byte code offset #618
/*      */     //   Java source line #173	-> byte code offset #627
/*      */     //   Java source line #177	-> byte code offset #628
/*      */     //   Java source line #178	-> byte code offset #640
/*      */     //   Java source line #179	-> byte code offset #644
/*      */     //   Java source line #181	-> byte code offset #667
/*      */     //   Java source line #182	-> byte code offset #676
/*      */     //   Java source line #183	-> byte code offset #681
/*      */     //   Java source line #184	-> byte code offset #686
/*      */     //   Java source line #181	-> byte code offset #695
/*      */     //   Java source line #185	-> byte code offset #696
/*      */     //   Java source line #186	-> byte code offset #708
/*      */     //   Java source line #187	-> byte code offset #744
/*      */     //   Java source line #188	-> byte code offset #753
/*      */     //   Java source line #189	-> byte code offset #758
/*      */     //   Java source line #190	-> byte code offset #763
/*      */     //   Java source line #187	-> byte code offset #772
/*      */     //   Java source line #191	-> byte code offset #773
/*      */     //   Java source line #192	-> byte code offset #785
/*      */     //   Java source line #193	-> byte code offset #821
/*      */     //   Java source line #194	-> byte code offset #830
/*      */     //   Java source line #195	-> byte code offset #835
/*      */     //   Java source line #196	-> byte code offset #840
/*      */     //   Java source line #193	-> byte code offset #849
/*      */     //   Java source line #197	-> byte code offset #850
/*      */     //   Java source line #198	-> byte code offset #862
/*      */     //   Java source line #199	-> byte code offset #898
/*      */     //   Java source line #200	-> byte code offset #907
/*      */     //   Java source line #201	-> byte code offset #912
/*      */     //   Java source line #202	-> byte code offset #917
/*      */     //   Java source line #199	-> byte code offset #926
/*      */     //   Java source line #203	-> byte code offset #927
/*      */     //   Java source line #204	-> byte code offset #939
/*      */     //   Java source line #205	-> byte code offset #943
/*      */     //   Java source line #208	-> byte code offset #966
/*      */     //   Java source line #209	-> byte code offset #976
/*      */     //   Java source line #210	-> byte code offset #982
/*      */     //   Java source line #211	-> byte code offset #988
/*      */     //   Java source line #208	-> byte code offset #997
/*      */     //   Java source line #212	-> byte code offset #998
/*      */     //   Java source line #213	-> byte code offset #1010
/*      */     //   Java source line #214	-> byte code offset #1047
/*      */     //   Java source line #215	-> byte code offset #1057
/*      */     //   Java source line #216	-> byte code offset #1063
/*      */     //   Java source line #217	-> byte code offset #1069
/*      */     //   Java source line #214	-> byte code offset #1078
/*      */     //   Java source line #218	-> byte code offset #1079
/*      */     //   Java source line #219	-> byte code offset #1091
/*      */     //   Java source line #222	-> byte code offset #1128
/*      */     //   Java source line #223	-> byte code offset #1137
/*      */     //   Java source line #224	-> byte code offset #1143
/*      */     //   Java source line #225	-> byte code offset #1149
/*      */     //   Java source line #222	-> byte code offset #1159
/*      */     //   Java source line #226	-> byte code offset #1160
/*      */     //   Java source line #227	-> byte code offset #1172
/*      */     //   Java source line #228	-> byte code offset #1209
/*      */     //   Java source line #229	-> byte code offset #1218
/*      */     //   Java source line #230	-> byte code offset #1224
/*      */     //   Java source line #231	-> byte code offset #1230
/*      */     //   Java source line #228	-> byte code offset #1240
/*      */     //   Java source line #232	-> byte code offset #1241
/*      */     //   Java source line #233	-> byte code offset #1253
/*      */     //   Java source line #234	-> byte code offset #1290
/*      */     //   Java source line #235	-> byte code offset #1299
/*      */     //   Java source line #236	-> byte code offset #1305
/*      */     //   Java source line #237	-> byte code offset #1311
/*      */     //   Java source line #234	-> byte code offset #1321
/*      */     //   Java source line #238	-> byte code offset #1322
/*      */     //   Java source line #239	-> byte code offset #1334
/*      */     //   Java source line #240	-> byte code offset #1371
/*      */     //   Java source line #241	-> byte code offset #1380
/*      */     //   Java source line #242	-> byte code offset #1386
/*      */     //   Java source line #243	-> byte code offset #1392
/*      */     //   Java source line #240	-> byte code offset #1402
/*      */     //   Java source line #244	-> byte code offset #1403
/*      */     //   Java source line #245	-> byte code offset #1415
/*      */     //   Java source line #247	-> byte code offset #1452
/*      */     //   Java source line #248	-> byte code offset #1461
/*      */     //   Java source line #249	-> byte code offset #1467
/*      */     //   Java source line #250	-> byte code offset #1473
/*      */     //   Java source line #247	-> byte code offset #1482
/*      */     //   Java source line #251	-> byte code offset #1483
/*      */     //   Java source line #252	-> byte code offset #1495
/*      */     //   Java source line #253	-> byte code offset #1499
/*      */     //   Java source line #256	-> byte code offset #1523
/*      */     //   Java source line #257	-> byte code offset #1532
/*      */     //   Java source line #258	-> byte code offset #1538
/*      */     //   Java source line #259	-> byte code offset #1544
/*      */     //   Java source line #256	-> byte code offset #1554
/*      */     //   Java source line #260	-> byte code offset #1555
/*      */     //   Java source line #261	-> byte code offset #1567
/*      */     //   Java source line #263	-> byte code offset #1604
/*      */     //   Java source line #264	-> byte code offset #1613
/*      */     //   Java source line #265	-> byte code offset #1619
/*      */     //   Java source line #263	-> byte code offset #1629
/*      */     //   Java source line #266	-> byte code offset #1630
/*      */     //   Java source line #267	-> byte code offset #1642
/*      */     //   Java source line #268	-> byte code offset #1646
/*      */     //   Java source line #271	-> byte code offset #1670
/*      */     //   Java source line #272	-> byte code offset #1679
/*      */     //   Java source line #273	-> byte code offset #1685
/*      */     //   Java source line #274	-> byte code offset #1691
/*      */     //   Java source line #271	-> byte code offset #1701
/*      */     //   Java source line #275	-> byte code offset #1702
/*      */     //   Java source line #276	-> byte code offset #1714
/*      */     //   Java source line #277	-> byte code offset #1751
/*      */     //   Java source line #278	-> byte code offset #1760
/*      */     //   Java source line #279	-> byte code offset #1766
/*      */     //   Java source line #280	-> byte code offset #1772
/*      */     //   Java source line #277	-> byte code offset #1782
/*      */     //   Java source line #281	-> byte code offset #1783
/*      */     //   Java source line #282	-> byte code offset #1795
/*      */     //   Java source line #284	-> byte code offset #1832
/*      */     //   Java source line #285	-> byte code offset #1841
/*      */     //   Java source line #286	-> byte code offset #1847
/*      */     //   Java source line #287	-> byte code offset #1853
/*      */     //   Java source line #284	-> byte code offset #1862
/*      */     //   Java source line #288	-> byte code offset #1863
/*      */     //   Java source line #289	-> byte code offset #1875
/*      */     //   Java source line #290	-> byte code offset #1879
/*      */     //   Java source line #293	-> byte code offset #1903
/*      */     //   Java source line #294	-> byte code offset #1912
/*      */     //   Java source line #295	-> byte code offset #1918
/*      */     //   Java source line #296	-> byte code offset #1924
/*      */     //   Java source line #293	-> byte code offset #1934
/*      */     //   Java source line #297	-> byte code offset #1935
/*      */     //   Java source line #298	-> byte code offset #1947
/*      */     //   Java source line #299	-> byte code offset #1951
/*      */     //   Java source line #300	-> byte code offset #1988
/*      */     //   Java source line #301	-> byte code offset #1997
/*      */     //   Java source line #302	-> byte code offset #2003
/*      */     //   Java source line #303	-> byte code offset #2009
/*      */     //   Java source line #304	-> byte code offset #2015
/*      */     //   Java source line #305	-> byte code offset #2021
/*      */     //   Java source line #300	-> byte code offset #2030
/*      */     //   Java source line #306	-> byte code offset #2031
/*      */     //   Java source line #307	-> byte code offset #2043
/*      */     //   Java source line #308	-> byte code offset #2047
/*      */     //   Java source line #310	-> byte code offset #2084
/*      */     //   Java source line #311	-> byte code offset #2093
/*      */     //   Java source line #312	-> byte code offset #2099
/*      */     //   Java source line #313	-> byte code offset #2105
/*      */     //   Java source line #310	-> byte code offset #2114
/*      */     //   Java source line #314	-> byte code offset #2115
/*      */     //   Java source line #315	-> byte code offset #2127
/*      */     //   Java source line #316	-> byte code offset #2131
/*      */     //   Java source line #336	-> byte code offset #2155
/*      */     //   Java source line #337	-> byte code offset #2164
/*      */     //   Java source line #338	-> byte code offset #2170
/*      */     //   Java source line #339	-> byte code offset #2176
/*      */     //   Java source line #340	-> byte code offset #2182
/*      */     //   Java source line #336	-> byte code offset #2191
/*      */     //   Java source line #341	-> byte code offset #2192
/*      */     //   Java source line #342	-> byte code offset #2204
/*      */     //   Java source line #344	-> byte code offset #2241
/*      */     //   Java source line #345	-> byte code offset #2250
/*      */     //   Java source line #346	-> byte code offset #2256
/*      */     //   Java source line #347	-> byte code offset #2262
/*      */     //   Java source line #348	-> byte code offset #2268
/*      */     //   Java source line #344	-> byte code offset #2277
/*      */     //   Java source line #349	-> byte code offset #2278
/*      */     //   Java source line #350	-> byte code offset #2290
/*      */     //   Java source line #353	-> byte code offset #2327
/*      */     //   Java source line #354	-> byte code offset #2336
/*      */     //   Java source line #355	-> byte code offset #2342
/*      */     //   Java source line #356	-> byte code offset #2348
/*      */     //   Java source line #357	-> byte code offset #2354
/*      */     //   Java source line #358	-> byte code offset #2360
/*      */     //   Java source line #359	-> byte code offset #2366
/*      */     //   Java source line #360	-> byte code offset #2372
/*      */     //   Java source line #361	-> byte code offset #2378
/*      */     //   Java source line #353	-> byte code offset #2388
/*      */     //   Java source line #362	-> byte code offset #2389
/*      */     //   Java source line #363	-> byte code offset #2401
/*      */     //   Java source line #365	-> byte code offset #2438
/*      */     //   Java source line #366	-> byte code offset #2447
/*      */     //   Java source line #367	-> byte code offset #2453
/*      */     //   Java source line #368	-> byte code offset #2459
/*      */     //   Java source line #369	-> byte code offset #2465
/*      */     //   Java source line #370	-> byte code offset #2471
/*      */     //   Java source line #371	-> byte code offset #2477
/*      */     //   Java source line #365	-> byte code offset #2486
/*      */     //   Java source line #372	-> byte code offset #2487
/*      */     //   Java source line #373	-> byte code offset #2499
/*      */     //   Java source line #375	-> byte code offset #2536
/*      */     //   Java source line #376	-> byte code offset #2545
/*      */     //   Java source line #377	-> byte code offset #2551
/*      */     //   Java source line #378	-> byte code offset #2557
/*      */     //   Java source line #379	-> byte code offset #2563
/*      */     //   Java source line #380	-> byte code offset #2569
/*      */     //   Java source line #381	-> byte code offset #2575
/*      */     //   Java source line #375	-> byte code offset #2584
/*      */     //   Java source line #382	-> byte code offset #2585
/*      */     //   Java source line #383	-> byte code offset #2597
/*      */     //   Java source line #385	-> byte code offset #2634
/*      */     //   Java source line #386	-> byte code offset #2643
/*      */     //   Java source line #387	-> byte code offset #2649
/*      */     //   Java source line #388	-> byte code offset #2655
/*      */     //   Java source line #385	-> byte code offset #2664
/*      */     //   Java source line #389	-> byte code offset #2665
/*      */     //   Java source line #390	-> byte code offset #2677
/*      */     //   Java source line #391	-> byte code offset #2681
/*      */     //   Java source line #403	-> byte code offset #2705
/*      */     //   Java source line #404	-> byte code offset #2714
/*      */     //   Java source line #405	-> byte code offset #2720
/*      */     //   Java source line #406	-> byte code offset #2726
/*      */     //   Java source line #407	-> byte code offset #2732
/*      */     //   Java source line #403	-> byte code offset #2741
/*      */     //   Java source line #408	-> byte code offset #2742
/*      */     //   Java source line #409	-> byte code offset #2754
/*      */     //   Java source line #411	-> byte code offset #2791
/*      */     //   Java source line #412	-> byte code offset #2800
/*      */     //   Java source line #413	-> byte code offset #2806
/*      */     //   Java source line #414	-> byte code offset #2812
/*      */     //   Java source line #411	-> byte code offset #2821
/*      */     //   Java source line #415	-> byte code offset #2822
/*      */     //   Java source line #416	-> byte code offset #2834
/*      */     //   Java source line #417	-> byte code offset #2838
/*      */     //   Java source line #420	-> byte code offset #2862
/*      */     //   Java source line #421	-> byte code offset #2871
/*      */     //   Java source line #422	-> byte code offset #2877
/*      */     //   Java source line #423	-> byte code offset #2883
/*      */     //   Java source line #424	-> byte code offset #2889
/*      */     //   Java source line #425	-> byte code offset #2895
/*      */     //   Java source line #420	-> byte code offset #2904
/*      */     //   Java source line #426	-> byte code offset #2905
/*      */     //   Java source line #427	-> byte code offset #2917
/*      */     //   Java source line #429	-> byte code offset #2954
/*      */     //   Java source line #430	-> byte code offset #2963
/*      */     //   Java source line #431	-> byte code offset #2969
/*      */     //   Java source line #432	-> byte code offset #2975
/*      */     //   Java source line #433	-> byte code offset #2981
/*      */     //   Java source line #434	-> byte code offset #2987
/*      */     //   Java source line #429	-> byte code offset #2996
/*      */     //   Java source line #435	-> byte code offset #2997
/*      */     //   Java source line #436	-> byte code offset #3009
/*      */     //   Java source line #438	-> byte code offset #3046
/*      */     //   Java source line #439	-> byte code offset #3055
/*      */     //   Java source line #440	-> byte code offset #3061
/*      */     //   Java source line #441	-> byte code offset #3067
/*      */     //   Java source line #442	-> byte code offset #3073
/*      */     //   Java source line #443	-> byte code offset #3079
/*      */     //   Java source line #438	-> byte code offset #3088
/*      */     //   Java source line #444	-> byte code offset #3089
/*      */     //   Java source line #445	-> byte code offset #3101
/*      */     //   Java source line #446	-> byte code offset #3105
/*      */     //   Java source line #449	-> byte code offset #3129
/*      */     //   Java source line #450	-> byte code offset #3138
/*      */     //   Java source line #451	-> byte code offset #3144
/*      */     //   Java source line #452	-> byte code offset #3150
/*      */     //   Java source line #453	-> byte code offset #3156
/*      */     //   Java source line #449	-> byte code offset #3165
/*      */     //   Java source line #454	-> byte code offset #3166
/*      */     //   Java source line #455	-> byte code offset #3178
/*      */     //   Java source line #456	-> byte code offset #3215
/*      */     //   Java source line #457	-> byte code offset #3224
/*      */     //   Java source line #458	-> byte code offset #3230
/*      */     //   Java source line #459	-> byte code offset #3236
/*      */     //   Java source line #460	-> byte code offset #3242
/*      */     //   Java source line #456	-> byte code offset #3251
/*      */     //   Java source line #461	-> byte code offset #3252
/*      */     //   Java source line #462	-> byte code offset #3264
/*      */     //   Java source line #463	-> byte code offset #3301
/*      */     //   Java source line #464	-> byte code offset #3310
/*      */     //   Java source line #465	-> byte code offset #3316
/*      */     //   Java source line #466	-> byte code offset #3322
/*      */     //   Java source line #467	-> byte code offset #3328
/*      */     //   Java source line #463	-> byte code offset #3337
/*      */     //   Java source line #468	-> byte code offset #3338
/*      */     //   Java source line #469	-> byte code offset #3350
/*      */     //   Java source line #470	-> byte code offset #3387
/*      */     //   Java source line #471	-> byte code offset #3396
/*      */     //   Java source line #472	-> byte code offset #3402
/*      */     //   Java source line #473	-> byte code offset #3408
/*      */     //   Java source line #470	-> byte code offset #3417
/*      */     //   Java source line #474	-> byte code offset #3418
/*      */     //   Java source line #475	-> byte code offset #3430
/*      */     //   Java source line #476	-> byte code offset #3434
/*      */     //   Java source line #479	-> byte code offset #3458
/*      */     //   Java source line #480	-> byte code offset #3467
/*      */     //   Java source line #481	-> byte code offset #3473
/*      */     //   Java source line #482	-> byte code offset #3479
/*      */     //   Java source line #479	-> byte code offset #3489
/*      */     //   Java source line #483	-> byte code offset #3490
/*      */     //   Java source line #484	-> byte code offset #3502
/*      */     //   Java source line #485	-> byte code offset #3539
/*      */     //   Java source line #486	-> byte code offset #3548
/*      */     //   Java source line #487	-> byte code offset #3554
/*      */     //   Java source line #488	-> byte code offset #3560
/*      */     //   Java source line #485	-> byte code offset #3569
/*      */     //   Java source line #489	-> byte code offset #3570
/*      */     //   Java source line #490	-> byte code offset #3582
/*      */     //   Java source line #491	-> byte code offset #3586
/*      */     //   Java source line #494	-> byte code offset #3610
/*      */     //   Java source line #495	-> byte code offset #3619
/*      */     //   Java source line #496	-> byte code offset #3625
/*      */     //   Java source line #497	-> byte code offset #3631
/*      */     //   Java source line #494	-> byte code offset #3640
/*      */     //   Java source line #498	-> byte code offset #3641
/*      */     //   Java source line #499	-> byte code offset #3653
/*      */     //   Java source line #500	-> byte code offset #3657
/*      */     //   Java source line #503	-> byte code offset #3681
/*      */     //   Java source line #504	-> byte code offset #3690
/*      */     //   Java source line #505	-> byte code offset #3696
/*      */     //   Java source line #506	-> byte code offset #3702
/*      */     //   Java source line #507	-> byte code offset #3708
/*      */     //   Java source line #503	-> byte code offset #3717
/*      */     //   Java source line #508	-> byte code offset #3718
/*      */     //   Java source line #509	-> byte code offset #3730
/*      */     //   Java source line #510	-> byte code offset #3767
/*      */     //   Java source line #511	-> byte code offset #3776
/*      */     //   Java source line #512	-> byte code offset #3782
/*      */     //   Java source line #513	-> byte code offset #3788
/*      */     //   Java source line #510	-> byte code offset #3797
/*      */     //   Java source line #514	-> byte code offset #3798
/*      */     //   Java source line #515	-> byte code offset #3810
/*      */     //   Java source line #516	-> byte code offset #3814
/*      */     //   Java source line #519	-> byte code offset #3838
/*      */     //   Java source line #520	-> byte code offset #3847
/*      */     //   Java source line #521	-> byte code offset #3853
/*      */     //   Java source line #522	-> byte code offset #3859
/*      */     //   Java source line #519	-> byte code offset #3868
/*      */     //   Java source line #523	-> byte code offset #3869
/*      */     //   Java source line #524	-> byte code offset #3881
/*      */     //   Java source line #525	-> byte code offset #3885
/*      */     //   Java source line #526	-> byte code offset #3909
/*      */     //   Java source line #529	-> byte code offset #3913
/*      */     //   Java source line #530	-> byte code offset #3916
/*      */     //   Java source line #531	-> byte code offset #3919
/*      */     //   Java source line #532	-> byte code offset #3940
/*      */     //   Java source line #531	-> byte code offset #3949
/*      */     //   Java source line #533	-> byte code offset #3951
/*      */     //   Java source line #534	-> byte code offset #3956
/*      */     //   Java source line #535	-> byte code offset #3980
/*      */     //   Java source line #537	-> byte code offset #3988
/*      */     //   Java source line #538	-> byte code offset #3996
/*      */     //   Java source line #539	-> byte code offset #4009
/*      */     //   Java source line #540	-> byte code offset #4017
/*      */     //   Java source line #544	-> byte code offset #4027
/*      */     //   Java source line #546	-> byte code offset #4035
/*      */     //   Java source line #547	-> byte code offset #4043
/*      */     //   Java source line #549	-> byte code offset #4056
/*      */     //   Java source line #552	-> byte code offset #4066
/*      */     //   Java source line #553	-> byte code offset #4080
/*      */     //   Java source line #555	-> byte code offset #4085
/*      */     //   Java source line #556	-> byte code offset #4103
/*      */     //   Java source line #557	-> byte code offset #4118
/*      */     //   Java source line #558	-> byte code offset #4128
/*      */     //   Java source line #560	-> byte code offset #4138
/*      */     //   Java source line #562	-> byte code offset #4152
/*      */     //   Java source line #563	-> byte code offset #4173
/*      */     //   Java source line #564	-> byte code offset #4194
/*      */     //   Java source line #565	-> byte code offset #4215
/*      */     //   Java source line #566	-> byte code offset #4236
/*      */     //   Java source line #568	-> byte code offset #4253
/*      */     //   Java source line #571	-> byte code offset #4267
/*      */     //   Java source line #572	-> byte code offset #4277
/*      */     //   Java source line #573	-> byte code offset #4283
/*      */     //   Java source line #574	-> byte code offset #4302
/*      */     //   Java source line #575	-> byte code offset #4315
/*      */     //   Java source line #577	-> byte code offset #4325
/*      */     //   Java source line #578	-> byte code offset #4350
/*      */     //   Java source line #579	-> byte code offset #4406
/*      */     //   Java source line #581	-> byte code offset #4413
/*      */     //   Java source line #585	-> byte code offset #4417
/*      */     //   Java source line #586	-> byte code offset #4425
/*      */     //   Java source line #591	-> byte code offset #4428
/*      */     //   Java source line #593	-> byte code offset #4438
/*      */     //   Java source line #594	-> byte code offset #4441
/*      */     //   Java source line #595	-> byte code offset #4449
/*      */     //   Java source line #597	-> byte code offset #4455
/*      */     //   Java source line #598	-> byte code offset #4474
/*      */     //   Java source line #599	-> byte code offset #4484
/*      */     //   Java source line #600	-> byte code offset #4500
/*      */     //   Java source line #602	-> byte code offset #4510
/*      */     //   Java source line #603	-> byte code offset #4526
/*      */     //   Java source line #605	-> byte code offset #4536
/*      */     //   Java source line #607	-> byte code offset #4544
/*      */     //   Java source line #608	-> byte code offset #4555
/*      */     //   Java source line #609	-> byte code offset #4567
/*      */     //   Java source line #610	-> byte code offset #4580
/*      */     //   Java source line #608	-> byte code offset #4590
/*      */     //   Java source line #610	-> byte code offset #4593
/*      */     //   Java source line #611	-> byte code offset #4596
/*      */     //   Java source line #595	-> byte code offset #4603
/*      */     //   Java source line #614	-> byte code offset #4619
/*      */     //   Java source line #617	-> byte code offset #4624
/*      */     //   Java source line #618	-> byte code offset #4642
/*      */     //   Java source line #619	-> byte code offset #4652
/*      */     //   Java source line #620	-> byte code offset #4662
/*      */     //   Java source line #621	-> byte code offset #4672
/*      */     //   Java source line #622	-> byte code offset #4682
/*      */     //   Java source line #623	-> byte code offset #4690
/*      */     //   Java source line #624	-> byte code offset #4700
/*      */     //   Java source line #625	-> byte code offset #4710
/*      */     //   Java source line #626	-> byte code offset #4718
/*      */     //   Java source line #628	-> byte code offset #4721
/*      */     //   Java source line #629	-> byte code offset #4732
/*      */     //   Java source line #630	-> byte code offset #4742
/*      */     //   Java source line #631	-> byte code offset #4750
/*      */     //   Java source line #633	-> byte code offset #4753
/*      */     //   Java source line #634	-> byte code offset #4763
/*      */     //   Java source line #635	-> byte code offset #4773
/*      */     //   Java source line #638	-> byte code offset #4783
/*      */     //   Java source line #639	-> byte code offset #4791
/*      */     //   Java source line #640	-> byte code offset #4799
/*      */     //   Java source line #642	-> byte code offset #4807
/*      */     //   Java source line #643	-> byte code offset #4815
/*      */     //   Java source line #644	-> byte code offset #4818
/*      */     //   Java source line #646	-> byte code offset #4824
/*      */     //   Java source line #647	-> byte code offset #4834
/*      */     //   Java source line #648	-> byte code offset #4847
/*      */     //   Java source line #650	-> byte code offset #4860
/*      */     //   Java source line #651	-> byte code offset #4867
/*      */     //   Java source line #644	-> byte code offset #4877
/*      */     //   Java source line #654	-> byte code offset #4893
/*      */     //   Java source line #656	-> byte code offset #4898
/*      */     //   Java source line #657	-> byte code offset #4909
/*      */     //   Java source line #658	-> byte code offset #4917
/*      */     //   Java source line #660	-> byte code offset #4930
/*      */     //   Java source line #661	-> byte code offset #4940
/*      */     //   Java source line #662	-> byte code offset #4950
/*      */     //   Java source line #664	-> byte code offset #4960
/*      */     //   Java source line #665	-> byte code offset #4971
/*      */     //   Java source line #666	-> byte code offset #4984
/*      */     //   Java source line #667	-> byte code offset #4995
/*      */     //   Java source line #668	-> byte code offset #5011
/*      */     //   Java source line #671	-> byte code offset #5015
/*      */     //   Java source line #672	-> byte code offset #5023
/*      */     //   Java source line #675	-> byte code offset #5033
/*      */     //   Java source line #676	-> byte code offset #5039
/*      */     //   Java source line #534	-> byte code offset #5043
/*      */     //   Java source line #818	-> byte code offset #5053
/*      */     //   Java source line #819	-> byte code offset #5062
/*      */     //   Java source line #820	-> byte code offset #5068
/*      */     //   Java source line #821	-> byte code offset #5074
/*      */     //   Java source line #818	-> byte code offset #5083
/*      */     //   Java source line #822	-> byte code offset #5084
/*      */     //   Java source line #823	-> byte code offset #5096
/*      */     //   Java source line #824	-> byte code offset #5100
/*      */     //   Java source line #826	-> byte code offset #5124
/*      */     //   Java source line #830	-> byte code offset #5128
/*      */     //   Java source line #831	-> byte code offset #5131
/*      */     //   Java source line #834	-> byte code offset #5134
/*      */     //   Java source line #835	-> byte code offset #5144
/*      */     //   Java source line #836	-> byte code offset #5150
/*      */     //   Java source line #837	-> byte code offset #5156
/*      */     //   Java source line #838	-> byte code offset #5166
/*      */     //   Java source line #834	-> byte code offset #5172
/*      */     //   Java source line #847	-> byte code offset #5173
/*      */     //   Java source line #848	-> byte code offset #5186
/*      */     //   Java source line #850	-> byte code offset #5195
/*      */     //   Java source line #851	-> byte code offset #5198
/*      */     //   Java source line #852	-> byte code offset #5201
/*      */     //   Java source line #853	-> byte code offset #5204
/*      */     //   Java source line #855	-> byte code offset #5209
/*      */     //   Java source line #856	-> byte code offset #5212
/*      */     //   Java source line #857	-> byte code offset #5215
/*      */     //   Java source line #859	-> byte code offset #5218
/*      */     //   Java source line #861	-> byte code offset #5221
/*      */     //   Java source line #863	-> byte code offset #5240
/*      */     //   Java source line #864	-> byte code offset #5247
/*      */     //   Java source line #865	-> byte code offset #5252
/*      */     //   Java source line #867	-> byte code offset #5257
/*      */     //   Java source line #868	-> byte code offset #5267
/*      */     //   Java source line #869	-> byte code offset #5277
/*      */     //   Java source line #870	-> byte code offset #5287
/*      */     //   Java source line #872	-> byte code offset #5297
/*      */     //   Java source line #874	-> byte code offset #5302
/*      */     //   Java source line #876	-> byte code offset #5319
/*      */     //   Java source line #877	-> byte code offset #5328
/*      */     //   Java source line #878	-> byte code offset #5340
/*      */     //   Java source line #879	-> byte code offset #5379
/*      */     //   Java source line #886	-> byte code offset #5419
/*      */     //   Java source line #887	-> byte code offset #5424
/*      */     //   Java source line #889	-> byte code offset #5431
/*      */     //   Java source line #890	-> byte code offset #5438
/*      */     //   Java source line #891	-> byte code offset #5445
/*      */     //   Java source line #892	-> byte code offset #5452
/*      */     //   Java source line #893	-> byte code offset #5459
/*      */     //   Java source line #894	-> byte code offset #5464
/*      */     //   Java source line #897	-> byte code offset #5469
/*      */     //   Java source line #898	-> byte code offset #5487
/*      */     //   Java source line #899	-> byte code offset #5502
/*      */     //   Java source line #900	-> byte code offset #5512
/*      */     //   Java source line #901	-> byte code offset #5522
/*      */     //   Java source line #902	-> byte code offset #5530
/*      */     //   Java source line #904	-> byte code offset #5540
/*      */     //   Java source line #905	-> byte code offset #5551
/*      */     //   Java source line #907	-> byte code offset #5567
/*      */     //   Java source line #908	-> byte code offset #5575
/*      */     //   Java source line #910	-> byte code offset #5585
/*      */     //   Java source line #911	-> byte code offset #5595
/*      */     //   Java source line #912	-> byte code offset #5605
/*      */     //   Java source line #913	-> byte code offset #5613
/*      */     //   Java source line #915	-> byte code offset #5623
/*      */     //   Java source line #916	-> byte code offset #5633
/*      */     //   Java source line #918	-> byte code offset #5643
/*      */     //   Java source line #919	-> byte code offset #5651
/*      */     //   Java source line #920	-> byte code offset #5661
/*      */     //   Java source line #921	-> byte code offset #5671
/*      */     //   Java source line #922	-> byte code offset #5681
/*      */     //   Java source line #923	-> byte code offset #5691
/*      */     //   Java source line #924	-> byte code offset #5699
/*      */     //   Java source line #926	-> byte code offset #5709
/*      */     //   Java source line #927	-> byte code offset #5717
/*      */     //   Java source line #928	-> byte code offset #5727
/*      */     //   Java source line #929	-> byte code offset #5735
/*      */     //   Java source line #931	-> byte code offset #5744
/*      */     //   Java source line #932	-> byte code offset #5752
/*      */     //   Java source line #933	-> byte code offset #5762
/*      */     //   Java source line #934	-> byte code offset #5770
/*      */     //   Java source line #935	-> byte code offset #5780
/*      */     //   Java source line #936	-> byte code offset #5788
/*      */     //   Java source line #937	-> byte code offset #5798
/*      */     //   Java source line #938	-> byte code offset #5806
/*      */     //   Java source line #940	-> byte code offset #5816
/*      */     //   Java source line #941	-> byte code offset #5824
/*      */     //   Java source line #942	-> byte code offset #5834
/*      */     //   Java source line #943	-> byte code offset #5842
/*      */     //   Java source line #946	-> byte code offset #5852
/*      */     //   Java source line #947	-> byte code offset #5860
/*      */     //   Java source line #949	-> byte code offset #5870
/*      */     //   Java source line #951	-> byte code offset #5875
/*      */     //   Java source line #953	-> byte code offset #5893
/*      */     //   Java source line #954	-> byte code offset #5907
/*      */     //   Java source line #955	-> byte code offset #5920
/*      */     //   Java source line #956	-> byte code offset #5933
/*      */     //   Java source line #957	-> byte code offset #5946
/*      */     //   Java source line #958	-> byte code offset #5956
/*      */     //   Java source line #960	-> byte code offset #5966
/*      */     //   Java source line #961	-> byte code offset #5972
/*      */     //   Java source line #962	-> byte code offset #5975
/*      */     //   Java source line #963	-> byte code offset #5976
/*      */     //   Java source line #965	-> byte code offset #6003
/*      */     //   Java source line #967	-> byte code offset #6006
/*      */     //   Java source line #969	-> byte code offset #6033
/*      */     //   Java source line #970	-> byte code offset #6036
/*      */     //   Java source line #972	-> byte code offset #6040
/*      */     //   Java source line #974	-> byte code offset #6050
/*      */     //   Java source line #975	-> byte code offset #6061
/*      */     //   Java source line #977	-> byte code offset #6068
/*      */     //   Java source line #978	-> byte code offset #6071
/*      */     //   Java source line #979	-> byte code offset #6079
/*      */     //   Java source line #981	-> byte code offset #6090
/*      */     //   Java source line #982	-> byte code offset #6098
/*      */     //   Java source line #984	-> byte code offset #6108
/*      */     //   Java source line #985	-> byte code offset #6118
/*      */     //   Java source line #987	-> byte code offset #6123
/*      */     //   Java source line #988	-> byte code offset #6137
/*      */     //   Java source line #991	-> byte code offset #6148
/*      */     //   Java source line #994	-> byte code offset #6158
/*      */     //   Java source line #995	-> byte code offset #6166
/*      */     //   Java source line #998	-> byte code offset #6179
/*      */     //   Java source line #999	-> byte code offset #6185
/*      */     //   Java source line #1001	-> byte code offset #6195
/*      */     //   Java source line #1002	-> byte code offset #6203
/*      */     //   Java source line #1004	-> byte code offset #6213
/*      */     //   Java source line #1005	-> byte code offset #6221
/*      */     //   Java source line #1007	-> byte code offset #6231
/*      */     //   Java source line #1009	-> byte code offset #6249
/*      */     //   Java source line #1010	-> byte code offset #6254
/*      */     //   Java source line #1011	-> byte code offset #6264
/*      */     //   Java source line #1012	-> byte code offset #6270
/*      */     //   Java source line #1014	-> byte code offset #6276
/*      */     //   Java source line #1015	-> byte code offset #6284
/*      */     //   Java source line #859	-> byte code offset #6287
/*      */     //   Java source line #1017	-> byte code offset #6297
/*      */     //   Java source line #1020	-> byte code offset #6302
/*      */     //   Java source line #1022	-> byte code offset #6319
/*      */     //   Java source line #1023	-> byte code offset #6328
/*      */     //   Java source line #1024	-> byte code offset #6340
/*      */     //   Java source line #1025	-> byte code offset #6379
/*      */     //   Java source line #1029	-> byte code offset #6419
/*      */     //   Java source line #1030	-> byte code offset #6427
/*      */     //   Java source line #1032	-> byte code offset #6437
/*      */     //   Java source line #1033	-> byte code offset #6443
/*      */     //   Java source line #1034	-> byte code offset #6446
/*      */     //   Java source line #1037	-> byte code offset #6447
/*      */     //   Java source line #1038	-> byte code offset #6452
/*      */     //   Java source line #1040	-> byte code offset #6456
/*      */     //   Java source line #1043	-> byte code offset #6463
/*      */     //   Java source line #1044	-> byte code offset #6466
/*      */     //   Java source line #1046	-> byte code offset #6468
/*      */     //   Java source line #1050	-> byte code offset #6500
/*      */     //   Java source line #1051	-> byte code offset #6507
/*      */     //   Java source line #1052	-> byte code offset #6510
/*      */     //   Java source line #1049	-> byte code offset #6516
/*      */     //   Java source line #1050	-> byte code offset #6518
/*      */     //   Java source line #1051	-> byte code offset #6525
/*      */     //   Java source line #1052	-> byte code offset #6528
/*      */     //   Java source line #1053	-> byte code offset #6531
/*      */     //   Java source line #1050	-> byte code offset #6534
/*      */     //   Java source line #1051	-> byte code offset #6541
/*      */     //   Java source line #1052	-> byte code offset #6544
/*      */     //   Java source line #1056	-> byte code offset #6547
/*      */     //   Java source line #1057	-> byte code offset #6556
/*      */     //   Java source line #1058	-> byte code offset #6562
/*      */     //   Java source line #1056	-> byte code offset #6572
/*      */     //   Java source line #1059	-> byte code offset #6573
/*      */     //   Java source line #1060	-> byte code offset #6585
/*      */     //   Java source line #1062	-> byte code offset #6602
/*      */     //   Java source line #1063	-> byte code offset #6620
/*      */     //   Java source line #1064	-> byte code offset #6638
/*      */     //   Java source line #1065	-> byte code offset #6666
/*      */     // Local variable table:
/*      */     //   start	length	slot	name	signature
/*      */     //   0	6672	0	this	ImportOrder
/*      */     //   1	6573	1	sql	StringBuilder
/*      */     //   3	6590	2	no	int
/*      */     //   20	6549	3	clientCheck	StringBuilder
/*      */     //   3914	2632	4	pstmt	java.sql.PreparedStatement
/*      */     //   3917	2626	5	rs	java.sql.ResultSet
/*      */     //   3949	8	6	implist	List<org.compiere.model.X_I_Order>
/*      */     //   3978	1056	7	imp	org.compiere.model.X_I_Order
/*      */     //   5129	1520	7	noInsert	int
/*      */     //   3963	1081	8	localIterator	java.util.Iterator
/*      */     //   5132	1528	8	noInsertLine	int
/*      */     //   4078	825	9	bp	org.compiere.model.MBPartner
/*      */     //   5196	241	9	oldC_BPartner_ID	int
/*      */     //   6466	30	9	e	Exception
/*      */     //   6664	3	9	msgreturn	StringBuilder
/*      */     //   4300	3	10	setBPsalesRep	boolean
/*      */     //   4439	337	10	bpl	org.compiere.model.MBPartnerLocation
/*      */     //   5199	252	10	oldBillTo_ID	int
/*      */     //   4404	5	11	BPGroup	org.compiere.model.MBPGroup
/*      */     //   4447	167	11	bpls	org.compiere.model.MBPartnerLocation[]
/*      */     //   5202	242	11	oldC_BPartner_Location_ID	int
/*      */     //   4450	162	12	i	int
/*      */     //   4640	95	12	loc	org.compiere.model.MLocation
/*      */     //   4813	75	12	users	org.compiere.model.MUser[]
/*      */     //   5207	261	12	oldDocumentNo	String
/*      */     //   4553	3	13	loc	org.compiere.model.MLocation
/*      */     //   4816	210	13	user	org.compiere.model.MUser
/*      */     //   5210	1248	13	order	MOrder
/*      */     //   4819	67	14	i	int
/*      */     //   5213	1225	14	fiscal	com.ghintech.puntocom.model.M_C_Invoice_Fiscal
/*      */     //   4832	16	15	name	String
/*      */     //   5216	853	15	lineNo	int
/*      */     //   5238	1039	16	imp	org.compiere.model.X_I_Order
/*      */     //   5245	45	17	cmpDocumentNo	String
/*      */     //   6059	198	18	line	org.compiere.model.MOrderLine
/*      */     //   6516	16	19	localObject	Object
/*      */     //   4416	1	36	localException1	Exception
/*      */     //   5014	1	37	localException2	Exception
/*      */     //   5975	1	38	localException3	Exception
/*      */     //   6446	1	39	localException4	Exception
/*      */     // Exception table:
/*      */     //   from	to	target	type
/*      */     //   4325	4413	4416	java/lang/Exception
/*      */     //   4960	5011	5014	java/lang/Exception
/*      */     //   5966	5972	5975	java/lang/Exception
/*      */     //   6437	6443	6446	java/lang/Exception
/*      */     //   5173	6463	6466	java/lang/Exception
/*      */     //   5173	6500	6516	finally
/*      */   }
/*      */   
/*      */   private String createAllocation(MOrder order)
/*      */   {
/* 1071 */     int count = 0;
/*      */     
/* 1073 */     if (order.getPaymentRule().compareTo("P") == 0)
/*      */     {
/* 1075 */       while ((order.getC_Invoice_ID() == 0) && (count < 5)) {
/*      */         try {
/* 1077 */           Thread.sleep(2000L);
/* 1078 */           count++;
/*      */         }
/*      */         catch (InterruptedException e) {
/* 1081 */           e.printStackTrace();
/*      */         }
/*      */       }
/* 1084 */       boolean complete = false;
/* 1085 */       this.log.warning("Verifique que ya existe el Numero de factura" + order.getC_Invoice_ID());
/* 1086 */       count = 0;
/* 1087 */       while ((!complete) && (count < 5)) {
/* 1088 */         MInvoice tempinv = new MInvoice(getCtx(), order.getC_Invoice_ID(), get_TrxName());
/* 1089 */         if ((tempinv != null) && 
/* 1090 */           (tempinv.getDocStatus().compareTo("CO") == 0)) {
/* 1091 */           complete = true;
/*      */         }
/*      */         
/* 1094 */         System.out.println(tempinv.getDocStatus());
/*      */         try {
/* 1096 */           Thread.sleep(2000L);
/* 1097 */           count++;
/*      */         }
/*      */         catch (InterruptedException e) {
/* 1100 */           e.printStackTrace();
/*      */         }
/*      */       }
/*      */       
/* 1104 */       MInvoice tempinv = new MInvoice(getCtx(), order.getC_Invoice_ID(), get_TrxName());
/* 1105 */       if ((tempinv != null) && 
/* 1106 */         (tempinv.getDocStatus().compareTo("CO") != 0)) {
/* 1107 */         this.log.severe("Luego de 10 intentos la factura no estaba completada. Error");
/* 1108 */         return "Luego de 10 intentos la factura no estaba completada. Error";
/*      */       }
/*      */       
/*      */ 
/* 1112 */       this.log.warning("La factura esta completada");
/* 1113 */       MAllocationHdr Allocation = new MAllocationHdr(getCtx(), Integer.parseInt(order.getDescription()), get_TrxName());
/* 1114 */       List<MAllocationLine> querya = null;
/* 1115 */       BigDecimal totalAllocated = BigDecimal.ZERO;
/* 1116 */       querya = new Query(Env.getCtx(), "C_AllocationLine", "C_AllocationHdr_ID = ? ", 
/* 1117 */         get_TrxName())
/* 1118 */         .setParameters(new Object[] {Integer.valueOf(Allocation.getC_AllocationHdr_ID()) })
/* 1119 */         .list();
/* 1120 */       for (MAllocationLine AllocationLine : querya) {
/* 1121 */         totalAllocated = totalAllocated.add(AllocationLine.getAmount());
/* 1122 */         System.out.println("totalAllocated = " + totalAllocated);
/*      */       }
/* 1124 */       MAllocationLine AllocationLine = new MAllocationLine(Allocation);
/* 1125 */       AllocationLine.setAD_Org_ID(order.getAD_Org_ID());
/* 1126 */       AllocationLine.setC_Order_ID(order.getC_Order_ID());
/* 1127 */       AllocationLine.setC_Invoice_ID(order.getC_Invoice_ID());
/* 1128 */       AllocationLine.setAmount(totalAllocated.negate());
/* 1129 */       AllocationLine.setC_BPartner_ID(order.getC_BPartner_ID());
/* 1130 */       AllocationLine.saveEx();
/* 1131 */       Allocation.setDocAction("CO");
/* 1132 */       if (!Allocation.processIt("CO")) {
/* 1133 */         this.log.severe("Allocation Process Failed: " + order + " - " + Allocation.getProcessMsg());
/* 1134 */         throw new IllegalStateException("Allocation Process Failed: " + Allocation + " - " + Allocation.getProcessMsg());
/*      */       }
/* 1136 */       Allocation.saveEx();
/*      */       
/*      */ 
/* 1139 */       String whereClause = "AD_Org_ID=? AND C_Currency_ID=?";
/* 1140 */       MBankAccount ba = 
/*      */       
/*      */ 
/* 1143 */         (MBankAccount)new Query(getCtx(), "C_BankAccount", whereClause, get_TrxName()).setParameters(new Object[] {Integer.valueOf(order.getAD_Org_ID()), Integer.valueOf(order.getC_Currency_ID()) }).setOrderBy("IsDefault DESC").first();
/* 1144 */       if (totalAllocated.setScale(2, RoundingMode.CEILING).abs().compareTo(order.getGrandTotal().setScale(2, RoundingMode.CEILING).abs()) != 0) {
/* 1145 */         MPayment Payment = new MPayment(getCtx(), 0, get_TrxName());
/* 1146 */         Payment.setAD_Org_ID(order.getAD_Org_ID());
/* 1147 */         Payment.setC_BPartner_ID(order.getC_BPartner_ID());
/* 1148 */         Payment.setC_BankAccount_ID(ba.getC_BankAccount_ID());
/* 1149 */         Payment.setC_Currency_ID(order.getC_Currency_ID());
/* 1150 */         Payment.setDescription("PAGO POR LA DIFERENCIA DE NOTAS DE CREDITO ASIGNADAS = " + totalAllocated + " VS TOTAL ORDEN = " + order.getGrandTotal());
/* 1151 */         Payment.setC_DocType_ID(true);
/* 1152 */         Payment.setTenderType("X");
/*      */         
/* 1154 */         Payment.setPayAmt(order.getGrandTotal().add(totalAllocated));
/* 1155 */         Payment.setC_Invoice_ID(order.getC_Invoice_ID());
/*      */         
/* 1157 */         Payment.saveEx();
/*      */         
/* 1159 */         Payment.setDocAction("CO");
/* 1160 */         if (!Payment.processIt("CO")) {
/* 1161 */           return "Cannot Complete the Payment :" + Payment;
/*      */         }
/* 1163 */         Payment.saveEx();
/*      */ 
/*      */       }
/* 1166 */       else if (Allocation.getDocStatus() == "CO") {
/* 1167 */         MInvoice invoice = new MInvoice(getCtx(), order.getC_Invoice_ID(), get_TrxName());
/* 1168 */         invoice.setIsPaid(true);
/* 1169 */         invoice.saveEx();
/*      */       }
/*      */     }
/*      */     
/*      */ 
/* 1174 */     return "Payment Ok";
/*      */   }
/*      */ }


/* Location:              /home/james/Desktop/POSIntegration/!/ImportOrder.class
 * Java compiler version: 6 (50.0)
 * JD-Core Version:       0.7.1
 */